Workbook

Sheet ReadMe
A1: (last update: 10/08/2026)
A2: M. Arias-Osorio, R. Moshrif, G. Nievas, T. Piketty, A. Van Der Ree "Global Inequality Update 2026: Insights from the WID Macro Series", WIL TN, 2026
A4: Content
A5: Tables
A6: 1 | B6: ='T1'!A1 -> Table 1. Gross domestic product by World Region USD-EUR (2025)
A7: 2 | B7: =T1a!A1 -> Table 1a. Per capita gross domestic product by World Region USD-EUR (2025)
A8: 3 | B8: ='T2'!A1 -> Table 2. Consumption of Fixed Capital by World Region USD-EUR (2025)
A9: 4 | B9: ='T3'!A1 -> Table 3. National Income by World Region USD-EUR (2025)
A10: 5 | B10: ='T4'!A1 -> Table 4. Per Capita National Income by World Region (2025)
A11: 6 | B11: =T4a!A1 -> Table 4a. Per capita national Income by World Region USD-EUR (2025)
B12: =DataT3c!B3 -> Table 3c. National Income by World Region (2021): New PPP (ICP 2021) vs Old PPP (ICP 2011)
A13: 7 | B13: =T5a!A1 -> Table 5a. Per Capita National Income Growth PPP 2025 € by World Regions (1800-2025)
A14: 8 | B14: =T5b!A1 -> Table 5b. Per Capita National Income Growth PPP 2025 $ by World Regions (1800-2025)
A15: 9 | B15: =T5c!A1 -> Table 5c. Per Capita National Income Growth MER 2025 € by World Regions (1800-2025)
A16: 10 | B16: =T5d!A1 -> Table 5d. Per Capita National Income Growth MER 2025 $ by World Regions (1800-2025)
A17: 11 | B17: ='T6'!A1 -> Table 6. Per Capita National Income Growth PPP 2025 € by WID core Territories (1980-2025)
A18: 12 | B18: ='T7'!A1 -> Table 7. Population by World Regions (1800-2025)
A19: 13 | B19: =T8a!A1 -> Table 8a. Price index Growth PPP 2025 € by World Regions (1980-2025)
A20: 14 | B20: =T8b!A1 -> Table 8b. Price index Growth PPP 2025 $ by World Regions (1980-2025)
A21: 15 | B21: =T8c!A1 -> Table 8c. Price index Growth MER € by World Regions (1980-2025)
A22: 16 | B22: =T8d!A1 -> Table 8d. Price index Growth MER $ by World Regions (1980-2025)
A23: 17 | B23: ='T9'!A1 -> Table 9. Price index Growth € by Core countries (1980-2025)
A24: 18 | B24: =T10a!A1 -> Table10a. Top 10 Richest Countries (2025),including countries with population below 10 million
A25: 19 | B25: =T10b!A1 -> Table10b. Top 10 Richest Countries (2025), excluding countries with population below 10 million
A26: 20 | B26: ='T11'!A1 -> Table 11. Bottom 10 Poorest Countries (2025)
A27: 21 | B27: ='T12'!A1 -> Table 12. Top 10 Largest Economies (2025)
A28: 22 | B28: =T13a!A1 -> Table 13a. Current Account by World Region PPP € (2025)
A29: 23 | B29: =T13b!A1 -> Table 13b. Current Account by World Region PPP $ (2025)
A30: 24 | B30: =T13c!A1 -> Table 13c. Current Account by World Region MER € (2025)
A31: 25 | B31: =T13d!A1 -> Table 13d. Current Account by World Region MER $ (2025)
A32: 26 | B32: =T14a!A1 -> Table 14a. Net foreign Assets PPP € 2025 by World Regions (1980-2025)
A33: 27 | B33: =T14b!A1 -> Table 14d. Net foreign Assets MER$ by World Regions (1980-2025)
A34: 28 | B34: =T14c!A1 -> Table 14c. Net foreign Assets MER € by World Regions (1980-2025)
A35: 29 | B35: =T14d!A1 -> Table 14d. Net foreign Assets MER$ by World Regions (1980-2025)
A36: 30 | B36: =T15a!A1 -> Table 15a. National Non-financial Assets by World Region PPP € (2025)
A37: 31 | B37: =T15b!A1 -> Table 15b. National Non-financial Assets by World Region PPP $ (2025)
A38: 32 | B38: =T15c!A1 -> Table 15c. National Non-financial Assets by World Region MER € (2025)
A39: 33 | B39: =T15d!A1 -> Table 15d. National Non-financial Assets by World Region MER $ (2025)
A40: 34 | B40: =T16a!A1 -> Table 16a. National Capital shares by World Region PPP € (2025)
A41: 35 | B41: =T16b!A1 -> Table 16b. National Capital shares by World Region PPP $ (2025)
A42: 36 | B42: =T16c!A1 -> Table 16c. National Capital shares by World Region MER € (2025)
A43: 37 | B43: =T16d!A1 -> Table 16d. National Capital shares by World Region MER $ (2025)
A44: 38 | B44: Appendix1
A45: Figures
A46: 1 | B46: Figure 0a. Exchange Rate and Purchasing Power Parity: Euro/Dollar
A47: 2 | B47: Figure 0b. Exchange Rate and Purchasing Power Parity: Euro/Yuan

Sheet F0a

Sheet F0b

Sheet T1
A1: =DataT1!B2 -> Table 1. Gross domestic product by World Region USD-EUR (2025)
B2: =DataT1!C3 -> PPP 2025 billions € | D2: =DataT1!E3 -> 2025 MER billions € | F2: =DataT1!G3 -> PPP 2025 billions $ | H2: =DataT1!I3 -> 2025 MER billions $
B3: =DataT1!C4 -> Gross domestic product | C3: =DataT1!D4 -> Gross domestic product (% world total) | D3: =DataT1!E4 -> Gross domestic product | E3: =DataT1!F4 -> Gross domestic product (% world total) | F3: =DataT1!G4 -> Gross domestic product | G3: =DataT1!H4 -> Gross domestic product (% world total) | H3: =DataT1!I4 -> Gross domestic product | I3: =DataT1!J4 -> Gross domestic product (% world total)
A4: =DataT1!B5 -> East Asia | B4: =DataT1!C5 -> 37298.113 | C4: =DataT1!D5/100 -> 0.26015704 | D4: =DataT1!E5 -> 23215.605 | E4: =DataT1!F5/100 -> 0.22605071 | F4: =DataT1!G5 -> 55011.574 | G4: =DataT1!H5/100 -> 0.26015705 | H4: =DataT1!I5 -> 27362.758 | I4: =DataT1!J5/100 -> 0.22605072
A5: =DataT1!B6 -> Europe | B5: =DataT1!C6 -> 24116.732 | C5: =DataT1!D6/100 -> 0.16821595 | D5: =DataT1!E6 -> 23800.626 | E5: =DataT1!F6/100 -> 0.23174707 | F5: =DataT1!G6 -> 35570.144 | G5: =DataT1!H6/100 -> 0.16821594 | H5: =DataT1!I6 -> 28052.286 | I5: =DataT1!J6/100 -> 0.23174709
A6: =DataT1!B7 -> Latin America | B6: =DataT1!C7 -> 10322.067 | C6: =DataT1!D7/100 -> 0.071997169 | D6: =DataT1!E7 -> 6496.2763 | E6: =DataT1!F7/100 -> 0.063254344 | F6: =DataT1!G7 -> 15224.179 | G6: =DataT1!H7/100 -> 0.071997166 | H6: =DataT1!I7 -> 7656.7479 | I6: =DataT1!J7/100 -> 0.063254346
A7: =DataT1!B8 -> MENA | B7: =DataT1!C8 -> 10670.033 | C7: =DataT1!D8/100 -> 0.074424253 | D7: =DataT1!E8 -> 5608.5037 | E7: =DataT1!F8/100 -> 0.054610088 | F7: =DataT1!G8 -> 15737.399 | G7: =DataT1!H8/100 -> 0.074424253 | H7: =DataT1!I8 -> 6610.3872 | I7: =DataT1!J8/100 -> 0.054610094
A8: =DataT1!B9 -> North America & Oceania | B8: =DataT1!C9 -> 24436.488 | C8: =DataT1!D9/100 -> 0.17044628 | D8: =DataT1!E9 -> 30016.639 | E8: =DataT1!F9/100 -> 0.29227249 | F8: =DataT1!G9 -> 36041.76 | G8: =DataT1!H9/100 -> 0.17044628 | H8: =DataT1!I9 -> 35378.704 | I8: =DataT1!J9/100 -> 0.29227249
A9: =DataT1!B10 -> Russia & Central Asia | B9: =DataT1!C10 -> 7011.3215 | C9: =DataT1!D10/100 -> 0.048904475 | D9: =DataT1!E10 -> 3149.6041 | E9: =DataT1!F10/100 -> 0.030667745 | F9: =DataT1!G10 -> 10341.108 | G9: =DataT1!H10/100 -> 0.048904474 | H9: =DataT1!I10 -> 3712.2382 | I9: =DataT1!J10/100 -> 0.030667746
A10: =DataT1!B11 -> South & South-East Asia | B10: =DataT1!C11 -> 23742.554 | C10: =DataT1!D11/100 -> 0.16560603 | D10: =DataT1!E11 -> 8057.2831 | E10: =DataT1!F11/100 -> 0.078453892 | F10: =DataT1!G11 -> 35018.265 | G10: =DataT1!H11/100 -> 0.16560603 | H10: =DataT1!I11 -> 9496.6075 | I10: =DataT1!J11/100 -> 0.078453896
A11: =DataT1!B12 -> Sub-Saharan Africa | B11: =DataT1!C12 -> 5298.7413 | C11: =DataT1!D12/100 -> 0.036959104 | D11: =DataT1!E12 -> 2356.3311 | E11: =DataT1!F12/100 -> 0.022943633 | F11: =DataT1!G12 -> 7815.1966 | G11: =DataT1!H12/100 -> 0.036959104 | H11: =DataT1!I12 -> 2777.2578 | I11: =DataT1!J12/100 -> 0.022943635
A12: =DataT1!B13 -> World | B12: =DataT1!C13 -> 143367.69 | C12: =DataT1!D13/100 -> 1 | D12: =DataT1!E13 -> 102700.87 | E12: =DataT1!F13/100 -> 1 | F12: =DataT1!G13 -> 211455.25 | G12: =DataT1!H13/100 -> 1 | H12: =DataT1!I13 -> 121046.98 | I12: =DataT1!J13/100 -> 1
A13: Interpretation. In 2025, gross domestic product amounts to 143 368€ (PPP) billion worldwide. Gross domestic product, varies from little more than 5 299€ billion in Subsaharan Africa to almost 24 436€ billion in North America/Oceania , i.e., an income scale of 1 to 5. Sources and series: wid.world

Sheet T1a
A1: =DataT1a!B2 -> Table 1a. Per capita gross domestic product by World Region USD-EUR (2025)
B2: =DataT1a!C3 -> PPP 2025 € | D2: =DataT1a!E3 -> 2025 MER € | F2: =DataT1a!G3 -> PPP 2025 $ | H2: =DataT1a!I3 -> 2025 MER $
B3: =DataT1a!C4 -> Per capita gross domestic product | C3: =DataT1a!D4 -> Per capita gross domestic product (% world total) | D3: =DataT1a!E4 -> Per capita gross domestic product | E3: =DataT1a!F4 -> Per capita gross domestic product (% world total) | F3: =DataT1a!G4 -> Per capita gross domestic product | G3: =DataT1a!H4 -> Per capita gross domestic product (% world total) | H3: =DataT1a!I4 -> Per capita gross domestic product | I3: =DataT1a!J4 -> Per capita gross domestic product (% world total)
A4: =DataT1a!B5 -> East Asia | B4: =DataT1a!C5 -> 22575.014 | C4: =DataT1a!D5/100 -> 1.2959992 | D4: =DataT1a!E5 -> 14051.451 | E4: =DataT1a!F5/100 -> 1.126095 | F4: =DataT1a!G5 -> 33296.243 | G4: =DataT1a!H5/100 -> 1.2959992 | H4: =DataT1a!I5 -> 16561.552 | I4: =DataT1a!J5/100 -> 1.126095
A5: =DataT1a!B6 -> Europe | B5: =DataT1a!C6 -> 43376.585 | C5: =DataT1a!D6/100 -> 2.4901876 | D5: =DataT1a!E6 -> 42808.035 | E5: =DataT1a!F6/100 -> 3.4306716 | F5: =DataT1a!G6 -> 63976.804 | G5: =DataT1a!H6/100 -> 2.4901875 | H5: =DataT1a!I6 -> 50455.111 | I5: =DataT1a!J6/100 -> 3.4306719
A6: =DataT1a!B7 -> Latin America | B6: =DataT1a!C7 -> 15481.475 | C6: =DataT1a!D7/100 -> 0.88876931 | D6: =DataT1a!E7 -> 9743.391 | E6: =DataT1a!F7/100 -> 0.78084347 | F6: =DataT1a!G7 -> 22833.869 | G6: =DataT1a!H7/100 -> 0.88876927 | H6: =DataT1a!I7 -> 11483.916 | I6: =DataT1a!J7/100 -> 0.7808435
A7: =DataT1a!B8 -> MENA | B7: =DataT1a!C8 -> 17428.241 | C7: =DataT1a!D8/100 -> 1.0005303 | D7: =DataT1a!E8 -> 9160.8296 | E7: =DataT1a!F8/100 -> 0.73415651 | F7: =DataT1a!G8 -> 25705.186 | G7: =DataT1a!H8/100 -> 1.0005303 | H7: =DataT1a!I8 -> 10797.288 | I7: =DataT1a!J8/100 -> 0.73415659
A8: =DataT1a!B9 -> North America & Oceania | B8: =DataT1a!C9 -> 56325.387 | C8: =DataT1a!D9/100 -> 3.2335598 | D8: =DataT1a!E9 -> 69187.47 | E8: =DataT1a!F9/100 -> 5.5447415 | F8: =DataT1a!G9 -> 83075.197 | G8: =DataT1a!H9/100 -> 3.2335598 | H8: =DataT1a!I9 -> 81546.871 | I8: =DataT1a!J9/100 -> 5.5447416
A9: =DataT1a!B10 -> Russia & Central Asia | B9: =DataT1a!C10 -> 23951.503 | C9: =DataT1a!D10/100 -> 1.3750215 | D9: =DataT1a!E10 -> 10759.42 | E9: =DataT1a!F10/100 -> 0.86226888 | F9: =DataT1a!G10 -> 35326.446 | G9: =DataT1a!H10/100 -> 1.3750214 | H9: =DataT1a!I10 -> 12681.445 | I9: =DataT1a!J10/100 -> 0.86226893
A10: =DataT1a!B11 -> South & South-East Asia | B10: =DataT1a!C11 -> 8816.9793 | C10: =DataT1a!D11/100 -> 0.50617015 | D10: =DataT1a!E11 -> 2992.1339 | E10: =DataT1a!F11/100 -> 0.2397921 | F10: =DataT1a!G11 -> 13004.301 | G10: =DataT1a!H11/100 -> 0.50617016 | H10: =DataT1a!I11 -> 3526.638 | I10: =DataT1a!J11/100 -> 0.23979212 | K10: =B8/B11 -> 14.074092
A11: =DataT1a!B12 -> Sub-Saharan Africa | B11: =DataT1a!C12 -> 4002.0618 | C11: =DataT1a!D12/100 -> 0.22975263 | D11: =DataT1a!E12 -> 1779.7024 | E11: =DataT1a!F12/100 -> 0.14262684 | F11: =DataT1a!G12 -> 5902.7037 | G11: =DataT1a!H12/100 -> 0.22975264 | H11: =DataT1a!I12 -> 2097.6222 | I11: =DataT1a!J12/100 -> 0.14262685
A12: =DataT1a!B13 -> World | B12: =DataT1a!C13 -> 17419.003 | C12: =DataT1a!D13/100 -> 1 | D12: =DataT1a!E13 -> 12478.033 | E12: =DataT1a!F13/100 -> 1 | F12: =DataT1a!G13 -> 25691.561 | G12: =DataT1a!H13/100 -> 1 | H12: =DataT1a!I13 -> 14707.064 | I12: =DataT1a!J13/100 -> 1
A13: Interpretation. In 2025, per capita gross domestic product amounts to 17 419€ (PPP) worldwide, i.e., 1 452€ per month. Per capita gross domestic product, i.e., the part of the product which all individuals would receive with a perfectly egalitarian distribution, varies from an average of little more than 4 002€ in Subsaharan Africa (about 333€ per month) to over 56 325€ in North America/Oceania (about 4 693€ per month), i.e., an income scale of 1 to 14. Sources and series: wid.world

Sheet T2
A1: =DataT2!B2 -> Table 2. Consumption of Fixed Capital by World Region USD-EUR (2025)
B2: =DataT2!C3 -> PPP 2025 billions € | E2: =DataT2!F3 -> 2025 MER billions € | H2: =DataT2!I3 -> PPP 2025 billions $ | K2: =DataT2!L3 -> 2025 MER billions $
B3: =DataT2!C4 -> Consumption of Fixed Capital | C3: =DataT2!D4 -> Consumption of Fixed Capital (% regional GDP) | D3: =DataT2!E4 -> Consumption of Fixed Capital (% world Consumption of Fixed capital total) | E3: =DataT2!F4 -> Consumption of Fixed Capital | F3: =DataT2!G4 -> Consumption of Fixed Capital (% regional GDP) | G3: =DataT2!H4 -> Consumption of Fixed Capital (% world Consumption of Fixed capital total) | H3: =DataT2!I4 -> Consumption of Fixed Capital | I3: =DataT2!J4 -> Consumption of Fixed Capital (% regional GDP) | ... M3: =DataT2!N4 -> Consumption of Fixed Capital (% world Consumption of Fixed capital total)
A4: =DataT2!B5 -> East Asia | B4: =DataT2!C5 -> 7030.8739 | C4: =DataT2!D5 -> 0.18850481 | D4: =DataT2!E5 -> 0.32014003 | E4: =DataT2!F5 -> 4453.0428 | F4: =DataT2!G5 -> 0.19181248 | G4: =DataT2!H5 -> 0.26679831 | H4: =DataT2!I5 -> 10369.947 | ... M4: =DataT2!N5 -> 0.2667983
A5: =DataT2!B6 -> Europe | B5: =DataT2!C6 -> 4134.191 | C5: =DataT2!D6 -> 0.17142418 | D5: =DataT2!E6 -> 0.18824403 | E5: =DataT2!F6 -> 4127.6796 | F5: =DataT2!G6 -> 0.17342735 | G5: =DataT2!H6 -> 0.2473046 | H5: =DataT2!I6 -> 6097.583 | ... M5: =DataT2!N6 -> 0.24730459
A6: =DataT2!B7 -> Latin America | B6: =DataT2!C7 -> 1322.6018 | C6: =DataT2!D7 -> 0.12813341 | D6: =DataT2!E7 -> 0.060222636 | E6: =DataT2!F7 -> 842.22538 | F6: =DataT2!G7 -> 0.12964741 | G6: =DataT2!H7 -> 0.050460847 | H6: =DataT2!I7 -> 1950.726 | ... M6: =DataT2!N7 -> 0.050460846
A7: =DataT2!B8 -> MENA | B7: =DataT2!C8 -> 1172.9157 | C7: =DataT2!D8 -> 0.10992616 | D7: =DataT2!E8 -> 0.053406913 | E7: =DataT2!F8 -> 645.51663 | F7: =DataT2!G8 -> 0.11509605 | G7: =DataT2!H8 -> 0.038675296 | H7: =DataT2!I8 -> 1729.9518 | ... M7: =DataT2!N8 -> 0.038675296
A8: =DataT2!B9 -> North America & Oceania | B8: =DataT2!C9 -> 4061.7377 | C8: =DataT2!D9 -> 0.16621609 | D8: =DataT2!E9 -> 0.18494498 | E8: =DataT2!F9 -> 4998.6314 | F8: =DataT2!G9 -> 0.16652868 | G8: =DataT2!H9 -> 0.29948655 | H8: =DataT2!I9 -> 5990.7205 | ... M8: =DataT2!N9 -> 0.29948654
A9: =DataT2!B10 -> Russia & Central Asia | B9: =DataT2!C10 -> 966.72875 | C9: =DataT2!D10 -> 0.1378811 | D9: =DataT2!E10 -> 0.044018507 | E9: =DataT2!F10 -> 431.07341 | F9: =DataT2!G10 -> 0.1368659 | G9: =DataT2!H10 -> 0.025827207 | H9: =DataT2!I10 -> 1425.8434 | ... M9: =DataT2!N10 -> 0.025827208
A10: =DataT2!B11 -> South & South-East Asia | B10: =DataT2!C11 -> 2755.6008 | C10: =DataT2!D11 -> 0.11606169 | D10: =DataT2!E11 -> 0.12547204 | E10: =DataT2!F11 -> 962.99039 | F10: =DataT2!G11 -> 0.119518 | G10: =DataT2!H11 -> 0.057696326 | H10: =DataT2!I11 -> 4064.2788 | ... M10: =DataT2!N11 -> 0.057696324
A11: =DataT2!B12 -> Sub-Saharan Africa | B11: =DataT2!C12 -> 517.22055 | C11: =DataT2!D12 -> 0.097611966 | D11: =DataT2!E12 -> 0.023550842 | E11: =DataT2!F12 -> 229.51139 | F11: =DataT2!G12 -> 0.097402013 | G11: =DataT2!H12 -> 0.013750879 | H11: =DataT2!I12 -> 762.8567 | ... M11: =DataT2!N12 -> 0.013750879
A12: =DataT2!B13 -> World | B12: =DataT2!C13 -> 21961.87 | C12: =DataT2!D13 -> 0.15369123 | D12: =DataT2!E13 -> 0.99999998 | E12: =DataT2!F13 -> 16690.671 | F12: =DataT2!G13 -> 0.16251733 | G12: =DataT2!H13 -> 1 | H12: =DataT2!I13 -> 32391.907 | ... M12: =DataT2!N13 -> 0.99999999
A13: Interpretation. In 2025, consumption of fixed capital amounts to €21,962 billion (2025 PPP) worldwide, equivalent to slightly more than 15% of global GDP. East Asia accounts for the largest share of global consumption of fixed capital, representing 32% in € and 27% in $, equivalent to approximately 19% of the region’s GDP. By contrast, Sub-Saharan Africa accounts for less than 2% of global consumption of fixed capital in both currencies, corresponding to approximately 10% of the region’s GDP. The relative position of regions varies depending on whether values are expressed using PPP or MER. For instance, Europe’s share of global consumption of fixed capital increases from 19% in PPP terms to 25% in MER terms. Similarly, North America and Oceania increase their share from 18% to 30% when moving from PPP to MER terms. This reflects, in part, the relatively strong currencies of these regions compared with those of other regions. Sources and series: wid.world

Sheet T3
A1: =DataT3!B2 -> Table 3. National Income by World Region USD-EUR (2025)
B2: =DataT3!C3 -> PPP 2025 billions € | D2: =DataT3!E3 -> 2025 MER billions € | F2: =DataT3!G3 -> PPP 2025 billions $ | H2: =DataT3!I3 -> 2025 MER billions $
B3: =DataT3!C4 -> National income | C3: =DataT3!D4 -> National income (% world total) | D3: =DataT3!E4 -> National income | E3: =DataT3!F4 -> National income (% world total) | F3: =DataT3!G4 -> National income | G3: =DataT3!H4 -> National income (% world total) | H3: =DataT3!I4 -> National income | I3: =DataT3!J4 -> National income (% world total)
A4: =DataT3!B5 -> East Asia | B4: =DataT3!C5 -> 30310.742 | C4: =DataT3!D5/100 -> 0.25244657 | D4: =DataT3!E5 -> 18893.618 | E4: =DataT3!F5/100 -> 0.2196672 | F4: =DataT3!G5 -> 44705.789 | G4: =DataT3!H5/100 -> 0.25244656 | H4: =DataT3!I5 -> 22268.707 | I4: =DataT3!J5/100 -> 0.2196672
A5: =DataT3!B6 -> Europe | B5: =DataT3!C6 -> 20201.059 | C5: =DataT3!D6/100 -> 0.16824689 | D5: =DataT3!E6 -> 19982.903 | E5: =DataT3!F6/100 -> 0.2323318 | F5: =DataT3!G6 -> 29794.859 | G5: =DataT3!H6/100 -> 0.16824688 | H5: =DataT3!I6 -> 23552.579 | I5: =DataT3!J6/100 -> 0.23233181
A6: =DataT3!B7 -> Latin America | B6: =DataT3!C7 -> 8669.1455 | C6: =DataT3!D7/100 -> 0.072201995 | D6: =DataT3!E7 -> 5460.5569 | E6: =DataT3!F7/100 -> 0.063487323 | F6: =DataT3!G7 -> 12786.258 | G6: =DataT3!H7/100 -> 0.072201991 | H6: =DataT3!I7 -> 6436.0114 | I6: =DataT3!J7/100 -> 0.063487322
A7: =DataT3!B8 -> MENA | B7: =DataT3!C8 -> 9423.3006 | C7: =DataT3!D8/100 -> 0.078483064 | D7: =DataT3!E8 -> 4949.6985 | E7: =DataT3!F8/100 -> 0.057547813 | F7: =DataT3!G8 -> 13898.574 | G7: =DataT3!H8/100 -> 0.078483061 | H7: =DataT3!I8 -> 5833.8953 | I7: =DataT3!J8/100 -> 0.057547814
A8: =DataT3!B9 -> North America & Oceania | B8: =DataT3!C9 -> 20396.536 | C8: =DataT3!D9/100 -> 0.16987494 | D8: =DataT3!E9 -> 25039.377 | E8: =DataT3!F9/100 -> 0.29112104 | F8: =DataT3!G9 -> 30083.169 | G8: =DataT3!H9/100 -> 0.16987493 | H8: =DataT3!I9 -> 29512.321 | I8: =DataT3!J9/100 -> 0.29112103
A9: =DataT3!B10 -> Russia & Central Asia | B9: =DataT3!C10 -> 5964.8477 | C9: =DataT3!D10/100 -> 0.049678934 | D9: =DataT3!E10 -> 2684.9708 | E9: =DataT3!F10/100 -> 0.031216891 | F9: =DataT3!G10 -> 8797.6471 | G9: =DataT3!H10/100 -> 0.04967893 | H9: =DataT3!I10 -> 3164.6047 | I9: =DataT3!J10/100 -> 0.031216892
A10: =DataT3!B11 -> South & South-East Asia | B10: =DataT3!C11 -> 20456.394 | C10: =DataT3!D11/100 -> 0.17037347 | D10: =DataT3!E11 -> 6950.256 | E10: =DataT3!F11/100 -> 0.080807352 | F10: =DataT3!G11 -> 30171.455 | G10: =DataT3!H11/100 -> 0.17037346 | H10: =DataT3!I11 -> 8191.825 | I10: =DataT3!J11/100 -> 0.08080735
A11: =DataT3!B12 -> Sub-Saharan Africa | B11: =DataT3!C12 -> 4645.9292 | C11: =DataT3!D12/100 -> 0.038694166 | D11: =DataT3!E12 -> 2048.8171 | E11: =DataT3!F12/100 -> 0.023820632 | F11: =DataT3!G12 -> 6852.354 | G11: =DataT3!H12/100 -> 0.038694166 | H11: =DataT3!I12 -> 2414.8106 | I11: =DataT3!J12/100 -> 0.023820632
A12: =DataT3!B13 -> World | B12: =DataT3!C13 -> 120067.95 | C12: =DataT3!D13/100 -> 1 | D12: =DataT3!E13 -> 86010.193 | E12: =DataT3!F13/100 -> 1 | F12: =DataT3!G13 -> 177090.11 | G12: =DataT3!H13/100 -> 1 | H12: =DataT3!I13 -> 101374.75 | I12: =DataT3!J13/100 -> 1
A13: Interpretation. In 2025, national income amounts to 120 068€ (PPP) billion worldwide. National Income, varies from an average of little more than 4 646 billion € in Subsaharan Africa to over 20 397 € billion in North America/Oceania , i.e., an income scale of 1 to 4. Sources and series: wid.world

Sheet T4
A1: ='DataT4-'!B3 -> Table 4. Per Capita National Income by World Region (2025)
B2: ='DataT4-'!C4 -> Population (millions) | C2: ='DataT4-'!D4 -> Population (% world total) | D2: ='DataT4-'!E4 -> National income (PPP 2025 billions €) | E2: ='DataT4-'!F4 -> National income (% world total) | F2: ='DataT4-'!G4 -> Per capita national income (PPP 2025 €) | G2: ='DataT4-'!H4 -> Per capita national income (% world average)
A3: ='DataT4-'!B5 -> East Asia | B3: ='DataT4-'!C5 -> 1652.1856 | C3: ='DataT4-'!D5/100 -> 0.20073858 | D3: ='DataT4-'!E5 -> 30310.742 | E3: ='DataT4-'!F5/100 -> 0.25244657 | F3: ='DataT4-'!G5 -> 18345.845 | G3: ='DataT4-'!H5/100 -> 1.2575887
A4: ='DataT4-'!B6 -> Europe | B4: ='DataT4-'!C6 -> 555.98502 | C4: ='DataT4-'!D6/100 -> 0.067551516 | D4: ='DataT4-'!E6 -> 20201.059 | E4: ='DataT4-'!F6/100 -> 0.16824689 | F4: ='DataT4-'!G6 -> 36333.82 | G4: ='DataT4-'!H6/100 -> 2.4906457
A5: ='DataT4-'!B7 -> Latin America | B5: ='DataT4-'!C7 -> 666.73669 | C5: ='DataT4-'!D7/100 -> 0.081007713 | D5: ='DataT4-'!E7 -> 8669.1455 | E5: ='DataT4-'!F7/100 -> 0.072201995 | F5: ='DataT4-'!G7 -> 13002.353 | G5: ='DataT4-'!H7/100 -> 0.89129779
A6: ='DataT4-'!B8 -> MENA | B6: ='DataT4-'!C8 -> 612.22662 | C6: ='DataT4-'!D8/100 -> 0.074384804 | D6: ='DataT4-'!E8 -> 9423.3006 | E6: ='DataT4-'!F8/100 -> 0.078483064 | F6: ='DataT4-'!G8 -> 15391.851 | G6: ='DataT4-'!H8/100 -> 1.0550954
A7: ='DataT4-'!B9 -> North America & Oceania | B7: ='DataT4-'!C9 -> 433.84502 | C7: ='DataT4-'!D9/100 -> 0.052711652 | D7: ='DataT4-'!E9 -> 20396.536 | E7: ='DataT4-'!F9/100 -> 0.16987494 | F7: ='DataT4-'!G9 -> 47013.414 | G7: ='DataT4-'!H9/100 -> 3.2227208
A8: ='DataT4-'!B10 -> Russia & Central Asia | B8: ='DataT4-'!C10 -> 292.72992 | C8: ='DataT4-'!D10/100 -> 0.035566336 | D8: ='DataT4-'!E10 -> 5964.8477 | E8: ='DataT4-'!F10/100 -> 0.049678934 | F8: ='DataT4-'!G10 -> 20376.625 | G8: ='DataT4-'!H10/100 -> 1.3967965
A9: ='DataT4-'!B11 -> South & South-East Asia | B9: ='DataT4-'!C11 -> 2692.8217 | C9: ='DataT4-'!D11/100 -> 0.32717463 | D9: ='DataT4-'!E11 -> 20456.394 | E9: ='DataT4-'!F11/100 -> 0.17037347 | F9: ='DataT4-'!G11 -> 7596.6386 | G9: ='DataT4-'!H11/100 -> 0.5207417
A10: ='DataT4-'!B12 -> Sub-Saharan Africa | B10: ='DataT4-'!C12 -> 1324.0029 | C10: ='DataT4-'!D12/100 -> 0.16086477 | D10: ='DataT4-'!E12 -> 4645.9292 | E10: ='DataT4-'!F12/100 -> 0.038694166 | F10: ='DataT4-'!G12 -> 3509.0024 | G10: ='DataT4-'!H12/100 -> 0.24053848
A11: ='DataT4-'!B13 -> World | B11: ='DataT4-'!C13 -> 8230.5335 | C11: ='DataT4-'!D13/100 -> 1 | D11: ='DataT4-'!E13 -> 120067.95 | E11: ='DataT4-'!F13/100 -> 1 | F11: ='DataT4-'!G13 -> 14588.113 | G11: ='DataT4-'!H13/100 -> 1
A12: Interpretation. In 2025, per capita national income amounts to a little more than 14 588€ (PPP) worldwide, i.e., 1 216€ per month. Per capita national income, i.e., the income which all individuals would receive with a perfectly egalitarian distribution, varies from an average of little more than 3509€ in Subsaharan Africa (about 292€ per month) to over 47 013€ in North America/Oceania (about 3 917€ per month), i.e., an income scale of 1 to 13. Sources and series: wid.world

Sheet T4a
A1: =DataT4a!B2 -> Table 4a. Per capita national Income by World Region USD-EUR (2025)
B2: =DataT4a!C3 -> PPP 2025 € | D2: =DataT4a!E3 -> 2025 MER € | F2: =DataT4a!G3 -> PPP 2025 $ | H2: =DataT4a!I3 -> 2025 MER $
B3: =DataT4a!C4 -> Per capita national income | C3: =DataT4a!D4 -> Per capita national income (% world total) | D3: =DataT4a!E4 -> Per capita national income | E3: =DataT4a!F4 -> Per capita national income (% world total) | F3: =DataT4a!G4 -> Per capita national income | G3: =DataT4a!H4 -> Per capita national income (% world total) | H3: =DataT4a!I4 -> Per capita national income | I3: =DataT4a!J4 -> Per capita national income (% world total)
A4: =DataT4a!B5 -> East Asia | B4: =DataT4a!C5 -> 18345.845 | C4: =DataT4a!D5/100 -> 1.2575887 | D4: =DataT4a!E5 -> 11435.53 | E4: =DataT4a!F5/100 -> 1.0942949 | F4: =DataT4a!G5 -> 27058.576 | G4: =DataT4a!H5/100 -> 1.2575887 | H4: =DataT4a!I5 -> 13478.333 | I4: =DataT4a!J5/100 -> 1.0942948 | K4: =B4/12 -> 1528.8205
A5: =DataT4a!B6 -> Europe | B5: =DataT4a!C6 -> 36333.82 | C5: =DataT4a!D6/100 -> 2.4906457 | D5: =DataT4a!E6 -> 35941.442 | E5: =DataT4a!F6/100 -> 3.4393277 | F5: =DataT4a!G6 -> 53589.32 | G5: =DataT4a!H6/100 -> 2.4906456 | H5: =DataT4a!I6 -> 42361.895 | I5: =DataT4a!J6/100 -> 3.4393278 | K5: =B5/12 -> 3027.8183
A6: =DataT4a!B7 -> Latin America | B6: =DataT4a!C7 -> 13002.353 | C6: =DataT4a!D7/100 -> 0.89129779 | D6: =DataT4a!E7 -> 8189.9751 | E6: =DataT4a!F7/100 -> 0.78371949 | F6: =DataT4a!G7 -> 19177.373 | G6: =DataT4a!H7/100 -> 0.89129774 | H6: =DataT4a!I7 -> 9653.0032 | I6: =DataT4a!J7/100 -> 0.78371947 | K6: =B6/12 -> 1083.5294
A7: =DataT4a!B8 -> MENA | B7: =DataT4a!C8 -> 15391.851 | C7: =DataT4a!D8/100 -> 1.0550954 | D7: =DataT4a!E8 -> 8084.7489 | E7: =DataT4a!F8/100 -> 0.77365012 | F7: =DataT4a!G8 -> 22701.682 | G7: =DataT4a!H8/100 -> 1.0550954 | H7: =DataT4a!I8 -> 9528.9802 | I7: =DataT4a!J8/100 -> 0.77365014 | K7: =B7/12 -> 1282.6542
A8: =DataT4a!B9 -> North America & Oceania | B8: =DataT4a!C9 -> 47013.414 | C8: =DataT4a!D9/100 -> 3.2227208 | D8: =DataT4a!E9 -> 57715.027 | E8: =DataT4a!F9/100 -> 5.5228973 | F8: =DataT4a!G9 -> 69340.819 | G8: =DataT4a!H9/100 -> 3.2227206 | H8: =DataT4a!I9 -> 68025.032 | I8: =DataT4a!J9/100 -> 5.522897 | K8: =B8/12 -> 3917.7845
A9: =DataT4a!B10 -> Russia & Central Asia | B9: =DataT4a!C10 -> 20376.625 | C9: =DataT4a!D10/100 -> 1.3967965 | D9: =DataT4a!E10 -> 9172.1777 | E9: =DataT4a!F10/100 -> 0.87770895 | F9: =DataT4a!G10 -> 30053.802 | G9: =DataT4a!H10/100 -> 1.3967964 | H9: =DataT4a!I10 -> 10810.664 | I9: =DataT4a!J10/100 -> 0.87770897 | K9: =B9/12 -> 1698.0521
A10: =DataT4a!B11 -> South & South-East Asia | B10: =DataT4a!C11 -> 7596.6386 | C10: =DataT4a!D11/100 -> 0.5207417 | D10: =DataT4a!E11 -> 2581.0309 | E10: =DataT4a!F11/100 -> 0.24698539 | F10: =DataT4a!G11 -> 11204.401 | G10: =DataT4a!H11/100 -> 0.52074168 | H10: =DataT4a!I11 -> 3042.097 | I10: =DataT4a!J11/100 -> 0.24698538 | K10: =B10/12 -> 633.05322
A11: =DataT4a!B12 -> Sub-Saharan Africa | B11: =DataT4a!C12 -> 3509.0024 | C11: =DataT4a!D12/100 -> 0.24053848 | D11: =DataT4a!E12 -> 1547.4416 | E11: =DataT4a!F12/100 -> 0.14807861 | F11: =DataT4a!G12 -> 5175.4827 | G11: =DataT4a!H12/100 -> 0.24053847 | H11: =DataT4a!I12 -> 1823.8711 | I11: =DataT4a!J12/100 -> 0.14807861 | K11: =B11/12 -> 292.41687
A12: =DataT4a!B13 -> World | B12: =DataT4a!C13 -> 14588.113 | C12: =DataT4a!D13/100 -> 1 | D12: =DataT4a!E13 -> 10450.136 | E12: =DataT4a!F13/100 -> 1 | F12: =DataT4a!G13 -> 21516.237 | G12: =DataT4a!H13/100 -> 1 | H12: =DataT4a!I13 -> 12316.911 | I12: =DataT4a!J13/100 -> 1 | K12: =B12/12 -> 1215.6761
A13: Interpretation. In 2025, per capita national income amounts to 14 588€ (PPP) worldwide, i.e., 1 216€ per month. Per capita national income, i.e., theincome which all individuals would receive with a perfectly egalitarian distribution, varies from an average of little more than 3 509€ in Subsaharan Africa (about 292€ per month) to over 47 013€ in North America/Oceania (about 3917€ per month), i.e., an income scale of 1 to 13. Sources and series: wid.world

Sheet T5a
A1: =DataT5a!B3 -> Table 5a. Per Capita National Income Growth PPP 2025 € by World Regions (1800-2025)
B2: =DataT5a!C4 -> 1800 Per capita national income (PPP 2025 €) | C2: =DataT5a!D4 -> 1980 Per capita national income (PPP 2025 €) | D2: =DataT5a!E4 -> 2000 Per capita national income (PPP 2025 €) | E2: =DataT5a!F4 -> 2020 Per capita national income (PPP 2025 €) | F2: =DataT5a!G4 -> 2025 Per capita national income (PPP 2025 €) | G2: =DataT5a!H4 -> Annual growth rate 1800-2025 | H2: =DataT5a!I4 -> Annual growth rate 1980-2025 | I2: =DataT5a!J4 -> Annual growth rate 1980-2000 | ... K2: =DataT5a!L4 -> Annual growth rate 2020-2025
A3: =DataT5a!B5 -> East Asia | B3: =DataT5a!C5 -> 756.87952 | C3: =DataT5a!D5 -> 3203.624 | D3: =DataT5a!E5 -> 5852.9658 | E3: =DataT5a!F5 -> 14669.656 | F3: =DataT5a!G5 -> 18345.846 | G3: =DataT5a!H5 -> 1.4269538 | H3: =DataT5a!I5 -> 3.9542232 | ... K3: =DataT5a!L5 -> 4.5739617
A4: =DataT5a!B6 -> Europe | B4: =DataT5a!C6 -> 1516.1448 | C4: =DataT5a!D6 -> 18521.828 | D4: =DataT5a!E6 -> 26905.697 | E4: =DataT5a!F6 -> 31373.441 | F4: =DataT5a!G6 -> 36333.82 | G4: =DataT5a!H6 -> 1.4218256 | H4: =DataT5a!I6 -> 1.5085975 | ... K4: =DataT5a!L6 -> 2.9792633
A5: =DataT5a!B7 -> Latin America | B5: =DataT5a!C7 -> 770.73651 | C5: =DataT5a!D7 -> 9067.3467 | D5: =DataT5a!E7 -> 9728.6865 | E5: =DataT5a!F7 -> 11199.896 | F5: =DataT5a!G7 -> 13002.353 | G5: =DataT5a!H7 -> 1.2637134 | H5: =DataT5a!I7 -> 0.80421788 | ... K5: =DataT5a!L7 -> 3.0295007
A6: =DataT5a!B8 -> MENA | B6: =DataT5a!C8 -> 696.99304 | C6: =DataT5a!D8 -> 10019.868 | D6: =DataT5a!E8 -> 9918.3545 | E6: =DataT5a!F8 -> 13260.667 | F6: =DataT5a!G8 -> 15391.851 | G6: =DataT5a!H8 -> 1.3849778 | H6: =DataT5a!I8 -> 0.95849383 | ... K6: =DataT5a!L8 -> 3.0255859
A7: =DataT5a!B9 -> North America & Oceania | B7: =DataT5a!C9 -> 1351.0249 | C7: =DataT5a!D9 -> 23183.15 | D7: =DataT5a!E9 -> 35849.449 | E7: =DataT5a!F9 -> 41591.25 | F7: =DataT5a!G9 -> 47013.414 | G7: =DataT5a!H9 -> 1.590096 | H7: =DataT5a!I9 -> 1.5835344 | ... K7: =DataT5a!L9 -> 2.4811435
A8: =DataT5a!B10 -> Russia & Central Asia | B8: =DataT5a!C10 -> 749.38873 | C8: =DataT5a!D10 -> 11946.08 | D8: =DataT5a!E10 -> 10243.371 | E8: =DataT5a!F10 -> 17544.988 | F8: =DataT5a!G10 -> 20376.625 | G8: =DataT5a!H10 -> 1.4787766 | H8: =DataT5a!I10 -> 1.1937023 | ... K8: =DataT5a!L10 -> 3.0376236
A9: =DataT5a!B11 -> South & South-East Asia | B9: =DataT5a!C11 -> 833.79749 | C9: =DataT5a!D11 -> 1616.8258 | D9: =DataT5a!E11 -> 2820.2151 | E9: =DataT5a!F11 -> 5935.7754 | F9: =DataT5a!G11 -> 7596.6387 | G9: =DataT5a!H11 -> 0.98682427 | H9: =DataT5a!I11 -> 3.4981067 | ... K9: =DataT5a!L11 -> 5.0579214
A10: =DataT5a!B12 -> Sub-Saharan Africa | B10: =DataT5a!C12 -> 505.86182 | C10: =DataT5a!D12 -> 2422.375 | D10: =DataT5a!E12 -> 2135.561 | E10: =DataT5a!F12 -> 3225.896 | F10: =DataT5a!G12 -> 3509.0024 | G10: =DataT5a!H12 -> 0.86452609 | H10: =DataT5a!I12 -> 0.82691872 | ... K10: =DataT5a!L12 -> 1.6966536
A11: =DataT5a!B13 -> World | B11: =DataT5a!C13 -> 730.17249 | C11: =DataT5a!D13 -> 7915.1694 | D11: =DataT5a!E13 -> 10036.208 | E11: =DataT5a!F13 -> 12714.921 | F11: =DataT5a!G13 -> 14588.112 | G11: =DataT5a!H13 -> 1.3398664 | H11: =DataT5a!I13 -> 1.3679968 | ... K11: =DataT5a!L13 -> 2.7867393
A12: Interpretation. Between 1800 and 2025, the real growth rate of per capita national income expressed in PPP 2025 € at the global level has been 1.3% per year. Since 1980 we observed almost doubling of average income, with an acceleration in the growth after 2000: 1.5% per year over 2000-2025 and 2.8% over 2020-2025. Sources and series: wid.world

Sheet T5b
A1: =DataT5b!B3 -> Table 5b. Per Capita National Income Growth PPP 2025 $ by World Regions (1800-2025)
B2: =DataT5b!C4 -> 1800 Per capita national income (PPP 2025 $) | C2: =DataT5b!D4 -> 1980 Per capita national income (PPP 2025 $) | D2: =DataT5b!E4 -> 2000 Per capita national income (PPP 2025 $) | E2: =DataT5b!F4 -> 2020 Per capita national income (PPP 2025 $) | F2: =DataT5b!G4 -> 2025 Per capita national income (PPP 2025 $) | G2: =DataT5b!H4 -> Annual growth rate 1800-2025 | H2: =DataT5b!I4 -> Annual growth rate 1980-2025 | I2: =DataT5b!J4 -> Annual growth rate 1980-2000 | ... K2: =DataT5b!L4 -> Annual growth rate 2020-2025
A3: =DataT5b!B5 -> East Asia | B3: =DataT5b!C5 -> 1116.3335 | C3: =DataT5b!D5 -> 4725.0757 | D3: =DataT5b!E5 -> 8632.6309 | E3: =DataT5b!F5 -> 21636.506 | F3: =DataT5b!G5 -> 27058.576 | G3: =DataT5b!H5 -> 1.4269538 | H3: =DataT5b!I5 -> 3.9542232 | ... K3: =DataT5b!L5 -> 4.5739622
A4: =DataT5b!B6 -> Europe | B4: =DataT5b!C6 -> 2236.1858 | C4: =DataT5b!D6 -> 27318.133 | D4: =DataT5b!E6 -> 39683.637 | E4: =DataT5b!F6 -> 46273.18 | F4: =DataT5b!G6 -> 53589.32 | G4: =DataT5b!H6 -> 1.4218256 | H4: =DataT5b!I6 -> 1.5085975 | ... K4: =DataT5b!L6 -> 2.9792635
A5: =DataT5b!B7 -> Latin America | B5: =DataT5b!C7 -> 1136.7714 | C5: =DataT5b!D7 -> 13373.572 | D5: =DataT5b!E7 -> 14348.992 | E5: =DataT5b!F7 -> 16518.9 | F5: =DataT5b!G7 -> 19177.373 | G5: =DataT5b!H7 -> 1.2637134 | H5: =DataT5b!I7 -> 0.80421788 | ... K5: =DataT5b!L7 -> 3.0295017
A6: =DataT5b!B8 -> MENA | B6: =DataT5b!C8 -> 1028.006 | C6: =DataT5b!D8 -> 14778.461 | D6: =DataT5b!E8 -> 14628.737 | E6: =DataT5b!F8 -> 19558.365 | F6: =DataT5b!G8 -> 22701.682 | G6: =DataT5b!H8 -> 1.3849778 | H6: =DataT5b!I8 -> 0.95849377 | ... K6: =DataT5b!L8 -> 3.0255859
A7: =DataT5b!B9 -> North America & Oceania | B7: =DataT5b!C9 -> 1992.6476 | C7: =DataT5b!D9 -> 34193.191 | D7: =DataT5b!E9 -> 52874.918 | E7: =DataT5b!F9 -> 61343.59 | F7: =DataT5b!G9 -> 69340.82 | G7: =DataT5b!H9 -> 1.590096 | H7: =DataT5b!I9 -> 1.5835344 | ... K7: =DataT5b!L9 -> 2.4811425
A8: =DataT5b!B10 -> Russia & Central Asia | B8: =DataT5b!C10 -> 1105.2852 | C8: =DataT5b!D10 -> 17619.461 | D8: =DataT5b!E10 -> 15108.108 | E8: =DataT5b!F10 -> 25877.379 | F8: =DataT5b!G10 -> 30053.803 | G8: =DataT5b!H10 -> 1.4787766 | H8: =DataT5b!I10 -> 1.1937022 | ... K8: =DataT5b!L10 -> 3.0376227
A9: =DataT5b!B11 -> South & South-East Asia | B9: =DataT5b!C11 -> 1229.781 | C9: =DataT5b!D11 -> 2384.6816 | D9: =DataT5b!E11 -> 4159.5796 | E9: =DataT5b!F11 -> 8754.7686 | F9: =DataT5b!G11 -> 11204.401 | G9: =DataT5b!H11 -> 0.98682421 | H9: =DataT5b!I11 -> 3.4981067 | ... K9: =DataT5b!L11 -> 5.0579205
A10: =DataT5b!B12 -> Sub-Saharan Africa | B10: =DataT5b!C12 -> 746.10358 | C10: =DataT5b!D12 -> 3572.7988 | D10: =DataT5b!E12 -> 3149.7725 | E10: =DataT5b!F12 -> 4757.9248 | F10: =DataT5b!G12 -> 5175.4829 | G10: =DataT5b!H12 -> 0.86452609 | H10: =DataT5b!I12 -> 0.82691878 | ... K10: =DataT5b!L12 -> 1.6966534
A11: =DataT5b!B13 -> World | B11: =DataT5b!C13 -> 1076.9429 | C11: =DataT5b!D13 -> 11674.208 | D11: =DataT5b!E13 -> 14802.561 | E11: =DataT5b!F13 -> 18753.436 | F11: =DataT5b!G13 -> 21516.236 | G11: =DataT5b!H13 -> 1.3398664 | H11: =DataT5b!I13 -> 1.3679968 | ... K11: =DataT5b!L13 -> 2.7867401
A12: Interpretation. Between 1800 and 2025, the real growth rate of per capita national income expressed in PPP 2025 $ at the global level has been 1.3% per year. Since 1980 we observed almost doubling of average income, with an acceleration in the growth after 2000: 1.5% per year over 2000-2025 and 2.8% over 2020-2025. Sources and series: wid.world

Sheet T5c
A1: =DataT5c!B3 -> Table 5c. Per Capita National Income Growth MER 2025 € by World Regions (1800-2025)
B2: =DataT5c!C4 -> 1800 Per capita national income (MER €) | C2: =DataT5c!D4 -> 1980 Per capita national income (MER €) | D2: =DataT5c!E4 -> 2000 Per capita national income (MER €) | E2: =DataT5c!F4 -> 2020 Per capita national income (MER €) | F2: =DataT5c!G4 -> 2025 Per capita national income (MER €) | G2: =DataT5c!H4 -> Annual growth rate 1800-2025 | H2: =DataT5c!I4 -> Annual growth rate 1980-2025 | I2: =DataT5c!J4 -> Annual growth rate 1980-2000 | ... K2: =DataT5c!L4 -> Annual growth rate 2020-2025
A3: =DataT5c!B5 -> East Asia | B3: =DataT5c!C5 -> 461.95917 | C3: =DataT5c!D5 -> 2053.4666 | D3: =DataT5c!E5 -> 3870.8618 | E3: =DataT5c!F5 -> 9194.4082 | F3: =DataT5c!G5 -> 11435.53 | G3: =DataT5c!H5 -> 1.4364431 | H3: =DataT5c!I5 -> 3.8897347 | ... K3: =DataT5c!L5 -> 4.4591532
A4: =DataT5c!B6 -> Europe | B4: =DataT5c!C6 -> 1511.7633 | C4: =DataT5c!D6 -> 18245.855 | D4: =DataT5c!E6 -> 26990.402 | E4: =DataT5c!F6 -> 31119.236 | F4: =DataT5c!G6 -> 35941.441 | G4: =DataT5c!H6 -> 1.4182359 | H4: =DataT5c!I6 -> 1.5179682 | ... K4: =DataT5c!L6 -> 2.9232075
A5: =DataT5c!B7 -> Latin America | B5: =DataT5c!C7 -> 509.2695 | C5: =DataT5c!D7 -> 5863.7632 | D5: =DataT5c!E7 -> 6267.3989 | E5: =DataT5c!F7 -> 7080.0942 | F5: =DataT5c!G7 -> 8189.9751 | G5: =DataT5c!H7 -> 1.2421801 | H5: =DataT5c!I7 -> 0.74525058 | ... K5: =DataT5c!L7 -> 2.9553001
A6: =DataT5c!B8 -> MENA | B6: =DataT5c!C8 -> 364.85007 | C6: =DataT5c!D8 -> 5337.6904 | D6: =DataT5c!E8 -> 5180.8804 | E6: =DataT5c!F8 -> 6948.0586 | F6: =DataT5c!G8 -> 8084.749 | G6: =DataT5c!H8 -> 1.3865235 | H6: =DataT5c!I8 -> 0.92690587 | ... K6: =DataT5c!L8 -> 3.076725
A7: =DataT5c!B9 -> North America & Oceania | B7: =DataT5c!C9 -> 1650.8887 | C7: =DataT5c!D9 -> 28446.799 | D7: =DataT5c!E9 -> 44061.113 | E7: =DataT5c!F9 -> 51057.941 | F7: =DataT5c!G9 -> 57715.027 | G7: =DataT5c!H9 -> 1.5921885 | H7: =DataT5c!I9 -> 1.5846059 | ... K7: =DataT5c!L9 -> 2.481416
A8: =DataT5c!B10 -> Russia & Central Asia | B8: =DataT5c!C10 -> 335.36237 | C8: =DataT5c!D10 -> 5265.4941 | D8: =DataT5c!E10 -> 4644.585 | E8: =DataT5c!F10 -> 7884.3892 | F8: =DataT5c!G10 -> 9172.1777 | G8: =DataT5c!H10 -> 1.4814072 | H8: =DataT5c!I10 -> 1.2409698 | ... K8: =DataT5c!L10 -> 3.0720422
A9: =DataT5c!B11 -> South & South-East Asia | B9: =DataT5c!C11 -> 268.45117 | C9: =DataT5c!D11 -> 561.28772 | D9: =DataT5c!E11 -> 990.20026 | E9: =DataT5c!F11 -> 2038.0701 | F9: =DataT5c!G11 -> 2581.0308 | G9: =DataT5c!H11 -> 1.0109762 | H9: =DataT5c!I11 -> 3.4485993 | ... K9: =DataT5c!L11 -> 4.8370557
A10: =DataT5c!B12 -> Sub-Saharan Africa | B10: =DataT5c!C12 -> 241.07956 | C10: =DataT5c!D12 -> 1107.356 | D10: =DataT5c!E12 -> 1175.5726 | E10: =DataT5c!F12 -> 1484.6976 | F10: =DataT5c!G12 -> 1547.4417 | G10: =DataT5c!H12 -> 0.82974851 | H10: =DataT5c!I12 -> 0.74638915 | ... K10: =DataT5c!L12 -> 0.83127367
A11: =DataT5c!B13 -> World | B11: =DataT5c!C13 -> 523.05615 | C11: =DataT5c!D13 -> 5670.0005 | D11: =DataT5c!E13 -> 7189.3979 | E11: =DataT5c!F13 -> 9108.2822 | F11: =DataT5c!G13 -> 10450.136 | G11: =DataT5c!H13 -> 1.3398664 | H11: =DataT5c!I13 -> 1.3679967 | ... K11: =DataT5c!L13 -> 2.7867393
A12: Interpretation. Between 1800 and 2025, the real growth rate of per capita national income expressed in MER € at the global level has been 1.3% per year. Since 1980 we observed almost doubling of average income, with an acceleration in the growth after 2000: 1.5% per year over 2000-2025 and 2.8% over 2020-2025. Sources and series: wid.world

Sheet T5d
A1: =DataT5d!B3 -> Table 5d. Per Capita National Income Growth MER 2025 $ by World Regions (1800-2025)
B2: =DataT5d!C4 -> 1800 Per capita national income (MER $) | C2: =DataT5d!D4 -> 1980 Per capita national income (MER $) | D2: =DataT5d!E4 -> 2000 Per capita national income (MER $) | E2: =DataT5d!F4 -> 2020 Per capita national income (MER $) | F2: =DataT5d!G4 -> 2025 Per capita national income (MER $) | G2: =DataT5d!H4 -> Annual growth rate 1800-2025 | H2: =DataT5d!I4 -> Annual growth rate 1980-2025 | I2: =DataT5d!J4 -> Annual growth rate 1980-2000 | ... K2: =DataT5d!L4 -> Annual growth rate 2020-2025
A3: =DataT5d!B5 -> East Asia | B3: =DataT5d!C5 -> 544.48193 | C3: =DataT5d!D5 -> 2420.2905 | D3: =DataT5d!E5 -> 4562.3389 | E3: =DataT5d!F5 -> 10836.865 | F3: =DataT5d!G5 -> 13478.333 | G3: =DataT5d!H5 -> 1.4364431 | H3: =DataT5d!I5 -> 3.8897347 | ... K3: =DataT5d!L5 -> 4.4591532
A4: =DataT5d!B6 -> Europe | B4: =DataT5d!C6 -> 1781.8195 | C4: =DataT5d!D6 -> 21505.23 | D4: =DataT5d!E6 -> 31811.871 | E4: =DataT5d!F6 -> 36678.27 | F4: =DataT5d!G6 -> 42361.895 | G4: =DataT5d!H6 -> 1.4182359 | H4: =DataT5d!I6 -> 1.5179682 | ... K4: =DataT5d!L6 -> 2.9232073
A5: =DataT5d!B7 -> Latin America | B5: =DataT5d!C7 -> 600.24359 | C5: =DataT5d!D7 -> 6911.2451 | D5: =DataT5d!E7 -> 7386.9854 | E5: =DataT5d!F7 -> 8344.8574 | F5: =DataT5d!G7 -> 9653.0029 | G5: =DataT5d!H7 -> 1.2421801 | H5: =DataT5d!I7 -> 0.74525058 | ... K5: =DataT5d!L7 -> 2.9552999
A6: =DataT5d!B8 -> MENA | B6: =DataT5d!C8 -> 430.0256 | C6: =DataT5d!D8 -> 6291.1963 | D6: =DataT5d!E8 -> 6106.3745 | E6: =DataT5d!F8 -> 8189.2354 | F6: =DataT5d!G8 -> 9528.9805 | G6: =DataT5d!H8 -> 1.3865235 | H6: =DataT5d!I8 -> 0.92690593 | ... K6: =DataT5d!L8 -> 3.0767255
A7: =DataT5d!B9 -> North America & Oceania | B7: =DataT5d!C9 -> 1945.7975 | C7: =DataT5d!D9 -> 33528.434 | D7: =DataT5d!E9 -> 51932.031 | E7: =DataT5d!F9 -> 60178.754 | F7: =DataT5d!G9 -> 68025.031 | G7: =DataT5d!H9 -> 1.5921885 | H7: =DataT5d!I9 -> 1.5846058 | ... K7: =DataT5d!L9 -> 2.4814148
A8: =DataT5d!B10 -> Russia & Central Asia | B8: =DataT5d!C10 -> 395.27032 | C8: =DataT5d!D10 -> 6206.1035 | D8: =DataT5d!E10 -> 5474.2769 | E8: =DataT5d!F10 -> 9292.8281 | F8: =DataT5d!G10 -> 10810.663 | G8: =DataT5d!H10 -> 1.4814072 | H8: =DataT5d!I10 -> 1.2409698 | ... K8: =DataT5d!L10 -> 3.0720434
A9: =DataT5d!B11 -> South & South-East Asia | B9: =DataT5d!C11 -> 316.40631 | C9: =DataT5d!D11 -> 661.5542 | D9: =DataT5d!E11 -> 1167.0862 | E9: =DataT5d!F11 -> 2402.1438 | F9: =DataT5d!G11 -> 3042.0969 | G9: =DataT5d!H11 -> 1.0109762 | H9: =DataT5d!I11 -> 3.4485993 | ... K9: =DataT5d!L11 -> 4.8370552
A10: =DataT5d!B12 -> Sub-Saharan Africa | B10: =DataT5d!C12 -> 284.14514 | C10: =DataT5d!D12 -> 1305.1702 | D10: =DataT5d!E12 -> 1385.5729 | E10: =DataT5d!F12 -> 1749.9187 | F10: =DataT5d!G12 -> 1823.8711 | G10: =DataT5d!H12 -> 0.82974851 | H10: =DataT5d!I12 -> 0.74638915 | ... K10: =DataT5d!L12 -> 0.83127379
A11: =DataT5d!B13 -> World | B11: =DataT5d!C13 -> 616.49304 | C11: =DataT5d!D13 -> 6682.8691 | D11: =DataT5d!E13 -> 8473.6865 | E11: =DataT5d!F13 -> 10735.354 | F11: =DataT5d!G13 -> 12316.911 | G11: =DataT5d!H13 -> 1.3398664 | H11: =DataT5d!I13 -> 1.3679967 | ... K11: =DataT5d!L13 -> 2.7867384
A12: Interpretation. Between 1800 and 2025, the real growth rate of per capita national income expressed in MER $ at the global level has been 1.3% per year. Since 1980 we observed almost doubling of average income, with an acceleration in the growth after 2000: 1.5% per year over 2000-2025 and 2.8% over 2020-2025. Sources and series: wid.world

Sheet T6
A1: =DataT6!B3 -> Table 6. Per Capita National Income Growth PPP 2025 € by WID core Territories (1980-2025)
A2: =DataT6!B4 -> Region | B2: =DataT6!C4 -> Country | C2: =DataT6!D4 -> 1800 Per capita national income (PPP 2025 €) | D2: =DataT6!E4 -> 1980 Per capita national income (PPP 2025 €) | E2: =DataT6!F4 -> 2000 Per capita national income (PPP 2025 €) | F2: =DataT6!G4 -> 2020 Per capita national income (PPP 2025 €) | G2: =DataT6!H4 -> 2025 Per capita national income (PPP 2025 €) | H2: =DataT6!I4 -> Annual growth rate 1800-2025 | ... L2: =DataT6!M4 -> Annual growth rate 2020-2025
A3: =DataT6!B5 -> East Asia | B3: =DataT6!C5 -> Taiwan | C3: =DataT6!D5 -> 762.37421 | D3: =DataT6!E5 -> 6466.3774 | E3: =DataT6!F5 -> 22022.65 | F3: =DataT6!G5 -> 41774.199 | G3: =DataT6!H5 -> 55286.777 | H3: =DataT6!I5 -> 1.9221745 | ... L3: =DataT6!M5 -> 5.7651582
B4: =DataT6!C6 -> South Korea | C4: =DataT6!D6 -> 564.92633 | D4: =DataT6!E6 -> 4334.2769 | E4: =DataT6!F6 -> 17094.975 | F4: =DataT6!G6 -> 31462.213 | G4: =DataT6!H6 -> 35047.836 | H4: =DataT6!I6 -> 1.8514977 | I4: =DataT6!J6 -> 4.7543583 | ... L4: =DataT6!M6 -> 2.1819987
B5: =DataT6!C7 -> Japan | C5: =DataT6!D7 -> 807.88416 | D5: =DataT6!E7 -> 15316.253 | E5: =DataT6!F7 -> 23818.285 | F5: =DataT6!G7 -> 26677.477 | G5: =DataT6!H7 -> 30128.635 | H5: =DataT6!I7 -> 1.621365 | I5: =DataT6!J7 -> 1.5148289 | ... L5: =DataT6!M7 -> 2.4629695
B6: =DataT6!C8 -> Other East Asia | C6: =DataT6!D8 -> 1452.4775 | D6: =DataT6!E8 -> 7102.3613 | E6: =DataT6!F8 -> 12931.475 | F6: =DataT6!G8 -> 21507.312 | G6: =DataT6!H8 -> 26422.281 | H6: =DataT6!I8 -> 1.2976527 | I6: =DataT6!J8 -> 2.9625473 | ... L6: =DataT6!M8 -> 4.2021871
B7: =DataT6!C9 -> China | C7: =DataT6!D9 -> 745.72699 | D7: =DataT6!E9 -> 1160.798 | E7: =DataT6!F9 -> 3007.4492 | F7: =DataT6!G9 -> 12333.229 | G7: =DataT6!H9 -> 15891.335 | H7: =DataT6!I9 -> 1.368916 | I7: =DataT6!J9 -> 5.9871993 | ... L7: =DataT6!M9 -> 5.2002368
A8: =DataT6!B10 -> Europe | B8: =DataT6!C10 -> Norway | C8: =DataT6!D10 -> 1622.7782 | D8: =DataT6!E10 -> 29528.547 | E8: =DataT6!F10 -> 51834.059 | F8: =DataT6!G10 -> 63179.25 | G8: =DataT6!H10 -> 70146.875 | H8: =DataT6!I10 -> 1.688068 | ... L8: =DataT6!M10 -> 2.1143498
B9: =DataT6!C11 -> Denmark | C9: =DataT6!D11 -> 1648.1161 | D9: =DataT6!E11 -> 23564.93 | E9: =DataT6!F11 -> 37408.625 | F9: =DataT6!G11 -> 44730.328 | G9: =DataT6!H11 -> 49726.016 | H9: =DataT6!I11 -> 1.5256975 | I9: =DataT6!J11 -> 1.6733319 | ... L9: =DataT6!M11 -> 2.14011
B10: =DataT6!C12 -> Netherlands | C10: =DataT6!D12 -> 2572.5249 | D10: =DataT6!E12 -> 25348.957 | E10: =DataT6!F12 -> 36834.434 | F10: =DataT6!G12 -> 42004.16 | G10: =DataT6!H12 -> 47551.422 | H10: =DataT6!I12 -> 1.3048505 | I10: =DataT6!J12 -> 1.4077593 | ... L10: =DataT6!M12 -> 2.5118902
B11: =DataT6!C13 -> Sweden | C11: =DataT6!D13 -> 1089.9889 | D11: =DataT6!E13 -> 23006.529 | E11: =DataT6!F13 -> 31703.746 | F11: =DataT6!G13 -> 41712.273 | G11: =DataT6!H13 -> 45180.148 | H11: =DataT6!I13 -> 1.6691055 | I11: =DataT6!J13 -> 1.5110351 | ... L11: =DataT6!M13 -> 1.6100713
B12: =DataT6!C14 -> Germany | C12: =DataT6!D14 -> 1810.4558 | D12: =DataT6!E14 -> 23004.826 | E12: =DataT6!F14 -> 33185.5 | F12: =DataT6!G14 -> 39611.574 | G12: =DataT6!H14 -> 41797.828 | H12: =DataT6!I14 -> 1.405008 | I12: =DataT6!J14 -> 1.335822 | ... L12: =DataT6!M14 -> 1.0802532
B13: =DataT6!C15 -> Other Western Europe | C13: =DataT6!D15 -> 1593.2117 | D13: =DataT6!E15 -> 21152.529 | E13: =DataT6!F15 -> 31288.102 | F13: =DataT6!G15 -> 34622.328 | G13: =DataT6!H15 -> 41160.832 | H13: =DataT6!I15 -> 1.4557093 | I13: =DataT6!J15 -> 1.4903919 | ... L13: =DataT6!M15 -> 3.5203128
B14: =DataT6!C16 -> United Kingdom | C14: =DataT6!D16 -> 2975.6355 | D14: =DataT6!E16 -> 17819.709 | E14: =DataT6!F16 -> 31424.762 | F14: =DataT6!G16 -> 32126.607 | G14: =DataT6!H16 -> 38013.445 | H14: =DataT6!I16 -> 1.1386482 | I14: =DataT6!J16 -> 1.697886 | ... L14: =DataT6!M16 -> 3.4223678
B15: =DataT6!C17 -> France | C15: =DataT6!D17 -> 1256.853 | D15: =DataT6!E17 -> 22009.463 | E15: =DataT6!F17 -> 31651.006 | F15: =DataT6!G17 -> 32877.523 | G15: =DataT6!H17 -> 37176.402 | H15: =DataT6!I17 -> 1.516749 | I15: =DataT6!J17 -> 1.1717039 | ... L15: =DataT6!M17 -> 2.4881487
B16: =DataT6!C18 -> Italy | C16: =DataT6!D18 -> 2109.2439 | D16: =DataT6!E18 -> 23224.664 | E16: =DataT6!F18 -> 33868.824 | F16: =DataT6!G18 -> 29077.705 | G16: =DataT6!H18 -> 34700.133 | H16: =DataT6!I18 -> 1.2524061 | I16: =DataT6!J18 -> 0.89627874 | ... L16: =DataT6!M18 -> 3.5986753
B17: =DataT6!C19 -> Spain | C17: =DataT6!D19 -> 1585.5116 | D17: =DataT6!E19 -> 17104.926 | E17: =DataT6!F19 -> 26827.758 | F17: =DataT6!G19 -> 26928.865 | G17: =DataT6!H19 -> 33533.711 | H17: =DataT6!I19 -> 1.3655256 | I17: =DataT6!J19 -> 1.5072119 | ... L17: =DataT6!M19 -> 4.4847035
B18: =DataT6!C20 -> Eastern Europe | C18: =DataT6!D20 -> 646.91724 | D18: =DataT6!E20 -> 10442.181 | E18: =DataT6!F20 -> 11076.905 | F18: =DataT6!G20 -> 21551.023 | G18: =DataT6!H20 -> 25895.305 | H18: =DataT6!I20 -> 1.6533405 | I18: =DataT6!J20 -> 2.0387444 | ... L18: =DataT6!M20 -> 3.7410452
A19: =DataT6!B21 -> Latin America | B19: =DataT6!C21 -> Argentina | C19: =DataT6!D21 -> 976.75232 | D19: =DataT6!E21 -> 15854.797 | E19: =DataT6!F21 -> 15526.597 | F19: =DataT6!G21 -> 17498.039 | G19: =DataT6!H21 -> 20248.16 | H19: =DataT6!I21 -> 1.3564895 | ... L19: =DataT6!M21 -> 2.962538
B20: =DataT6!C22 -> Chile | C20: =DataT6!D22 -> 600.43573 | D20: =DataT6!E22 -> 6160.0034 | E20: =DataT6!F22 -> 11588.76 | F20: =DataT6!G22 -> 16560.623 | G20: =DataT6!H22 -> 19354.293 | H20: =DataT6!I22 -> 1.5555362 | I20: =DataT6!J22 -> 2.57672 | ... L20: =DataT6!M22 -> 3.1668396
B21: =DataT6!C23 -> Mexico | C21: =DataT6!D23 -> 1052.4484 | D21: =DataT6!E23 -> 12415.942 | E21: =DataT6!F23 -> 13548.574 | F21: =DataT6!G23 -> 11943.775 | G21: =DataT6!H23 -> 13822.125 | H21: =DataT6!I23 -> 1.1510863 | I21: =DataT6!J23 -> 0.23870505 | ... L21: =DataT6!M23 -> 2.9642928
B22: =DataT6!C24 -> Brazil | C22: =DataT6!D24 -> 722.03461 | D22: =DataT6!E24 -> 8915.9453 | E22: =DataT6!F24 -> 9569.7793 | F22: =DataT6!G24 -> 11504.803 | G22: =DataT6!H24 -> 13109.847 | H22: =DataT6!I24 -> 1.2968013 | I22: =DataT6!J24 -> 0.8603965 | ... L22: =DataT6!M24 -> 2.6463923
B23: =DataT6!C25 -> Colombia | C23: =DataT6!D25 -> 832.60352 | D23: =DataT6!E25 -> 6324.7832 | E23: =DataT6!F25 -> 7518.2021 | F23: =DataT6!G25 -> 10805.216 | G23: =DataT6!H25 -> 12763.927 | H23: =DataT6!I25 -> 1.2206434 | I23: =DataT6!J25 -> 1.5725639 | ... L23: =DataT6!M25 -> 3.3880086
B24: =DataT6!C26 -> Other Latin America | C24: =DataT6!D26 -> 544.88599 | D24: =DataT6!E26 -> 6880.4141 | E24: =DataT6!F26 -> 6952.5767 | F24: =DataT6!G26 -> 8655.6992 | G24: =DataT6!H26 -> 10159.311 | H24: =DataT6!I26 -> 1.3087431 | I24: =DataT6!J26 -> 0.86978698 | ... L24: =DataT6!M26 -> 3.2553163
A25: =DataT6!B27 -> MENA | B25: =DataT6!C27 -> United Arab Emirates | C25: =DataT6!D27 -> 448.92169 | D25: =DataT6!E27 -> 122996.63 | E25: =DataT6!F27 -> 65164.047 | F25: =DataT6!G27 -> 48366.523 | G25: =DataT6!H27 -> 53645.613 | H25: =DataT6!I27 -> 2.1486726 | ... L25: =DataT6!M27 -> 2.0934465
B26: =DataT6!C28 -> Saudi Arabia | C26: =DataT6!D28 -> 1031.3004 | D26: =DataT6!E28 -> 103553.73 | E26: =DataT6!F28 -> 40415.008 | F26: =DataT6!G28 -> 41351.004 | G26: =DataT6!H28 -> 48625.164 | H26: =DataT6!I28 -> 1.7273358 | I26: =DataT6!J28 -> -1.665856 | ... L26: =DataT6!M28 -> 3.2939782
B27: =DataT6!C29 -> Turkiye | C27: =DataT6!D29 -> 602.97614 | D27: =DataT6!E29 -> 6594.0449 | E27: =DataT6!F29 -> 9733.1055 | F27: =DataT6!G29 -> 18187.838 | G27: =DataT6!H29 -> 24358.051 | H27: =DataT6!I29 -> 1.6574706 | I27: =DataT6!J29 -> 2.9463382 | ... L27: =DataT6!M29 -> 6.0162134
B28: =DataT6!C30 -> Egypt | C28: =DataT6!D30 -> 804.67749 | D28: =DataT6!E30 -> 4924.4355 | E28: =DataT6!F30 -> 8226.293 | F28: =DataT6!G30 -> 11830.522 | G28: =DataT6!H30 -> 13136.62 | H28: =DataT6!I30 -> 1.2489427 | I28: =DataT6!J30 -> 2.2043767 | ... L28: =DataT6!M30 -> 2.1165056
B29: =DataT6!C31 -> Algeria | C29: =DataT6!D31 -> 642.2785 | D29: =DataT6!E31 -> 7829.6885 | E29: =DataT6!F31 -> 8054.2549 | F29: =DataT6!G31 -> 9950.3496 | G29: =DataT6!H31 -> 11393.849 | H29: =DataT6!I31 -> 1.2863394 | I29: =DataT6!J31 -> 0.83715332 | ... L29: =DataT6!M31 -> 2.7463539
B30: =DataT6!C32 -> Other MENA | C30: =DataT6!D32 -> 1014.0021 | D30: =DataT6!E32 -> 8818.6758 | E30: =DataT6!F32 -> 8632.3516 | F30: =DataT6!G32 -> 9742.6602 | G30: =DataT6!H32 -> 9848.6885 | H30: =DataT6!I32 -> 1.0155367 | I30: =DataT6!J32 -> 0.24578275 | ... L30: =DataT6!M32 -> 0.21671641
B31: =DataT6!C33 -> Iran | C31: =DataT6!D33 -> 502.86456 | D31: =DataT6!E33 -> 6538.2236 | E31: =DataT6!F33 -> 6334.3315 | F31: =DataT6!G33 -> 7443.2759 | G31: =DataT6!H33 -> 9042.7969 | H31: =DataT6!I33 -> 1.2924601 | I31: =DataT6!J33 -> 0.7232765 | ... L31: =DataT6!M33 -> 3.9699264
B32: =DataT6!C34 -> Morocco | C32: =DataT6!D34 -> 505.73511 | D32: =DataT6!E34 -> 2609.3403 | E32: =DataT6!F34 -> 3288.4707 | F32: =DataT6!G34 -> 6066.0781 | G32: =DataT6!H34 -> 7146.0513 | H32: =DataT6!I34 -> 1.1839774 | I32: =DataT6!J34 -> 2.264055 | ... L32: =DataT6!M34 -> 3.3312366
A33: =DataT6!B35 -> North America & Oceania | B33: =DataT6!C35 -> USA | C33: =DataT6!D35 -> 1777.0096 | D33: =DataT6!E35 -> 23764.225 | E33: =DataT6!F35 -> 37661.988 | F33: =DataT6!G35 -> 43821.824 | G33: =DataT6!H35 -> 49940.434 | H33: =DataT6!I35 -> 1.4936671 | ... L33: =DataT6!M35 -> 2.6484447
B34: =DataT6!C36 -> Canada | C34: =DataT6!D36 -> 1000.8845 | D34: =DataT6!E36 -> 23569.922 | E34: =DataT6!F36 -> 32637.424 | F34: =DataT6!G36 -> 37533.629 | G34: =DataT6!H36 -> 42166.84 | H34: =DataT6!I36 -> 1.6764529 | I34: =DataT6!J36 -> 1.3009738 | ... L34: =DataT6!M36 -> 2.3552454
B35: =DataT6!C37 -> Australia | C35: =DataT6!D37 -> 847.40851 | D35: =DataT6!E37 -> 21172.516 | E35: =DataT6!F37 -> 30623.172 | F35: =DataT6!G37 -> 38907.602 | G35: =DataT6!H37 -> 41639.902 | H35: =DataT6!I37 -> 1.746015 | I35: =DataT6!J37 -> 1.5143632 | ... L35: =DataT6!M37 -> 1.3666396
B36: =DataT6!C38 -> New Zealand | C36: =DataT6!D38 -> 761.20264 | D36: =DataT6!E38 -> 16853.344 | E36: =DataT6!F38 -> 20553.406 | F36: =DataT6!G38 -> 31809.367 | G36: =DataT6!H38 -> 32442.963 | H36: =DataT6!I38 -> 1.6816902 | I36: =DataT6!J38 -> 1.4660525 | ... L36: =DataT6!M38 -> 0.39523336
B37: =DataT6!C39 -> Other North America & Oceania | C37: =DataT6!D39 -> 311.58298 | D37: =DataT6!E39 -> 4737.187 | E37: =DataT6!F39 -> 5402.9712 | F37: =DataT6!G39 -> 4803.7461 | G37: =DataT6!H39 -> 4771.292 | H37: =DataT6!I39 -> 1.2201422 | I37: =DataT6!J39 -> 0.015942549 | ... L37: =DataT6!M39 -> -0.13548619
A38: =DataT6!B40 -> Russia & Central Asia | B38: =DataT6!C40 -> Russia | C38: =DataT6!D40 -> 807.11578 | D38: =DataT6!E40 -> 13502.185 | E38: =DataT6!F40 -> 14894.996 | F38: =DataT6!G40 -> 24669.295 | G38: =DataT6!H40 -> 29058.408 | H38: =DataT6!I40 -> 1.6054605 | ... L38: =DataT6!M40 -> 3.3291869
B39: =DataT6!C41 -> Other Russia & Central Asia | C39: =DataT6!D41 -> 655.97595 | D39: =DataT6!E41 -> 9870.208 | E39: =DataT6!F41 -> 4965.7236 | F39: =DataT6!G41 -> 10406.147 | G39: =DataT6!H41 -> 11971.24 | H39: =DataT6!I41 -> 1.299094 | I39: =DataT6!J41 -> 0.42977932 | ... L39: =DataT6!M41 -> 2.8418405
A40: =DataT6!B42 -> South & South-East Asia | B40: =DataT6!C42 -> Thailand | C40: =DataT6!D42 -> 791.96613 | D40: =DataT6!E42 -> 3928.2195 | E40: =DataT6!F42 -> 8030.6611 | F40: =DataT6!G42 -> 12422.272 | G40: =DataT6!H42 -> 14093.052 | H40: =DataT6!I42 -> 1.2877402 | ... L40: =DataT6!M42 -> 2.5559344
B41: =DataT6!C43 -> Other South & South-East Asia | C41: =DataT6!D43 -> 1532.6392 | D41: =DataT6!E43 -> 3164.7634 | E41: =DataT6!F43 -> 6242.5454 | F41: =DataT6!G43 -> 10938.711 | G41: =DataT6!H43 -> 12319.271 | H41: =DataT6!I43 -> 0.93060279 | I41: =DataT6!J43 -> 3.0662625 | ... L41: =DataT6!M43 -> 2.4056158
B42: =DataT6!C44 -> Viet Nam | C42: =DataT6!D44 -> 636.47589 | D42: =DataT6!E44 -> 1012.6856 | E42: =DataT6!F44 -> 2379.1846 | F42: =DataT6!G44 -> 7819.9561 | G42: =DataT6!H44 -> 10207.155 | H42: =DataT6!I44 -> 1.2409242 | I42: =DataT6!J44 -> 5.2685027 | ... L42: =DataT6!M44 -> 5.4727039
B43: =DataT6!C45 -> Indonesia | C43: =DataT6!D45 -> 562.22858 | D43: =DataT6!E45 -> 2303.2454 | E43: =DataT6!F45 -> 3999.5352 | F43: =DataT6!G45 -> 7654.7598 | G43: =DataT6!H45 -> 9755.3721 | H43: =DataT6!I45 -> 1.2763724 | I43: =DataT6!J45 -> 3.259779 | ... L43: =DataT6!M45 -> 4.9693365
B44: =DataT6!C46 -> Philippines | C44: =DataT6!D46 -> 884.09906 | D44: =DataT6!E46 -> 3602.5505 | E44: =DataT6!F46 -> 3469.6392 | F44: =DataT6!G46 -> 5929.6895 | G44: =DataT6!H46 -> 7613.0371 | H44: =DataT6!I46 -> 0.96150339 | I44: =DataT6!J46 -> 1.6766113 | ... L44: =DataT6!M46 -> 5.1248045
B45: =DataT6!C47 -> India | C45: =DataT6!D47 -> 810.90027 | D45: =DataT6!E47 -> 1145.1254 | E45: =DataT6!F47 -> 2146.0342 | F45: =DataT6!G47 -> 5038.5708 | G45: =DataT6!H47 -> 6995.4917 | H45: =DataT6!I47 -> 0.96232355 | I45: =DataT6!J47 -> 4.1036348 | ... L45: =DataT6!M47 -> 6.7830153
B46: =DataT6!C48 -> Bangladesh | C46: =DataT6!D48 -> 1152.0449 | D46: =DataT6!E48 -> 1124.5784 | E46: =DataT6!F48 -> 1703.9778 | F46: =DataT6!G48 -> 5295.7212 | G46: =DataT6!H48 -> 6363.2266 | H46: =DataT6!I48 -> 0.76244617 | I46: =DataT6!J48 -> 3.9265215 | ... L46: =DataT6!M48 -> 3.7410049
B47: =DataT6!C49 -> Pakistan | C47: =DataT6!D49 -> 908.58966 | D47: =DataT6!E49 -> 1588.6708 | E47: =DataT6!F49 -> 2696.2517 | F47: =DataT6!G49 -> 4172.21 | G47: =DataT6!H49 -> 4349.1509 | H47: =DataT6!I49 -> 0.69835716 | I47: =DataT6!J49 -> 2.2631922 | ... L47: =DataT6!M49 -> 0.83415508
B48: =DataT6!C50 -> Myanmar | C48: =DataT6!D50 -> 320.77966 | D48: =DataT6!E50 -> 488.77899 | E48: =DataT6!F50 -> 829.04755 | F48: =DataT6!G50 -> 3658.4741 | G48: =DataT6!H50 -> 3684.1235 | H48: =DataT6!I50 -> 1.0908102 | I48: =DataT6!J50 -> 4.5908794 | ... L48: =DataT6!M50 -> 0.13982806
A49: =DataT6!B51 -> Sub-Saharan Africa | B49: =DataT6!C51 -> South Africa | C49: =DataT6!D51 -> 2048.5669 | D49: =DataT6!E51 -> 7733.7188 | E49: =DataT6!F51 -> 7458.4253 | F49: =DataT6!G51 -> 8826.0635 | G49: =DataT6!H51 -> 9131.0029 | H49: =DataT6!I51 -> 0.66644877 | ... L49: =DataT6!M51 -> 0.68164152
B50: =DataT6!C52 -> Nigeria | C50: =DataT6!D52 -> 686.46362 | D50: =DataT6!E52 -> 3303.6304 | E50: =DataT6!F52 -> 2675.7937 | F50: =DataT6!G52 -> 5559.0044 | G50: =DataT6!H52 -> 5774.8232 | H50: =DataT6!I52 -> 0.95103145 | I50: =DataT6!J52 -> 1.2488126 | ... L50: =DataT6!M52 -> 0.76468164
B51: =DataT6!C53 -> Cote d’Ivoire | C51: =DataT6!D53 -> 627.01978 | D51: =DataT6!E53 -> 3420.8716 | E51: =DataT6!F53 -> 2455.5737 | F51: =DataT6!G53 -> 4141.1133 | G51: =DataT6!H53 -> 4940.7188 | H51: =DataT6!I53 -> 0.92168295 | I51: =DataT6!J53 -> 0.82026917 | ... L51: =DataT6!M53 -> 3.594002
B52: =DataT6!C54 -> Kenya | C52: =DataT6!D54 -> 729.5686 | D52: =DataT6!E54 -> 2611.0386 | E52: =DataT6!F54 -> 2477.7463 | F52: =DataT6!G54 -> 3483.282 | G52: =DataT6!H54 -> 4177.3555 | H52: =DataT6!I54 -> 0.77856189 | I52: =DataT6!J54 -> 1.0497613 | ... L52: =DataT6!M54 -> 3.7009079
B53: =DataT6!C55 -> Other Sub-Saharan Africa | C53: =DataT6!D55 -> 272.44897 | D53: =DataT6!E55 -> 1609.8154 | E53: =DataT6!F55 -> 2034.8102 | F53: =DataT6!G55 -> 2619.3435 | G53: =DataT6!H55 -> 2886.6775 | H53: =DataT6!I55 -> 1.0545932 | I53: =DataT6!J55 -> 1.3062055 | ... L53: =DataT6!M55 -> 1.962662
B54: =DataT6!C56 -> Ethiopia | C54: =DataT6!D56 -> 510.57071 | D54: =DataT6!E56 -> 677.52563 | E54: =DataT6!F56 -> 691.02228 | F54: =DataT6!G56 -> 2076.2761 | G54: =DataT6!H56 -> 2571.2207 | H54: =DataT6!I56 -> 0.72107935 | I54: =DataT6!J56 -> 3.0081091 | ... L54: =DataT6!M56 -> 4.3688397
B55: =DataT6!C57 -> Rwanda | C55: =DataT6!D57 -> 391.74356 | D55: =DataT6!E57 -> 799.62781 | E55: =DataT6!F57 -> 779.58038 | F55: =DataT6!G57 -> 1891.6797 | G55: =DataT6!H57 -> 2506.8457 | H55: =DataT6!I57 -> 0.82837802 | I55: =DataT6!J57 -> 2.5716991 | ... L55: =DataT6!M57 -> 5.7927732
B56: =DataT6!C58 -> Mali | C56: =DataT6!D58 -> 671.06805 | D56: =DataT6!E58 -> 1557.4855 | E56: =DataT6!F58 -> 1552.1152 | F56: =DataT6!G58 -> 1969.3359 | G56: =DataT6!H58 -> 2113.9626 | H56: =DataT6!I58 -> 0.51127994 | I56: =DataT6!J58 -> 0.68117982 | ... L56: =DataT6!M58 -> 1.427449
B57: =DataT6!C59 -> Niger | C57: =DataT6!D59 -> 659.45825 | D57: =DataT6!E59 -> 1403.4547 | E57: =DataT6!F59 -> 847.75665 | F57: =DataT6!G59 -> 1131.4457 | G57: =DataT6!H59 -> 1268.6312 | H57: =DataT6!I59 -> 0.29121217 | I57: =DataT6!J59 -> -0.224189 | ... L57: =DataT6!M59 -> 2.3152416
B58: =DataT6!C60 -> DR Congo | C58: =DataT6!D60 -> 905.35327 | D58: =DataT6!E60 -> 2129.0396 | E58: =DataT6!F60 -> 653.01929 | F58: =DataT6!G60 -> 984.88159 | G58: =DataT6!H60 -> 1174.9895 | H58: =DataT6!I60 -> 0.11592907 | I58: =DataT6!J60 -> -1.3122292 | ... L58: =DataT6!M60 -> 3.5929008
B59: =DataT6!C61 -> Sudan | C59: =DataT6!D61 -> 329.47675 | D59: =DataT6!E61 -> 856.55841 | E59: =DataT6!F61 -> 1827.5265 | F59: =DataT6!G61 -> 1690.2909 | G59: =DataT6!H61 -> 916.99811 | H59: =DataT6!I61 -> 0.45596957 | I59: =DataT6!J61 -> 0.15163235 | ... L59: =DataT6!M61 -> -11.512608
A60: =DataT6!B62 -> World | B60: =DataT6!C62 -> World | C60: =DataT6!D62 -> 730.17249 | D60: =DataT6!E62 -> 7915.1694 | E60: =DataT6!F62 -> 10036.208 | F60: =DataT6!G62 -> 12714.921 | G60: =DataT6!H62 -> 14588.112 | H60: =DataT6!I62 -> 1.3398664 | ... L60: =DataT6!M62 -> 2.7867393
A61: Interpretation. From a very long-run perspective, we find the real growth rate of per capita national income at the global level has been 1.3% per year between 1800 and 2025. Only United Arab Emirates kept an average growth in per capita national income (PPP-adjusted) above 2% but decreasing in average since 1800. East Asia's contries presented significant growths ratesbetween 1980 and 2000. Sub-Saharan Africa, in contrast, saw slow grothws let contrasting only with, Sudan with an increase of 3,9% anual from 1980 to 2000, with its highest growth period occurring during this century. Sources and series: wid.world

Sheet T7
A1: =DataT7!B3 -> Table 7. Population by World Regions (1800-2025)
B2: =DataT7!C4 -> 1800 Population (millions) | C2: =DataT7!D4 -> 1980 Population (millions) | D2: =DataT7!E4 -> 2000 Population (millions) | E2: =DataT7!F4 -> 2020 Population (millions) | F2: =DataT7!G4 -> 2025 Population (millions) | G2: =DataT7!H4 -> Ratio 2025/1800 | H2: =DataT7!I4 -> Annual growth rate 1800-2025 | I2: =DataT7!J4 -> Annual growth rate 1980-2025 | ... L2: =DataT7!M4 -> Annual growth rate 2020-2025
A3: =DataT7!B5 -> East Asia | B3: =DataT7!C5 -> 400.53827 | C3: =DataT7!D5 -> 1182.8966 | D3: =DataT7!E5 -> 1498.9716 | E3: =DataT7!F5 -> 1665.533 | F3: =DataT7!G5 -> 1652.1857 | G3: =DataT7!H5 -> 4.1249132 | H3: =DataT7!I5 -> 0.63178515 | ... L3: =DataT7!M5 -> -0.16079363
A4: =DataT7!B6 -> Europe | B4: =DataT7!C6 -> 145.62494 | C4: =DataT7!D6 -> 498.12009 | D4: =DataT7!E6 -> 524.72095 | E4: =DataT7!F6 -> 552.56982 | F4: =DataT7!G6 -> 555.98505 | G4: =DataT7!H6 -> 3.8179245 | H4: =DataT7!I6 -> 0.59720147 | ... L4: =DataT7!M6 -> 0.12330764
A5: =DataT7!B7 -> Latin America | B5: =DataT7!C7 -> 17.609682 | C5: =DataT7!D7 -> 359.65326 | D5: =DataT7!E7 -> 520.17303 | E5: =DataT7!F7 -> 645.54279 | F5: =DataT7!G7 -> 666.73669 | G5: =DataT7!H7 -> 37.861938 | H5: =DataT7!I7 -> 1.6282003 | ... L5: =DataT7!M7 -> 0.64816612
A6: =DataT7!B8 -> MENA | B6: =DataT7!C8 -> 37.663643 | C6: =DataT7!D8 -> 229.96655 | D6: =DataT7!E8 -> 384.21326 | E6: =DataT7!F8 -> 566.16345 | F6: =DataT7!G8 -> 612.22662 | G6: =DataT7!H8 -> 16.255108 | H6: =DataT7!I8 -> 1.2470032 | ... L6: =DataT7!M8 -> 1.5766952
A7: =DataT7!B9 -> North America & Oceania | B7: =DataT7!C9 -> 9.2114439 | C7: =DataT7!D9 -> 277.25616 | D7: =DataT7!E9 -> 343.52652 | E7: =DataT7!F9 -> 421.51688 | F7: =DataT7!G9 -> 433.84503 | G7: =DataT7!H9 -> 47.09848 | H7: =DataT7!I9 -> 1.7268475 | ... L7: =DataT7!M9 -> 0.57821703
A8: =DataT7!B10 -> Russia & Central Asia | B8: =DataT7!C10 -> 42.272114 | C8: =DataT7!D10 -> 254.01833 | D8: =DataT7!E10 -> 278.07523 | E8: =DataT7!F10 -> 293.70242 | F8: =DataT7!G10 -> 292.72992 | G8: =DataT7!H10 -> 6.9248943 | H8: =DataT7!I10 -> 0.86376369 | ... L8: =DataT7!M10 -> -0.066310696
A9: =DataT7!B11 -> South & South-East Asia | B9: =DataT7!C11 -> 254.15353 | C9: =DataT7!D11 -> 1254.941 | D9: =DataT7!E11 -> 1939.319 | E9: =DataT7!F11 -> 2570.7754 | F9: =DataT7!G11 -> 2692.8218 | G9: =DataT7!H11 -> 10.595256 | H9: =DataT7!I11 -> 1.0545915 | ... L9: =DataT7!M11 -> 0.93195653
A10: =DataT7!B12 -> Sub-Saharan Africa | B10: =DataT7!C12 -> 99.95414 | C10: =DataT7!D12 -> 390.27625 | D10: =DataT7!E12 -> 681.90436 | E10: =DataT7!F12 -> 1170.1597 | F10: =DataT7!G12 -> 1324.0028 | G10: =DataT7!H12 -> 13.246103 | H10: =DataT7!I12 -> 1.1549311 | ... L10: =DataT7!M12 -> 2.5011549
A11: =DataT7!B13 -> World | B11: =DataT7!C13 -> 1007.0278 | C11: =DataT7!D13 -> 4447.1284 | D11: =DataT7!E13 -> 6170.9038 | E11: =DataT7!F13 -> 7885.9634 | F11: =DataT7!G13 -> 8230.5332 | G11: =DataT7!H13 -> 8.1730947 | H11: =DataT7!I13 -> 0.93808275 | ... L11: =DataT7!M13 -> 0.85899723
A12: Interpretation. Between 1800 and 2025, North America/Oceania and Latin America saw their populations grow more than 30-fold, while Europe, East Asia, and Russia/Central Asia experienced less than a 10-fold increase. Since 1980, Sub-Saharan Africa and the Middle East/North Africa have led in population growth rates (arround 3-fold), with Russia/Central Asia and Europe showing the slowest growth. Sources and series: wid.world

Sheet T8a
A1: =DataT8a!B3 -> Table 8a. Price index Growth PPP 2025 € by World Regions (1980-2025)
B2: =DataT8a!C4 -> 1800 Price index (PPP 2025 €) | C2: =DataT8a!D4 -> 1980 Price index (PPP 2025 €) | D2: =DataT8a!E4 -> 2000 Price index (PPP 2025 €) | E2: =DataT8a!F4 -> 2020 Price index (PPP 2025 €) | F2: =DataT8a!G4 -> 2025 Price index (PPP 2025 €) | G2: =DataT8a!H4 -> Annual growth rate 1800-2025 | H2: =DataT8a!I4 -> Annual growth rate 1980-2025 | I2: =DataT8a!J4 -> Annual growth rate 1980-2000 | J2: =DataT8a!K4 -> Annual growth rate 2000-2025
A3: =DataT8a!B5 -> East Asia | B3: =DataT8a!C5 -> 0.0015700549 | C3: =DataT8a!D5 -> 0.29674822 | D3: =DataT8a!E5 -> 0.57910627 | E3: =DataT8a!F5 -> 0.83524191 | F3: =DataT8a!G5 -> 1 | G3: =DataT8a!H5 -> 2.91119 | H3: =DataT8a!I5 -> 2.7364862 | ... J3: =DataT8a!K5 -> 2.2091248
A4: =DataT8a!B6 -> Europe | B4: =DataT8a!C6 -> 0.0017174565 | C4: =DataT8a!D6 -> 0.30642176 | D4: =DataT8a!E6 -> 0.6058858 | E4: =DataT8a!F6 -> 0.83755869 | F4: =DataT8a!G6 -> 1 | G4: =DataT8a!H6 -> 2.8701556 | H4: =DataT8a!I6 -> 2.6632764 | ... J4: =DataT8a!K6 -> 2.0244751
A5: =DataT8a!B7 -> Latin America | B5: =DataT8a!C7 -> 0.0016052589 | C5: =DataT8a!D7 -> 0.29722139 | D5: =DataT8a!E7 -> 0.60075706 | E5: =DataT8a!F7 -> 0.83682209 | F5: =DataT8a!G7 -> 1 | G5: =DataT8a!H7 -> 2.9010484 | H5: =DataT8a!I7 -> 2.7328489 | ... J5: =DataT8a!K7 -> 2.0591729
A6: =DataT8a!B8 -> MENA | B6: =DataT8a!C8 -> 0.00165345 | C6: =DataT8a!D8 -> 0.30088457 | D6: =DataT8a!E8 -> 0.61785024 | E6: =DataT8a!F8 -> 0.84192848 | F6: =DataT8a!G8 -> 1 | G6: =DataT8a!H8 -> 2.8875217 | H6: =DataT8a!I8 -> 2.7048879 | ... J6: =DataT8a!K8 -> 1.9447044
A7: =DataT8a!B9 -> North America & Oceania | B7: =DataT8a!C9 -> 0.0015868581 | C7: =DataT8a!D9 -> 0.30529642 | D7: =DataT8a!E9 -> 0.61371332 | E7: =DataT8a!F9 -> 0.83985311 | F7: =DataT8a!G9 -> 1 | G7: =DataT8a!H9 -> 2.9063213 | H7: =DataT8a!I9 -> 2.6716707 | ... J7: =DataT8a!K9 -> 1.9721035
A8: =DataT8a!B10 -> Russia & Central Asia | B8: =DataT8a!C10 -> 0.0018250472 | C8: =DataT8a!D10 -> 0.31163204 | D8: =DataT8a!E10 -> 0.6099689 | E8: =DataT8a!F10 -> 0.84124565 | F8: =DataT8a!G10 -> 1 | G8: =DataT8a!H10 -> 2.8423791 | H8: =DataT8a!I10 -> 2.6248176 | ... J8: =DataT8a!K10 -> 1.9970691
A9: =DataT8a!B11 -> South & South-East Asia | B9: =DataT8a!C11 -> 0.0015574421 | C9: =DataT8a!D11 -> 0.2986517 | D9: =DataT8a!E11 -> 0.59456915 | E9: =DataT8a!F11 -> 0.83105099 | F9: =DataT8a!G11 -> 1 | G9: =DataT8a!H11 -> 2.9148793 | H9: =DataT8a!I11 -> 2.7218897 | ... J9: =DataT8a!K11 -> 2.101449
A10: =DataT8a!B12 -> Sub-Saharan Africa | B10: =DataT8a!C12 -> 0.0019503632 | C10: =DataT8a!D12 -> 0.29437461 | D10: =DataT8a!E12 -> 0.49222594 | E10: =DataT8a!F12 -> 0.80471206 | F10: =DataT8a!G12 -> 1 | G10: =DataT8a!H12 -> 2.8120294 | H10: =DataT8a!I12 -> 2.7548227 | ... J10: =DataT8a!K12 -> 2.8758461
A11: =DataT8a!B13 -> World | B11: =DataT8a!C13 -> 0.0016282595 | C11: =DataT8a!D13 -> 0.28377786 | D11: =DataT8a!E13 -> 0.53426248 | E11: =DataT8a!F13 -> 0.82272089 | F11: =DataT8a!G13 -> 1 | G11: =DataT8a!H13 -> 2.8945422 | H11: =DataT8a!I13 -> 2.8385708 | ... J11: =DataT8a!K13 -> 2.5391736
A12: Interpretation. Between 1800 and 2025, the average inflation in PPP € at the global level has been 2.9% per year, accelating during the last decades: 3.5% per year over 1980-2000 and 4% over last 5 years (2020-2025). Sources and series: wid.world

Sheet T8b
A1: =DataT8b!B3 -> Table 8b. Price index Growth PPP 2025 $ by World Regions (1980-2025)
B2: =DataT8b!C4 -> 1800 Price index (PPP 2025 $) | C2: =DataT8b!D4 -> 1980 Price index (PPP 2025 $) | D2: =DataT8b!E4 -> 2000 Price index (PPP 2025 $) | E2: =DataT8b!F4 -> 2020 Price index (PPP 2025 $) | F2: =DataT8b!G4 -> 2025 Price index (PPP 2025 $) | G2: =DataT8b!H4 -> Annual growth rate 1800-2025 | H2: =DataT8b!I4 -> Annual growth rate 1980-2025 | I2: =DataT8b!J4 -> Annual growth rate 1980-2000 | ... K2: =DataT8b!L4 -> Annual growth rate 2020-2025
A3: =DataT8b!B5 -> East Asia | B3: =DataT8b!C5 -> 0.022628207 | C3: =DataT8b!D5 -> 0.29683179 | D3: =DataT8b!E5 -> 0.53138733 | E3: =DataT8b!F5 -> 0.81249303 | F3: =DataT8b!G5 -> 1 | G3: =DataT8b!H5 -> 1.6980594 | H3: =DataT8b!I5 -> 2.7358434 | ... K3: =DataT8b!L5 -> 4.2404008
A4: =DataT8b!B6 -> Europe | B4: =DataT8b!C6 -> 0.024752613 | C4: =DataT8b!D6 -> 0.30650812 | D4: =DataT8b!E6 -> 0.55596018 | E4: =DataT8b!F6 -> 0.81474662 | F4: =DataT8b!G6 -> 1 | G4: =DataT8b!H6 -> 1.6575086 | H4: =DataT8b!I6 -> 2.6626334 | ... K4: =DataT8b!L6 -> 4.1826706
A5: =DataT8b!B7 -> Latin America | B5: =DataT8b!C7 -> 0.023135578 | C5: =DataT8b!D7 -> 0.29730514 | D5: =DataT8b!E7 -> 0.55125409 | E5: =DataT8b!F7 -> 0.81403011 | F5: =DataT8b!G7 -> 1 | G5: =DataT8b!H7 -> 1.6880373 | H5: =DataT8b!I7 -> 2.7322059 | ... K5: =DataT8b!L7 -> 4.2010045
A6: =DataT8b!B8 -> MENA | B6: =DataT8b!C8 -> 0.023830129 | C6: =DataT8b!D8 -> 0.30096933 | D6: =DataT8b!E8 -> 0.5669387 | E6: =DataT8b!F8 -> 0.81899738 | F6: =DataT8b!G8 -> 1 | G6: =DataT8b!H8 -> 1.67467 | H6: =DataT8b!I8 -> 2.7042451 | ... K6: =DataT8b!L8 -> 4.0742998
A7: =DataT8b!B9 -> North America & Oceania | B7: =DataT8b!C9 -> 0.022870384 | C7: =DataT8b!D9 -> 0.30538246 | D7: =DataT8b!E9 -> 0.56314272 | E7: =DataT8b!F9 -> 0.81697857 | F7: =DataT8b!G9 -> 1 | G7: =DataT8b!H9 -> 1.6932479 | H7: =DataT8b!I9 -> 2.6710277 | ... K7: =DataT8b!L9 -> 4.1256838
A8: =DataT8b!B10 -> Russia & Central Asia | B8: =DataT8b!C10 -> 0.026303248 | C8: =DataT8b!D10 -> 0.31171983 | D8: =DataT8b!E10 -> 0.55970681 | E8: =DataT8b!F10 -> 0.81833333 | F8: =DataT8b!G10 -> 1 | G8: =DataT8b!H10 -> 1.6300596 | H8: =DataT8b!I10 -> 2.6241751 | ... K8: =DataT8b!L10 -> 4.0911851
A9: =DataT8b!B11 -> South & South-East Asia | B9: =DataT8b!C11 -> 0.022446427 | C9: =DataT8b!D11 -> 0.29873586 | D9: =DataT8b!E11 -> 0.54557598 | E9: =DataT8b!F11 -> 0.80841625 | F9: =DataT8b!G11 -> 1 | G9: =DataT8b!H11 -> 1.7017052 | H9: =DataT8b!I11 -> 2.7212465 | ... K9: =DataT8b!L11 -> 4.3453245
A10: =DataT8b!B12 -> Sub-Saharan Africa | B10: =DataT8b!C12 -> 0.028109347 | C10: =DataT8b!D12 -> 0.29445753 | D10: =DataT8b!E12 -> 0.45166603 | E10: =DataT8b!F12 -> 0.78279465 | F10: =DataT8b!G12 -> 1 | G10: =DataT8b!H12 -> 1.6000675 | H10: =DataT8b!I12 -> 2.7541797 | ... K10: =DataT8b!L12 -> 5.0196171
A11: =DataT8b!B13 -> World | B11: =DataT8b!C13 -> 0.023467075 | C11: =DataT8b!D13 -> 0.28385779 | D11: =DataT8b!E13 -> 0.49023873 | E11: =DataT8b!F13 -> 0.80031306 | F11: =DataT8b!G13 -> 1 | G11: =DataT8b!H13 -> 1.6816077 | H11: =DataT8b!I13 -> 2.8379273 | ... K11: =DataT8b!L13 -> 4.5557737
A12: Interpretation. Between 1800 and 2025, the average inflation in PPP $ at the global level has been 1.7% per year, accelating during the last decades: 3% per year over 1980-2000 and 2.9% over 2000-2025 and 4.6% during the last 5 years. Sources and series: wid.world

Sheet T8c
A1: =DataT8c!B3 -> Table 8c. Price index Growth MER € by World Regions (1980-2025)
B2: =DataT8c!C4 -> 1800 Price index (€) | C2: =DataT8c!D4 -> 1980 Price index (€) | D2: =DataT8c!E4 -> 2000 Price index (€) | E2: =DataT8c!F4 -> 2020 Price index (€) | F2: =DataT8c!G4 -> 2025 Price index (€) | G2: =DataT8c!H4 -> Annual growth rate 1800-2025 | H2: =DataT8c!I4 -> Annual growth rate 1980-2025 | I2: =DataT8c!J4 -> Annual growth rate 1980-2000 | ... K2: =DataT8c!L4 -> Annual growth rate 2020-2025
A3: =DataT8c!B5 -> East Asia | B3: =DataT8c!C5 -> 0.0013899104 | C3: =DataT8c!D5 -> 0.38338977 | D3: =DataT8c!E5 -> 1.077821 | E3: =DataT8c!F5 -> 1.0622771 | F3: =DataT8c!G5 -> 1 | G3: =DataT8c!H5 -> 2.9669471 | H3: =DataT8c!I5 -> 2.1533074 | ... K3: =DataT8c!L5 -> -1.2010252
A4: =DataT8c!B6 -> Europe | B4: =DataT8c!C6 -> 0.0019370096 | C4: =DataT8c!D6 -> 0.27626634 | D4: =DataT8c!E6 -> 0.61933756 | E4: =DataT8c!F6 -> 0.81865954 | F4: =DataT8c!G6 -> 1 | G4: =DataT8c!H6 -> 2.8151686 | H4: =DataT8c!I6 -> 2.8998957 | ... K4: =DataT8c!L6 -> 4.0828881
A5: =DataT8c!B7 -> Latin America | B5: =DataT8c!C7 -> 0.0018849939 | C5: =DataT8c!D7 -> 0.27726188 | D5: =DataT8c!E7 -> 0.66564852 | E5: =DataT8c!F7 -> 0.74560314 | F5: =DataT8c!G7 -> 1 | G5: =DataT8c!H7 -> 2.8276081 | H5: =DataT8c!I7 -> 2.8916705 | ... K5: =DataT8c!L7 -> 6.0470161
A6: =DataT8c!B8 -> MENA | B6: =DataT8c!C8 -> 0.0018162756 | C6: =DataT8c!D8 -> 0.33761245 | D6: =DataT8c!E8 -> 0.59566516 | E6: =DataT8c!F8 -> 0.77855211 | F6: =DataT8c!G8 -> 1 | G6: =DataT8c!H8 -> 2.8445814 | H6: =DataT8c!I8 -> 2.4423635 | ... K6: =DataT8c!L8 -> 5.1338243
A7: =DataT8c!B9 -> North America & Oceania | B7: =DataT8c!C9 -> 0.0018588076 | C7: =DataT8c!D9 -> 0.25418952 | D7: =DataT8c!E9 -> 0.70405853 | E7: =DataT8c!F9 -> 0.84505874 | F7: =DataT8c!G9 -> 1 | G7: =DataT8c!H9 -> 2.8340015 | H7: =DataT8c!I9 -> 3.0905173 | ... K7: =DataT8c!L9 -> 3.4243073
A8: =DataT8c!B10 -> Russia & Central Asia | B8: =DataT8c!C10 -> 0.0032267612 | C8: =DataT8c!D10 -> 0.38675919 | D8: =DataT8c!E10 -> 0.26038262 | E8: =DataT8c!F10 -> 0.66072994 | F8: =DataT8c!G10 -> 1 | G8: =DataT8c!H10 -> 2.5822327 | H8: =DataT8c!I10 -> 2.133446 | ... K8: =DataT8c!L10 -> 8.6413622
A9: =DataT8c!B11 -> South & South-East Asia | B9: =DataT8c!C11 -> 0.0030061097 | C9: =DataT8c!D11 -> 0.41356218 | D9: =DataT8c!E11 -> 0.63543278 | E9: =DataT8c!F11 -> 0.9497962 | F9: =DataT8c!G11 -> 1 | G9: =DataT8c!H11 -> 2.6145318 | H9: =DataT8c!I11 -> 1.9814812 | ... K9: =DataT8c!L11 -> 1.0354812
A10: =DataT8c!B12 -> Sub-Saharan Africa | B10: =DataT8c!C12 -> 0.0022162516 | C10: =DataT8c!D12 -> 0.68637061 | D10: =DataT8c!E12 -> 0.49866372 | E10: =DataT8c!F12 -> 0.83866405 | F10: =DataT8c!G12 -> 1 | G10: =DataT8c!H12 -> 2.7536478 | H10: =DataT8c!I12 -> 0.83981246 | ... K10: =DataT8c!L12 -> 3.5815473
A11: =DataT8c!B13 -> World | B11: =DataT8c!C13 -> 0.0019296241 | C11: =DataT8c!D13 -> 0.31604996 | D11: =DataT8c!E13 -> 0.69861245 | E11: =DataT8c!F13 -> 0.87662148 | F11: =DataT8c!G13 -> 1 | G11: =DataT8c!H13 -> 2.8169143 | H11: =DataT8c!I13 -> 2.5927188 | ... K11: =DataT8c!L13 -> 2.6685853
A12: Interpretation. Between 1980 and 2025, the average inflation in € at the global level has been 2.8% per year, accelating during the last decades: 4.8% per year over 1980-2000 and 2.7% over 2020-2025. Sources and series: wid.world

Sheet T8d
A1: =DataT8d!B3 -> Table 8d. Price index Growth MER $ by World Regions (1980-2025)
B2: =DataT8d!C4 -> 1800 Price index ($) | C2: =DataT8d!D4 -> 1980 Price index ($) | D2: =DataT8d!E4 -> 2000 Price index ($) | E2: =DataT8d!F4 -> 2020 Price index ($) | F2: =DataT8d!G4 -> 2025 Price index ($) | G2: =DataT8d!H4 -> Annual growth rate 1800-2025 | H2: =DataT8d!I4 -> Annual growth rate 1980-2025 | I2: =DataT8d!J4 -> Annual growth rate 1980-2000 | ... K2: =DataT8d!L4 -> Annual growth rate 2020-2025
A3: =DataT8d!B5 -> East Asia | B3: =DataT8d!C5 -> 0.018200267 | C3: =DataT8d!D5 -> 0.46355653 | D3: =DataT8d!E5 -> 0.84461069 | E3: =DataT8d!F5 -> 1.0294343 | F3: =DataT8d!G5 -> 1 | G3: =DataT8d!H5 -> 1.7965332 | H3: =DataT8d!I5 -> 1.7231827 | ... K3: =DataT8d!L5 -> -0.57850915
A4: =DataT8d!B6 -> Europe | B4: =DataT8d!C6 -> 0.025364295 | C4: =DataT8d!D6 -> 0.33403358 | D4: =DataT8d!E6 -> 0.48533019 | E4: =DataT8d!F6 -> 0.79334813 | F4: =DataT8d!G6 -> 1 | G4: =DataT8d!H6 -> 1.6464798 | H4: =DataT8d!I6 -> 2.4666274 | ... K4: =DataT8d!L6 -> 4.7387142
A5: =DataT8d!B7 -> Latin America | B5: =DataT8d!C7 -> 0.024683172 | C5: =DataT8d!D7 -> 0.33523729 | D5: =DataT8d!E7 -> 0.52162081 | E5: =DataT8d!F7 -> 0.72255105 | F5: =DataT8d!G7 -> 1 | G5: =DataT8d!H7 -> 1.658778 | H5: =DataT8d!I7 -> 2.458437 | ... K5: =DataT8d!L7 -> 6.7152023
A6: =DataT8d!B8 -> MENA | B6: =DataT8d!C8 -> 0.023783335 | C6: =DataT8d!D8 -> 0.40820715 | D6: =DataT8d!E8 -> 0.46677983 | E6: =DataT8d!F8 -> 0.75448138 | F6: =DataT8d!G8 -> 1 | G6: =DataT8d!H8 -> 1.6755582 | H6: =DataT8d!I8 -> 2.0110219 | ... K6: =DataT8d!L8 -> 5.7962551
A7: =DataT8d!B9 -> North America & Oceania | B7: =DataT8d!C9 -> 0.024340274 | C7: =DataT8d!D9 -> 0.30734053 | D7: =DataT8d!E9 -> 0.5517199 | E7: =DataT8d!F9 -> 0.81893176 | F7: =DataT8d!G9 -> 1 | G7: =DataT8d!H9 -> 1.6650988 | H7: =DataT8d!I9 -> 2.6564462 | ... K7: =DataT8d!L9 -> 4.0759678
A8: =DataT8d!B10 -> Russia & Central Asia | B8: =DataT8d!C10 -> 0.042253029 | C8: =DataT8d!D10 -> 0.46763048 | D8: =DataT8d!E10 -> 0.20404312 | E8: =DataT8d!F10 -> 0.64030182 | F8: =DataT8d!G10 -> 1 | G8: =DataT8d!H10 -> 1.4161917 | H8: =DataT8d!I10 -> 1.703405 | ... K8: =DataT8d!L10 -> 9.3258982
A9: =DataT8d!B11 -> South & South-East Asia | B9: =DataT8d!C11 -> 0.039363693 | C9: =DataT8d!D11 -> 0.50003803 | D9: =DataT8d!E11 -> 0.49794284 | E9: =DataT8d!F11 -> 0.92043102 | F9: =DataT8d!G11 -> 1 | G9: =DataT8d!H11 -> 1.4481236 | H9: =DataT8d!I11 -> 1.5520797 | ... K9: =DataT8d!L11 -> 1.6720899
A10: =DataT8d!B12 -> Sub-Saharan Africa | B10: =DataT8d!C12 -> 0.029020846 | C10: =DataT8d!D12 -> 0.82989061 | D10: =DataT8d!E12 -> 0.39076686 | E10: =DataT8d!F12 -> 0.81273472 | F10: =DataT8d!G12 -> 1 | G10: =DataT8d!H12 -> 1.5856584 | H10: =DataT8d!I12 -> 0.41521829 | ... K10: =DataT8d!L12 -> 4.2342
A11: =DataT8d!B13 -> World | B11: =DataT8d!C13 -> 0.025267582 | C11: =DataT8d!D13 -> 0.38213599 | D11: =DataT8d!E13 -> 0.54745227 | E11: =DataT8d!F13 -> 0.84951842 | F11: =DataT8d!G13 -> 1 | G11: =DataT8d!H13 -> 1.6482058 | H11: =DataT8d!I13 -> 2.1607437 | ... K11: =DataT8d!L13 -> 3.31549
A12: Interpretation. Between 1800 and 2025, the average inflation in $ at the global level has been 1.6% per year, accelating during the last decades: 2.1% per year over 1980-2000 and 3.3% over 2020-2025. Sources and series: wid.world

Sheet T9
A1: =DataT9!B3 -> Table 9. Price index Growth € by Core countries (1980-2025)
A2: =DataT9!B4 -> Region | B2: =DataT9!C4 -> Country | C2: =DataT9!D4 -> 1800 Price index (€) | D2: =DataT9!E4 -> 1980 Price index (€) | E2: =DataT9!F4 -> 2000 Price index (€) | F2: =DataT9!G4 -> 2020 Price index (€) | G2: =DataT9!H4 -> 2025 Price index (€) | H2: =DataT9!I4 -> Annual growth rate 1800-2025 | ... L2: =DataT9!M4 -> Annual growth rate 2020-2025
A3: =DataT9!B5 -> East Asia | B3: =DataT9!C5 -> Taiwan | C3: =DataT9!D5 -> 0.0015830443 | D3: =DataT9!E5 -> 0.30515155 | E3: =DataT9!F5 -> 0.61442852 | F3: =DataT9!G5 -> 0.8398419 | G3: =DataT9!H5 -> 1 | H3: =DataT9!I5 -> 2.9074218 | ... L3: =DataT9!M5 -> 3.5524771
B4: =DataT9!C6 -> Other East Asia | C4: =DataT9!D6 -> 0.0015510252 | D4: =DataT9!E6 -> 0.94521433 | E4: =DataT9!F6 -> 0.9118287 | F4: =DataT9!G6 -> 0.8876434 | G4: =DataT9!H6 -> 1 | H4: =DataT9!I6 -> 2.9167678 | I4: =DataT9!J6 -> 0.12528636 | ... L4: =DataT9!M6 -> 2.4123414
B5: =DataT9!C7 -> Japan | C5: =DataT9!D7 -> 0.0015956747 | D5: =DataT9!E7 -> 0.30515158 | E5: =DataT9!F7 -> 0.61442852 | F5: =DataT9!G7 -> 0.83984196 | G5: =DataT9!H7 -> 1 | H5: =DataT9!I7 -> 2.9037871 | I5: =DataT9!J7 -> 2.6727533 | ... L5: =DataT9!M7 -> 3.5524757
B6: =DataT9!C8 -> South Korea | C6: =DataT9!D8 -> 0.0015910997 | D6: =DataT9!E8 -> 0.30515155 | E6: =DataT9!F8 -> 0.61442858 | F6: =DataT9!G8 -> 0.8398419 | G6: =DataT9!H8 -> 1 | H6: =DataT9!I8 -> 2.9051003 | I6: =DataT9!J8 -> 2.6727536 | ... L6: =DataT9!M8 -> 3.5524771
B7: =DataT9!C9 -> China | C7: =DataT9!D9 -> 0.0015273578 | D7: =DataT9!E9 -> 0.30515155 | E7: =DataT9!F9 -> 0.61442852 | F7: =DataT9!G9 -> 0.83984196 | G7: =DataT9!H9 -> 1 | H7: =DataT9!I9 -> 2.9238014 | I7: =DataT9!J9 -> 2.6727536 | ... L7: =DataT9!M9 -> 3.5524757
A8: =DataT9!B10 -> Europe | B8: =DataT9!C10 -> Denmark | C8: =DataT9!D10 -> 0.001566579 | D8: =DataT9!E10 -> 0.30515152 | E8: =DataT9!F10 -> 0.61442858 | F8: =DataT9!G10 -> 0.83984196 | G8: =DataT9!H10 -> 1 | H8: =DataT9!I10 -> 2.9122038 | ... L8: =DataT9!M10 -> 3.5524757
B9: =DataT9!C11 -> United Kingdom | C9: =DataT9!D11 -> 0.001600127 | D9: =DataT9!E11 -> 0.30515155 | E9: =DataT9!F11 -> 0.61442858 | F9: =DataT9!G11 -> 0.83984196 | G9: =DataT9!H11 -> 1 | H9: =DataT9!I11 -> 2.9025128 | I9: =DataT9!J11 -> 2.6727536 | ... L9: =DataT9!M11 -> 3.5524757
B10: =DataT9!C12 -> Netherlands | C10: =DataT9!D12 -> 0.0015919352 | D10: =DataT9!E12 -> 0.30515158 | E10: =DataT9!F12 -> 0.61442858 | F10: =DataT9!G12 -> 0.83984202 | G10: =DataT9!H12 -> 1 | H10: =DataT9!I12 -> 2.9048603 | I10: =DataT9!J12 -> 2.6727533 | ... L10: =DataT9!M12 -> 3.5524743
B11: =DataT9!C13 -> Other Western Europe | C11: =DataT9!D13 -> 0.0017223378 | D11: =DataT9!E13 -> 0.30867776 | E11: =DataT9!F13 -> 0.6219191 | F11: =DataT9!G13 -> 0.83551514 | G11: =DataT9!H13 -> 1 | H11: =DataT9!I13 -> 2.8688581 | I11: =DataT9!J13 -> 2.6465425 | ... L11: =DataT9!M13 -> 3.6595061
B12: =DataT9!C14 -> Eastern Europe | C12: =DataT9!D14 -> 0.0017007744 | D12: =DataT9!E14 -> 0.30026364 | E12: =DataT9!F14 -> 0.60869986 | F12: =DataT9!G14 -> 0.83655232 | G12: =DataT9!H14 -> 1 | H12: =DataT9!I14 -> 2.8746183 | I12: =DataT9!J14 -> 2.7096028 | ... L12: =DataT9!M14 -> 3.6337893
B13: =DataT9!C15 -> Germany | C13: =DataT9!D15 -> 0.0015892994 | D13: =DataT9!E15 -> 0.30515152 | E13: =DataT9!F15 -> 0.61442846 | F13: =DataT9!G15 -> 0.83984196 | G13: =DataT9!H15 -> 1 | H13: =DataT9!I15 -> 2.9056182 | I13: =DataT9!J15 -> 2.6727538 | ... L13: =DataT9!M15 -> 3.5524757
B14: =DataT9!C16 -> Norway | C14: =DataT9!D16 -> 0.001564646 | D14: =DataT9!E16 -> 0.30515155 | E14: =DataT9!F16 -> 0.61442852 | F14: =DataT9!G16 -> 0.8398419 | G14: =DataT9!H16 -> 1 | H14: =DataT9!I16 -> 2.9127686 | I14: =DataT9!J16 -> 2.6727536 | ... L14: =DataT9!M16 -> 3.5524771
B15: =DataT9!C17 -> Sweden | C15: =DataT9!D17 -> 0.0015618465 | D15: =DataT9!E17 -> 0.30515155 | E15: =DataT9!F17 -> 0.61442858 | F15: =DataT9!G17 -> 0.83984196 | G15: =DataT9!H17 -> 1 | H15: =DataT9!I17 -> 2.9135878 | I15: =DataT9!J17 -> 2.6727536 | ... L15: =DataT9!M17 -> 3.5524757
B16: =DataT9!C18 -> France | C16: =DataT9!D18 -> 0.0015609944 | D16: =DataT9!E18 -> 0.30515158 | E16: =DataT9!F18 -> 0.61442858 | F16: =DataT9!G18 -> 0.83984202 | G16: =DataT9!H18 -> 1 | H16: =DataT9!I18 -> 2.9138372 | I16: =DataT9!J18 -> 2.6727533 | ... L16: =DataT9!M18 -> 3.5524743
B17: =DataT9!C19 -> Italy | C17: =DataT9!D19 -> 0.0015736368 | D17: =DataT9!E19 -> 0.30515155 | E17: =DataT9!F19 -> 0.61442852 | F17: =DataT9!G19 -> 0.83984196 | G17: =DataT9!H19 -> 1 | H17: =DataT9!I19 -> 2.9101479 | I17: =DataT9!J19 -> 2.6727536 | ... L17: =DataT9!M19 -> 3.5524757
B18: =DataT9!C20 -> Spain | C18: =DataT9!D20 -> 0.0015874696 | D18: =DataT9!E20 -> 0.30515158 | E18: =DataT9!F20 -> 0.61442858 | F18: =DataT9!G20 -> 0.83984202 | G18: =DataT9!H20 -> 1 | H18: =DataT9!I20 -> 2.9061451 | I18: =DataT9!J20 -> 2.6727533 | ... L18: =DataT9!M20 -> 3.5524743
A19: =DataT9!B21 -> Latin America | B19: =DataT9!C21 -> Mexico | C19: =DataT9!D21 -> 0.001614315 | D19: =DataT9!E21 -> 0.30515155 | E19: =DataT9!F21 -> 0.61442852 | F19: =DataT9!G21 -> 0.8398419 | G19: =DataT9!H21 -> 1 | H19: =DataT9!I21 -> 2.8984756 | ... L19: =DataT9!M21 -> 3.5524771
B20: =DataT9!C22 -> Brazil | C20: =DataT9!D22 -> 0.0016312361 | D20: =DataT9!E22 -> 0.30515155 | E20: =DataT9!F22 -> 0.61442852 | F20: =DataT9!G22 -> 0.8398419 | G20: =DataT9!H22 -> 1 | H20: =DataT9!I22 -> 2.893707 | I20: =DataT9!J22 -> 2.6727536 | ... L20: =DataT9!M22 -> 3.5524771
B21: =DataT9!C23 -> Chile | C21: =DataT9!D23 -> 0.0016360346 | D21: =DataT9!E23 -> 0.30515155 | E21: =DataT9!F23 -> 0.61442852 | F21: =DataT9!G23 -> 0.8398419 | G21: =DataT9!H23 -> 1 | H21: =DataT9!I23 -> 2.8923638 | I21: =DataT9!J23 -> 2.6727536 | ... L21: =DataT9!M23 -> 3.5524771
B22: =DataT9!C24 -> Other Latin America | C22: =DataT9!D24 -> 0.0015958268 | D22: =DataT9!E24 -> 0.27937925 | E22: =DataT9!F24 -> 0.57187688 | F22: =DataT9!G24 -> 0.82461262 | G22: =DataT9!H24 -> 1 | H22: =DataT9!I24 -> 2.9037435 | I22: =DataT9!J24 -> 2.8742771 | ... L22: =DataT9!M24 -> 3.9321723
B23: =DataT9!C25 -> Argentina | C23: =DataT9!D25 -> 0.0021459544 | D23: =DataT9!E25 -> 0.30515155 | E23: =DataT9!F25 -> 0.61442864 | F23: =DataT9!G25 -> 0.8398419 | G23: =DataT9!H25 -> 1 | H23: =DataT9!I25 -> 2.7683692 | I23: =DataT9!J25 -> 2.6727536 | ... L23: =DataT9!M25 -> 3.5524771
B24: =DataT9!C26 -> Colombia | C24: =DataT9!D26 -> 0.0016265357 | D24: =DataT9!E26 -> 0.30515158 | E24: =DataT9!F26 -> 0.61442858 | F24: =DataT9!G26 -> 0.83984196 | G24: =DataT9!H26 -> 1 | H24: =DataT9!I26 -> 2.8950267 | I24: =DataT9!J26 -> 2.6727533 | ... L24: =DataT9!M26 -> 3.5524757
A25: =DataT9!B27 -> MENA | B25: =DataT9!C27 -> United Arab Emirates | C25: =DataT9!D27 -> 0.0015092361 | D25: =DataT9!E27 -> 0.30515152 | E25: =DataT9!F27 -> 0.61442852 | F25: =DataT9!G27 -> 0.83984178 | G25: =DataT9!H27 -> 1 | H25: =DataT9!I27 -> 2.9292614 | ... L25: =DataT9!M27 -> 3.55248
B26: =DataT9!C28 -> Saudi Arabia | C26: =DataT9!D28 -> 0.0015032439 | D26: =DataT9!E28 -> 0.30515155 | E26: =DataT9!F28 -> 0.61442852 | F26: =DataT9!G28 -> 0.8398419 | G26: =DataT9!H28 -> 1 | H26: =DataT9!I28 -> 2.9310815 | I26: =DataT9!J28 -> 2.6727536 | ... L26: =DataT9!M28 -> 3.5524771
B27: =DataT9!C29 -> Algeria | C27: =DataT9!D29 -> 0.001545754 | D27: =DataT9!E29 -> 0.30515158 | E27: =DataT9!F29 -> 0.61442852 | F27: =DataT9!G29 -> 0.83984202 | G27: =DataT9!H29 -> 1 | H27: =DataT9!I29 -> 2.9183249 | I27: =DataT9!J29 -> 2.6727533 | ... L27: =DataT9!M29 -> 3.5524743
B28: =DataT9!C30 -> Morocco | C28: =DataT9!D30 -> 0.0015725244 | D28: =DataT9!E30 -> 0.30515158 | E28: =DataT9!F30 -> 0.61442858 | F28: =DataT9!G30 -> 0.83984196 | G28: =DataT9!H30 -> 1 | H28: =DataT9!I30 -> 2.9104712 | I28: =DataT9!J30 -> 2.6727533 | ... L28: =DataT9!M30 -> 3.5524757
B29: =DataT9!C31 -> Iran | C29: =DataT9!D31 -> 0.0023055973 | D29: =DataT9!E31 -> 0.30515158 | E29: =DataT9!F31 -> 0.61442864 | F29: =DataT9!G31 -> 0.83984202 | G29: =DataT9!H31 -> 1 | H29: =DataT9!I31 -> 2.7356002 | I29: =DataT9!J31 -> 2.6727533 | ... L29: =DataT9!M31 -> 3.5524743
B30: =DataT9!C32 -> Egypt | C30: =DataT9!D32 -> 0.0019280271 | D30: =DataT9!E32 -> 0.30515155 | E30: =DataT9!F32 -> 0.61442858 | F30: =DataT9!G32 -> 0.83984196 | G30: =DataT9!H32 -> 1 | H30: =DataT9!I32 -> 2.8172927 | I30: =DataT9!J32 -> 2.6727536 | ... L30: =DataT9!M32 -> 3.5524757
B31: =DataT9!C33 -> Other MENA | C31: =DataT9!D33 -> 0.0015898804 | D31: =DataT9!E33 -> 0.36086258 | E31: =DataT9!F33 -> 0.65877104 | F31: =DataT9!G33 -> 0.84996521 | G31: =DataT9!H33 -> 1 | H31: =DataT9!I33 -> 2.9054511 | I31: =DataT9!J33 -> 2.2908642 | ... L31: =DataT9!M33 -> 3.304626
B32: =DataT9!C34 -> Turkiye | C32: =DataT9!D34 -> 0.0021048614 | D32: =DataT9!E34 -> 0.30515158 | E32: =DataT9!F34 -> 0.61442864 | F32: =DataT9!G34 -> 0.83984202 | G32: =DataT9!H34 -> 1 | H32: =DataT9!I34 -> 2.7772007 | I32: =DataT9!J34 -> 2.6727533 | ... L32: =DataT9!M34 -> 3.5524743
A33: =DataT9!B35 -> North America & Oceania | B33: =DataT9!C35 -> Australia | C33: =DataT9!D35 -> 0.001584304 | D33: =DataT9!E35 -> 0.30515152 | E33: =DataT9!F35 -> 0.61442852 | F33: =DataT9!G35 -> 0.83984196 | G33: =DataT9!H35 -> 1 | H33: =DataT9!I35 -> 2.907058 | ... L33: =DataT9!M35 -> 3.5524757
B34: =DataT9!C36 -> USA | C34: =DataT9!D36 -> 0.0015866351 | D34: =DataT9!E36 -> 0.30515155 | E34: =DataT9!F36 -> 0.61442858 | F34: =DataT9!G36 -> 0.83984196 | G34: =DataT9!H36 -> 1 | H34: =DataT9!I36 -> 2.9063854 | I34: =DataT9!J36 -> 2.6727536 | ... L34: =DataT9!M36 -> 3.5524757
B35: =DataT9!C37 -> New Zealand | C35: =DataT9!D37 -> 0.0016032566 | D35: =DataT9!E37 -> 0.30515158 | E35: =DataT9!F37 -> 0.61442858 | F35: =DataT9!G37 -> 0.83984196 | G35: =DataT9!H37 -> 1 | H35: =DataT9!I37 -> 2.9016192 | I35: =DataT9!J37 -> 2.6727533 | ... L35: =DataT9!M37 -> 3.5524757
B36: =DataT9!C38 -> Canada | C36: =DataT9!D38 -> 0.0015822591 | D36: =DataT9!E38 -> 0.30515152 | E36: =DataT9!F38 -> 0.61442858 | F36: =DataT9!G38 -> 0.8398419 | G36: =DataT9!H38 -> 1 | H36: =DataT9!I38 -> 2.9076486 | I36: =DataT9!J38 -> 2.6727538 | ... L36: =DataT9!M38 -> 3.5524771
B37: =DataT9!C39 -> Other North America & Oceania | C37: =DataT9!D39 -> 0.0015928191 | D37: =DataT9!E39 -> 0.28733617 | E37: =DataT9!F39 -> 0.56538957 | F37: =DataT9!G39 -> 0.81537664 | G37: =DataT9!H39 -> 1 | H37: =DataT9!I39 -> 2.9046063 | I37: =DataT9!J39 -> 2.8100975 | ... L37: =DataT9!M39 -> 4.1665659
A38: =DataT9!B40 -> Russia & Central Asia | B38: =DataT9!C40 -> Russia | C38: =DataT9!D40 -> 0.0016124195 | D38: =DataT9!E40 -> 0.30515155 | E38: =DataT9!F40 -> 0.61442864 | F38: =DataT9!G40 -> 0.83984196 | G38: =DataT9!H40 -> 1 | H38: =DataT9!I40 -> 2.8990128 | ... L38: =DataT9!M40 -> 3.5524757
B39: =DataT9!C41 -> Other Russia & Central Asia | C39: =DataT9!D41 -> 0.0016215186 | D39: =DataT9!E41 -> 0.31158331 | E39: =DataT9!F41 -> 0.62458509 | F39: =DataT9!G41 -> 0.84476072 | G39: =DataT9!H41 -> 1 | H39: =DataT9!I41 -> 2.8964393 | I39: =DataT9!J41 -> 2.625174 | ... L39: =DataT9!M41 -> 3.4316037
A40: =DataT9!B42 -> South & South-East Asia | B40: =DataT9!C42 -> Pakistan | C40: =DataT9!D42 -> 0.0016180804 | D40: =DataT9!E42 -> 0.30515158 | E40: =DataT9!F42 -> 0.61442858 | F40: =DataT9!G42 -> 0.83984196 | G40: =DataT9!H42 -> 1 | H40: =DataT9!I42 -> 2.8974102 | ... L40: =DataT9!M42 -> 3.5524757
B41: =DataT9!C43 -> Viet Nam | C41: =DataT9!D43 -> 0.0015942724 | D41: =DataT9!E43 -> 0.30515152 | E41: =DataT9!F43 -> 0.61442858 | F41: =DataT9!G43 -> 0.83984196 | G41: =DataT9!H43 -> 1 | H41: =DataT9!I43 -> 2.9041893 | I41: =DataT9!J43 -> 2.6727538 | ... L41: =DataT9!M43 -> 3.5524757
B42: =DataT9!C44 -> Bangladesh | C42: =DataT9!D44 -> 0.0016435246 | D42: =DataT9!E44 -> 0.30515158 | E42: =DataT9!F44 -> 0.61442858 | F42: =DataT9!G44 -> 0.83984202 | G42: =DataT9!H44 -> 1 | H42: =DataT9!I44 -> 2.890275 | I42: =DataT9!J44 -> 2.6727533 | ... L42: =DataT9!M44 -> 3.5524743
B43: =DataT9!C45 -> Indonesia | C43: =DataT9!D45 -> 0.0015794177 | D43: =DataT9!E45 -> 0.30515155 | E43: =DataT9!F45 -> 0.61442858 | F43: =DataT9!G45 -> 0.83984202 | G43: =DataT9!H45 -> 1 | H43: =DataT9!I45 -> 2.9084706 | I43: =DataT9!J45 -> 2.6727536 | ... L43: =DataT9!M45 -> 3.5524743
B44: =DataT9!C46 -> Philippines | C44: =DataT9!D46 -> 0.0015654102 | D44: =DataT9!E46 -> 0.30515155 | E44: =DataT9!F46 -> 0.61442864 | F44: =DataT9!G46 -> 0.83984202 | G44: =DataT9!H46 -> 1 | H44: =DataT9!I46 -> 2.9125452 | I44: =DataT9!J46 -> 2.6727536 | ... L44: =DataT9!M46 -> 3.5524743
B45: =DataT9!C47 -> Thailand | C45: =DataT9!D47 -> 0.0015298952 | D45: =DataT9!E47 -> 0.30515155 | E45: =DataT9!F47 -> 0.61442852 | F45: =DataT9!G47 -> 0.83984202 | G45: =DataT9!H47 -> 1 | H45: =DataT9!I47 -> 2.9230423 | I45: =DataT9!J47 -> 2.6727536 | ... L45: =DataT9!M47 -> 3.5524743
B46: =DataT9!C48 -> Other South & South-East Asia | C46: =DataT9!D48 -> 0.0016182649 | D46: =DataT9!E48 -> 0.34603417 | E46: =DataT9!F48 -> 0.60797757 | F46: =DataT9!G48 -> 0.8360545 | G46: =DataT9!H48 -> 1 | H46: =DataT9!I48 -> 2.8973579 | I46: =DataT9!J48 -> 2.3862886 | ... L46: =DataT9!M48 -> 3.6461279
B47: =DataT9!C49 -> India | C47: =DataT9!D49 -> 0.0015618226 | D47: =DataT9!E49 -> 0.30515158 | E47: =DataT9!F49 -> 0.61442858 | F47: =DataT9!G49 -> 0.83984196 | G47: =DataT9!H49 -> 1 | H47: =DataT9!I49 -> 2.9135947 | I47: =DataT9!J49 -> 2.6727533 | ... L47: =DataT9!M49 -> 3.5524757
B48: =DataT9!C50 -> Myanmar | C48: =DataT9!D50 -> 0.0016894431 | D48: =DataT9!E50 -> 0.30515155 | E48: =DataT9!F50 -> 0.61442858 | F48: =DataT9!G50 -> 0.8398419 | G48: =DataT9!H50 -> 1 | H48: =DataT9!I50 -> 2.8776748 | I48: =DataT9!J50 -> 2.6727536 | ... L48: =DataT9!M50 -> 3.5524771
A49: =DataT9!B51 -> Sub-Saharan Africa | B49: =DataT9!C51 -> Other Sub-Saharan Africa | C49: =DataT9!D51 -> 0.0022855103 | D49: =DataT9!E51 -> 0.32525706 | E49: =DataT9!F51 -> 0.51476479 | F49: =DataT9!G51 -> 0.80061638 | G49: =DataT9!H51 -> 1 | H49: =DataT9!I51 -> 2.7395957 | ... L49: =DataT9!M51 -> 4.5478497
B50: =DataT9!C52 -> Niger | C50: =DataT9!D52 -> 0.0015199848 | D50: =DataT9!E52 -> 0.30515155 | E50: =DataT9!F52 -> 0.61442852 | F50: =DataT9!G52 -> 0.83984196 | G50: =DataT9!H52 -> 1 | H50: =DataT9!I52 -> 2.9260151 | I50: =DataT9!J52 -> 2.6727536 | ... L50: =DataT9!M52 -> 3.5524757
B51: =DataT9!C53 -> DR Congo | C51: =DataT9!D53 -> 0.0016739634 | D51: =DataT9!E53 -> 0.30515155 | E51: =DataT9!F53 -> 0.61442858 | F51: =DataT9!G53 -> 0.8398419 | G51: =DataT9!H53 -> 1 | H51: =DataT9!I53 -> 2.8818836 | I51: =DataT9!J53 -> 2.6727536 | ... L51: =DataT9!M53 -> 3.5524771
B52: =DataT9!C54 -> South Africa | C52: =DataT9!D54 -> 0.0015859087 | D52: =DataT9!E54 -> 0.30515155 | E52: =DataT9!F54 -> 0.61442858 | F52: =DataT9!G54 -> 0.83984196 | G52: =DataT9!H54 -> 1 | H52: =DataT9!I54 -> 2.906595 | I52: =DataT9!J54 -> 2.6727536 | ... L52: =DataT9!M54 -> 3.5524757
B53: =DataT9!C55 -> Rwanda | C53: =DataT9!D55 -> 0.0016521402 | D53: =DataT9!E55 -> 0.30515158 | E53: =DataT9!F55 -> 0.61442852 | F53: =DataT9!G55 -> 0.83984196 | G53: =DataT9!H55 -> 1 | H53: =DataT9!I55 -> 2.8878841 | I53: =DataT9!J55 -> 2.6727533 | ... L53: =DataT9!M55 -> 3.5524757
B54: =DataT9!C56 -> Kenya | C54: =DataT9!D56 -> 0.0015992994 | D54: =DataT9!E56 -> 0.30515152 | E54: =DataT9!F56 -> 0.61442852 | F54: =DataT9!G56 -> 0.8398419 | G54: =DataT9!H56 -> 1 | H54: =DataT9!I56 -> 2.9027495 | I54: =DataT9!J56 -> 2.6727538 | ... L54: =DataT9!M56 -> 3.5524771
B55: =DataT9!C57 -> Sudan | C55: =DataT9!D57 -> 0.0031430607 | D55: =DataT9!E57 -> 0.30515158 | E55: =DataT9!F57 -> 0.61442858 | F55: =DataT9!G57 -> 0.83984196 | G55: =DataT9!H57 -> 1 | H55: =DataT9!I57 -> 2.5942159 | I55: =DataT9!J57 -> 2.6727533 | ... L55: =DataT9!M57 -> 3.5524757
B56: =DataT9!C58 -> Ethiopia | C56: =DataT9!D58 -> 0.0018155101 | D56: =DataT9!E58 -> 0.30515155 | E56: =DataT9!F58 -> 0.61442864 | F56: =DataT9!G58 -> 0.8398419 | G56: =DataT9!H58 -> 1 | H56: =DataT9!I58 -> 2.844774 | I56: =DataT9!J58 -> 2.6727536 | ... L56: =DataT9!M58 -> 3.5524771
B57: =DataT9!C59 -> Cote d’Ivoire | C57: =DataT9!D59 -> 0.0015752628 | D57: =DataT9!E59 -> 0.30515158 | E57: =DataT9!F59 -> 0.61442852 | F57: =DataT9!G59 -> 0.8398419 | G57: =DataT9!H59 -> 1 | H57: =DataT9!I59 -> 2.9096756 | I57: =DataT9!J59 -> 2.6727533 | ... L57: =DataT9!M59 -> 3.5524771
B58: =DataT9!C60 -> Mali | C58: =DataT9!D60 -> 0.0015814344 | D58: =DataT9!E60 -> 0.30515155 | E58: =DataT9!F60 -> 0.61442858 | F58: =DataT9!G60 -> 0.83984196 | G58: =DataT9!H60 -> 1 | H58: =DataT9!I60 -> 2.9078872 | I58: =DataT9!J60 -> 2.6727536 | ... L58: =DataT9!M60 -> 3.5524757
B59: =DataT9!C61 -> Nigeria | C59: =DataT9!D61 -> 0.0017566743 | D59: =DataT9!E61 -> 0.30515158 | E59: =DataT9!F61 -> 0.61442858 | F59: =DataT9!G61 -> 0.83984196 | G59: =DataT9!H61 -> 1 | H59: =DataT9!I61 -> 2.8598335 | I59: =DataT9!J61 -> 2.6727533 | ... L59: =DataT9!M61 -> 3.5524757
A60: =DataT9!B62 -> World | B60: =DataT9!C62 -> World | C60: =DataT9!D62 -> 0.0016282595 | D60: =DataT9!E62 -> 0.28377786 | E60: =DataT9!F62 -> 0.53426248 | F60: =DataT9!G62 -> 0.82272089 | G60: =DataT9!H62 -> 1 | H60: =DataT9!I62 -> 2.8945422 | ... L60: =DataT9!M62 -> 3.979924
A61: Interpretation. Between 1800 and 2025, the average inflation in PPP € at the global level has been 2.9% per year, accelating during the last decades: 3.5% per year over 1980-2000 and 4% over last 5 years (2020-2025).During 2000-2025, the average inflation has been 2% per year in most of countries wiht the exception of small eocnomis in Latin America, Nort Americal and Oceania ya dn Sub-Saharan Africa, above 2.3%. In contrast, the small eocnomies in East asia displayed a lower growth of the price level of 0.4% per year for the same period. Sources and series: wid.world

Sheet T10a
A1: Table10a. Top 10 Richest Countries (2025),including countries with population below 10 million
B2: =DataT10!C4 -> Name of Country | C2: =DataT10!D4 -> Per capita national income (PPP 2025 €) | D2: =DataT10!E4 -> Total Population | E2: =DataT10!F4 -> Net Foreign Income as % of Net Domestic Product (PPP) | F2: =DataT10!G4 -> Ratio between MER and PPP Per Capita National Income | G2: =DataT10!H4 -> Net Foreign Wealth as % of Net Domestic Product (PPP 2025 €)
A3: =DataT10!B5 -> 1 | B3: =DataT10!C5 -> Monaco | C3: =DataT10!D5 -> 169163.17 | D3: =DataT10!E5 -> 38341 | E3: =DataT10!F5 -> -0.28889778 | F3: =DataT10!G5 -> 0.99974638 | G3: =DataT10!H5 -> 10.960053
A4: =DataT10!B6 -> 2 | B4: =DataT10!C6 -> Liechtenstein | C4: =DataT10!D6 -> 147878.45 | D4: =DataT10!E6 -> 40128 | E4: =DataT10!F6 -> 0.23186712 | F4: =DataT10!G6 -> 1.4142368 | G4: =DataT10!H6 -> 14.35644
A5: =DataT10!B7 -> 3 | B5: =DataT10!C7 -> Luxembourg | C5: =DataT10!D7 -> 127784.85 | D5: =DataT10!E7 -> 680453 | E5: =DataT10!F7 -> 0.4723143 | F5: =DataT10!G7 -> 1.2885356 | G5: =DataT10!H7 -> 6.8448987
A6: =DataT10!B8 -> 4 | B6: =DataT10!C8 -> Bermuda | C6: =DataT10!D8 -> 126080.46 | D6: =DataT10!E8 -> 64555 | E6: =DataT10!F8 -> 0.58675259 | F6: =DataT10!G8 -> 1.4313023 | G6: =DataT10!H8 -> 50.688442
A7: =DataT10!B9 -> 5 | B7: =DataT10!C9 -> Guernsey | C7: =DataT10!D9 -> 125533.95 | D7: =DataT10!E9 -> 64477 | E7: =DataT10!F9 -> 0.92716485 | F7: =DataT10!G9 -> 1.185871 | G7: =DataT10!H9 -> 32.579826
A8: =DataT10!B10 -> 6 | B8: =DataT10!C10 -> Jersey | C8: =DataT10!D10 -> 121734.24 | D8: =DataT10!E10 -> 103989 | E8: =DataT10!F10 -> 0.89299792 | F8: =DataT10!G10 -> 1.185871 | G8: =DataT10!H10 -> 21.811874
A9: =DataT10!B11 -> 7 | B9: =DataT10!C11 -> Singapore | C9: =DataT10!D11 -> 107491.48 | D9: =DataT10!E11 -> 5870750 | E9: =DataT10!F11 -> 0.11871433 | F9: =DataT10!G11 -> 0.75498581 | G9: =DataT10!H11 -> 2.2225156
A10: =DataT10!B12 -> 8 | B10: =DataT10!C12 -> Cayman Islands | C10: =DataT10!D12 -> 101096.93 | D10: =DataT10!E12 -> 75844 | E10: =DataT10!F12 -> 0.69490141 | F10: =DataT10!G12 -> 1.4001544 | G10: =DataT10!H12 -> -68.204185
A11: =DataT10!B13 -> 9 | B11: =DataT10!C13 -> Gibraltar | C11: =DataT10!D13 -> 86012.516 | D11: =DataT10!E13 -> 40126 | E11: =DataT10!F13 -> 0.37179816 | F11: =DataT10!G13 -> 1.185871 | G11: =DataT10!H13 -> 8.1169558
A12: =DataT10!B14 -> 10 | B12: =DataT10!C14 -> Macao | C12: =DataT10!D14 -> 78176.766 | D12: =DataT10!E14 -> 722007 | E12: =DataT10!F14 -> 0.054944336 | F12: =DataT10!G14 -> 0.68804359 | G12: =DataT10!H14 -> 4.0976324
A13: =DataT10!B15 -> 11 | B13: =DataT10!C15 -> Anguilla | C13: =DataT10!D15 -> 73980.734 | D13: =DataT10!E15 -> 14728 | E13: =DataT10!F15 -> -0.033290822 | F13: =DataT10!G15 -> 0.30965298 | G13: =DataT10!H15 -> -1.6904958
A14: =DataT10!B16 -> 12 | B14: =DataT10!C16 -> Norway | C14: =DataT10!D16 -> 70146.875 | D14: =DataT10!E16 -> 5623071 | E14: =DataT10!F16 -> 0.16000696 | F14: =DataT10!G16 -> 1.1006633 | G14: =DataT10!H16 -> 4.0930853
... A22: =DataT10!B24 -> 20 | B22: =DataT10!C24 -> Montserrat | C22: =DataT10!D24 -> 52952.348 | D22: =DataT10!E24 -> 4359 | E22: =DataT10!F24 -> 0.067695476 | F22: =DataT10!G24 -> 0.29125014 | G22: =DataT10!H24 -> 1.5353235
A23: Interpretation. In 2025, the majority of the world's richest countries by per capita national income are small nations with populations under 1 million, with Singapore being the only exception among the top 10. These countries generally benefit from positive net foreign income (except Monaco). Sources and series: wid.world

Sheet T10b
A1: Table10b. Top 10 Richest Countries (2025), excluding countries with population below 10 million
B2: =DataT10!I4 -> Name of Country (excluding small countries) | C2: =DataT10!J4 -> Per capita national income (PPP 2025 €) (excluding small countries) | D2: =DataT10!K4 -> Total Population (excluding small countries) | E2: =DataT10!L4 -> Net Foreign Income as % of Net Domestic Product (PPP) (excluding small countries) | F2: =DataT10!M4 -> Ratio between MER and PPP Per Capita National Income (excluding small countries) | G2: =DataT10!N4 -> Net Foreign Wealth as % of Net Domestic Product (PPP 2025 €) (excluding small countries)
A3: =DataT10!B5 -> 1 | B3: =DataT10!I5 -> Taiwan | C3: =DataT10!J5 -> 55286.777 | D3: =DataT10!K5 -> 23112793 | E3: =DataT10!L5 -> 0.059912708 | F3: =DataT10!M5 -> 0.58458114 | G3: =DataT10!N5 -> 2.0169506
A4: =DataT10!B6 -> 2 | B4: =DataT10!I6 -> United Arab Emirates | C4: =DataT10!J6 -> 53645.613 | D4: =DataT10!K6 -> 11346000 | E4: =DataT10!L6 -> 0.042752936 | F4: =DataT10!M6 -> 0.75419009 | G4: =DataT10!N6 -> 2.7793922
A5: =DataT10!B7 -> 3 | B5: =DataT10!I7 -> USA | C5: =DataT10!J7 -> 49940.434 | D5: =DataT10!K7 -> 347275807 | E5: =DataT10!L7 -> -0.00065918168 | F5: =DataT10!M7 -> 1.2513745 | G5: =DataT10!N7 -> -1.0439836
A6: =DataT10!B8 -> 4 | B6: =DataT10!I8 -> Saudi Arabia | C6: =DataT10!J8 -> 48625.164 | D6: =DataT10!K8 -> 34566328 | E6: =DataT10!L8 -> 0.003596971 | F6: =DataT10!M8 -> 0.58542264 | G6: =DataT10!N8 -> 1.5154332
A7: =DataT10!B9 -> 5 | B7: =DataT10!I9 -> Netherlands | C7: =DataT10!J9 -> 47551.422 | D7: =DataT10!K9 -> 18346819 | E7: =DataT10!L9 -> 0.020829035 | F7: =DataT10!M9 -> 1.1503193 | G7: =DataT10!N9 -> 1.1482332
A8: =DataT10!B10 -> 6 | B8: =DataT10!I10 -> Sweden | C8: =DataT10!J10 -> 45180.148 | D8: =DataT10!K10 -> 10656633 | E8: =DataT10!L10 -> 0.092048801 | F8: =DataT10!M10 -> 1.1068054 | G8: =DataT10!N10 -> 0.81506252
A9: =DataT10!B11 -> 7 | B9: =DataT10!I11 -> Canada | C9: =DataT10!J11 -> 42166.84 | D9: =DataT10!K11 -> 40126723 | E9: =DataT10!L11 -> 0.030414274 | F9: =DataT10!M11 -> 1.0549725 | G9: =DataT10!N11 -> 0.86321223
A10: =DataT10!B12 -> 8 | B10: =DataT10!I12 -> Belgium | C10: =DataT10!J12 -> 42067.367 | D10: =DataT10!K12 -> 11758603 | E10: =DataT10!L12 -> 0.028689658 | F10: =DataT10!M12 -> 1.0582048 | G10: =DataT10!N12 -> 0.79132295
A11: =DataT10!B13 -> 9 | B11: =DataT10!I13 -> Germany | C11: =DataT10!J13 -> 41797.828 | D11: =DataT10!K13 -> 84075075 | E11: =DataT10!L13 -> 0.046689585 | F11: =DataT10!M13 -> 1.0649185 | G11: =DataT10!N13 -> 0.88065732
A12: =DataT10!B14 -> 10 | B12: =DataT10!I14 -> Australia | C12: =DataT10!J14 -> 41639.902 | D12: =DataT10!K14 -> 26974026 | E12: =DataT10!L14 -> -0.01371872 | F12: =DataT10!M14 -> 1.1546172 | G12: =DataT10!N14 -> -0.21116962
A13: =DataT10!B15 -> 11 | B13: =DataT10!I15 -> United Kingdom | C13: =DataT10!J15 -> 38013.445 | D13: =DataT10!K15 -> 69551332 | E13: =DataT10!L15 -> 0.015832845 | F13: =DataT10!M15 -> 1.1858708 | G13: =DataT10!N15 -> 0.05264695
A14: =DataT10!B16 -> 12 | B14: =DataT10!I16 -> France | C14: =DataT10!J16 -> 37176.402 | D14: =DataT10!K16 -> 68898112 | E14: =DataT10!L16 -> 0.037949465 | F14: =DataT10!M16 -> 0.99082261 | G14: =DataT10!N16 -> -0.23334269
... A22: =DataT10!B24 -> 20 | B22: =DataT10!I24 -> Romania | C22: =DataT10!J24 -> 28085.98 | D22: =DataT10!K24 -> 18908650 | E22: =DataT10!L24 -> -0.033819661 | F22: =DataT10!M24 -> 0.60826409 | G22: =DataT10!N24 -> 0.030247768
A23: Interpretation. Most of these countries receive positive net foreign income. These net foreign incomes provide income supplements to these countries, which are much smaller. The fact that they receive positive net foreign income is striking in some cases, given that some of them – especially the USA – have large negative foreign wealth. Richest countries are usually even richer if we use MER (market exchange rate) rather than PPP, reflecting the fact that their price level (given their exchange rate) is generally larger than the world average, or to put it differently, the fact that their exchange rate is high (given their price level), with the exception of Taïwan and Saudi Arabia. Sources and series: wid.world

Sheet T11
A1: =DataT11!B3 -> Table 11. Bottom 10 Poorest Countries (2025)
B2: =DataT11!C4 -> Name of Country | C2: =DataT11!D4 -> Per capita national income (PPP 2025 €) | D2: =DataT11!E4 -> Total Population | E2: =DataT11!F4 -> Net Foreign Income as % of Net Domestic Product (PPP) | F2: =DataT11!G4 -> Ratio between MER and PPP Per Capita National Income | G2: =DataT11!H4 -> Net Foreign Wealth as % of Net Domestic Product (PPP 2025 €)
A3: Ranking 1 | B3: =DataT11!C5 -> Burundi | C3: =DataT11!D5 -> 622.83752 | D3: =DataT11!E5 -> 14390003 | E3: =DataT11!F5 -> -0.0097411145 | F3: =DataT11!G5 -> 0.49313712 | G3: =DataT11!H5 -> -0.87071437
A4: Ranking 2 | B4: =DataT11!C6 -> Yemen | C4: =DataT11!D6 -> 708.84412 | D4: =DataT11!E6 -> 41773878 | E4: =DataT11!F6 -> -0.0010935905 | F4: =DataT11!G6 -> 0.94936574 | G4: =DataT11!H6 -> -0.077065609
A5: Ranking 3 | B5: =DataT11!C7 -> Central African Republic | C5: =DataT11!D7 -> 828.28979 | D5: =DataT11!E7 -> 5513282 | E5: =DataT11!F7 -> 0.00098294194 | F5: =DataT11!G7 -> 0.55026484 | G5: =DataT11!H7 -> -0.56027281
A6: Ranking 4 | B6: =DataT11!C8 -> Mozambique | C6: =DataT11!D8 -> 879.04749 | D6: =DataT11!E8 -> 35631653 | E6: =DataT11!F8 -> -0.13162093 | F6: =DataT11!G8 -> 0.46290615 | G6: =DataT11!H8 -> -3.4789267
A7: Ranking 5 | B7: =DataT11!C9 -> Sudan | C7: =DataT11!D9 -> 916.99811 | D7: =DataT11!E9 -> 51662147 | E7: =DataT11!F9 -> -0.02371897 | F7: =DataT11!G9 -> 1.9754618 | G7: =DataT11!H9 -> -0.68855971
A8: Ranking 6 | B8: =DataT11!C10 -> Somalia | C8: =DataT11!D10 -> 969.79803 | D8: =DataT11!E10 -> 19654739 | E8: =DataT11!F10 -> 0.0030080038 | F8: =DataT11!G10 -> 0.5290947 | G8: =DataT11!H10 -> -0.52960789
A9: Ranking 7 | B9: =DataT11!C11 -> Malawi | C9: =DataT11!D11 -> 1164.002 | D9: =DataT11!E11 -> 22216120 | E9: =DataT11!F11 -> -0.017494872 | F9: =DataT11!G11 -> 0.44583711 | G9: =DataT11!H11 -> -0.3461619
A10: Ranking 8 | B10: =DataT11!C12 -> DR Congo | C10: =DataT11!D12 -> 1174.9895 | D10: =DataT11!E12 -> 112832473 | E10: =DataT11!F12 -> -0.039742582 | F10: =DataT11!G12 -> 0.47531852 | G10: =DataT11!H12 -> -0.50315613
A11: Ranking 9 | B11: =DataT11!C13 -> Madagascar | C11: =DataT11!D13 -> 1177.6971 | D11: =DataT11!E13 -> 32740678 | E11: =DataT11!F13 -> -0.036227111 | F11: =DataT11!G13 -> 0.39191315 | G11: =DataT11!H13 -> -0.3942402
A12: Ranking 10 | B12: =DataT11!C14 -> Niger | C12: =DataT11!D14 -> 1268.6312 | D12: =DataT11!E14 -> 27917831 | E12: =DataT11!F14 -> -0.021101184 | F12: =DataT11!G14 -> 0.43841031 | G12: =DataT11!H14 -> -0.95446408
A13: Ranking 11 | B13: =DataT11!C15 -> Liberia | C13: =DataT11!D15 -> 1309.9266 | D13: =DataT11!E15 -> 5731206 | E13: =DataT11!F15 -> -0.075811602 | F13: =DataT11!G15 -> 0.54056793 | G13: =DataT11!H15 -> -0.6436851
A14: Ranking 12 | B14: =DataT11!C16 -> Afghanistan | C14: =DataT11!D16 -> 1408.2302 | D14: =DataT11!E16 -> 43844111 | E14: =DataT11!F16 -> 0.0096867718 | F14: =DataT11!G16 -> 0.24501151 | G14: =DataT11!H16 -> 0.025133463
... A22: Ranking 20 | B22: =DataT11!C24 -> Haiti | C22: =DataT11!D24 -> 2065.2913 | D22: =DataT11!E24 -> 11906095 | E22: =DataT11!F24 -> 0.00078438222 | F22: =DataT11!G24 -> 1.0489646 | G22: =DataT11!H24 -> 0.012041268
A23: Interpretation. In 2024, the world's poorest countries by per capita national income exhibit several common characteristics. There is no ultra-small country among them; they all pay substantial net foreign income to the rest of the world (except for Burundi and the Central African Republic); and their MER (market exchange rate) national income is always a lot smaller than their PPP national income, reflecting their low price level (given their exchange rate) relative to the world average, or to put it differently, their low exchange rate given their price level. Sources and series: wid.world

Sheet T12
A1: =DataT12!B3 -> Table 12. Top 10 Largest Economies (2025)
B2: =DataT12!B4 -> Name of Country | C2: =DataT12!C4 -> National income (PPP 2025 billions €) | D2: =DataT12!D4 -> Total Population (millions) | E2: =DataT12!E4 -> Per Capita National Income (PPP 2025 €) | F2: =DataT12!F4 -> National income (MER 2025 billions €) | G2: =DataT12!G4 -> Gross domestic product (PPP 2025 billions €) | H2: =DataT12!H4 -> Gross domestic product (MER 2025 billions €) | I2: =DataT12!I4 -> Ranking National income (MER 2025 billions €) | ... L2: =DataT12!L4 -> Net Foreign Wealth as % NDP (MER 2025 $)
A3: Ranking 1 | B3: =DataT12!B5 -> China | C3: =DataT12!C5 -> 22503.658 | D3: =DataT12!D5 -> 1416.0961 | E3: =DataT12!E5 -> 15891.335 | F3: =DataT12!F5 -> 13347.468 | G3: =DataT12!G5 -> 27988.652 | H3: =DataT12!H5 -> 16600.752 | I3: =DataT12!I5 -> 2 | ... L3: =DataT12!L5 -> 0.24394329
A4: Ranking 2 | B4: =DataT12!B6 -> USA | C4: =DataT12!C6 -> 17343.104 | D4: =DataT12!D6 -> 347.27581 | E4: =DataT12!E6 -> 49940.434 | F4: =DataT12!F6 -> 21702.719 | G4: =DataT12!G6 -> 20860.193 | H4: =DataT12!H6 -> 26103.916 | I4: =DataT12!I6 -> 1 | ... L4: =DataT12!L6 -> -1.0446723
A5: Ranking 3 | B5: =DataT12!B7 -> India | C5: =DataT12!C7 -> 10240.459 | D5: =DataT12!D7 -> 1463.8655 | E5: =DataT12!E7 -> 6995.4917 | F5: =DataT12!F7 -> 3037.5376 | G5: =DataT12!G7 -> 11755.397 | H5: =DataT12!H7 -> 3486.9006 | I5: =DataT12!I7 -> 6 | ... L5: =DataT12!L7 -> -0.37667301
A6: Ranking 4 | B6: =DataT12!B8 -> Russia | C6: =DataT12!C8 -> 4184.335 | D6: =DataT12!D8 -> 143.99739 | E6: =DataT12!E8 -> 29058.408 | F6: =DataT12!F8 -> 1974.7528 | G6: =DataT12!G8 -> 4880.21 | H6: =DataT12!H8 -> 2303.1638 | I6: =DataT12!I8 -> 8 | ... L6: =DataT12!L8 -> 0.35366252
A7: Ranking 5 | B7: =DataT12!B9 -> Japan | C7: =DataT12!C9 -> 3708.9397 | D7: =DataT12!D9 -> 123.10348 | E7: =DataT12!E9 -> 30128.635 | F7: =DataT12!F9 -> 3040.6348 | G7: =DataT12!G9 -> 4492.4995 | H7: =DataT12!H9 -> 3683.0068 | I7: =DataT12!I9 -> 5 | ... L7: =DataT12!L9 -> 0.94621229
A8: Ranking 6 | B8: =DataT12!B10 -> Germany | C8: =DataT12!C10 -> 3514.1555 | D8: =DataT12!D10 -> 84.075075 | E8: =DataT12!E10 -> 41797.828 | F8: =DataT12!F10 -> 3742.2893 | G8: =DataT12!G10 -> 4159.1982 | H8: =DataT12!H10 -> 4429.207 | I8: =DataT12!I10 -> 3 | ... L8: =DataT12!L10 -> 0.84137386
A9: Ranking 7 | B9: =DataT12!B11 -> Brazil | C9: =DataT12!C11 -> 2789.938 | D9: =DataT12!D11 -> 212.81241 | E9: =DataT12!E11 -> 13109.847 | F9: =DataT12!F11 -> 1641.2936 | G9: =DataT12!G11 -> 3382.2444 | H9: =DataT12!H11 -> 1989.7417 | I9: =DataT12!I11 -> 11 | ... L9: =DataT12!L11 -> -0.40240809
A10: Ranking 8 | B10: =DataT12!B12 -> Indonesia | C10: =DataT12!C12 -> 2787.3169 | D10: =DataT12!D12 -> 285.72124 | E10: =DataT12!E12 -> 9755.3721 | F10: =DataT12!F12 -> 1019.3528 | G10: =DataT12!G12 -> 3409.271 | H10: =DataT12!H12 -> 1246.8083 | I10: =DataT12!I12 -> 17 | ... L10: =DataT12!L12 -> -0.18292734
A11: Ranking 9 | B11: =DataT12!B13 -> United Kingdom | C11: =DataT12!C13 -> 2643.8857 | D11: =DataT12!D13 -> 69.551332 | E11: =DataT12!E13 -> 38013.445 | F11: =DataT12!F13 -> 3135.3066 | G11: =DataT12!G13 -> 2977.1265 | H11: =DataT12!H13 -> 3530.4871 | I11: =DataT12!I13 -> 4 | ... L11: =DataT12!L13 -> 0.051826391
A12: Ranking 10 | B12: =DataT12!B14 -> France | C12: =DataT12!C14 -> 2561.3838 | D12: =DataT12!D14 -> 68.898112 | E12: =DataT12!E14 -> 37176.402 | F12: =DataT12!F14 -> 2537.8772 | G12: =DataT12!G14 -> 3040.5652 | H12: =DataT12!H14 -> 3012.6609 | I12: =DataT12!I14 -> 7 | ... L12: =DataT12!L14 -> -0.22481121
A13: Interpretation. In 2025, the world's largest economies by total national income are predominantly large nations with populations exceeding 65 million. These countries all boast per capita national incomes surpassing 15,000 euros, with the exceptions of Brazil, Indonesia, and India. BRICS are dominant in PPP but severely weakened in MER. Sources and series: wid.world

Sheet T13a
A1: =DataT13a!B2 -> Table 13a. Current Account by World Region PPP € (2025)
B2: =DataT13a!C3 -> PPP 2025 billions € | H2: =DataT13a!I3 -> % of Gross Domestic Product
A3: =DataT13a!B4 -> Region | B3: =DataT13a!C4 -> Net foreign capital income | C3: =DataT13a!D4 -> Net foreign labor income | D3: =DataT13a!E4 -> Trade balance | E3: =DataT13a!F4 -> Foreign subsidies less taxes on production and imports | F3: =DataT13a!G4 -> Net foreign transfers | G3: =DataT13a!H4 -> Current Account | H3: =DataT13a!I4 -> Net foreign capital income as % of Gross Domestic Product | ... M3: =DataT13a!N4 -> Current Account as % of Gross Domestic Product
A4: =DataT13a!B5 -> East Asia | B4: =DataT13a!C5 -> 81.975501 | C4: =DataT13a!D5 -> -41.234278 | D4: =DataT13a!E5 -> 1350.1177 | E4: =DataT13a!F5 -> 2.7619335 | F4: =DataT13a!G5 -> -99.377785 | G4: =DataT13a!H5 -> 1294.2431 | H4: =DataT13a!I5 -> 0.0021978458 | ... M4: =DataT13a!N5 -> 0.034699962
A5: =DataT13a!B6 -> Europe | B5: =DataT13a!C6 -> 175.86368 | C5: =DataT13a!D6 -> 24.683304 | D5: =DataT13a!E6 -> 190.8974 | E5: =DataT13a!F6 -> 17.972081 | F5: =DataT13a!G6 -> -150.9205 | G5: =DataT13a!H6 -> 258.49596 | H5: =DataT13a!I6 -> 0.0072921854 | ... M5: =DataT13a!N6 -> 0.010718532
A6: =DataT13a!B7 -> Latin America | B6: =DataT13a!C7 -> -329.53625 | C6: =DataT13a!D7 -> 4.2237663 | D6: =DataT13a!E7 -> -100.13473 | E6: =DataT13a!F7 -> -5.0075858 | F6: =DataT13a!G7 -> 210.85456 | G6: =DataT13a!H7 -> -219.60025 | H6: =DataT13a!I7 -> -0.03192541 | ... M6: =DataT13a!N7 -> -0.021274831
A7: =DataT13a!B8 -> MENA | B7: =DataT13a!C8 -> -88.869305 | C7: =DataT13a!D8 -> 12.759817 | D7: =DataT13a!E8 -> 126.08443 | E7: =DataT13a!F8 -> 2.2929245 | F7: =DataT13a!G8 -> 23.732523 | G7: =DataT13a!H8 -> 76.000368 | H7: =DataT13a!I8 -> -0.008328869 | ... M7: =DataT13a!N8 -> 0.0071227867
A8: =DataT13a!B9 -> North America & Oceania | B8: =DataT13a!C9 -> 54.993563 | C8: =DataT13a!D9 -> -14.774147 | D8: =DataT13a!E9 -> -790.64742 | E8: =DataT13a!F9 -> -18.435941 | F8: =DataT13a!G9 -> -140.33292 | G8: =DataT13a!H9 -> -909.19691 | H8: =DataT13a!I9 -> 0.0022504691 | ... M8: =DataT13a!N9 -> -0.037206531
A9: =DataT13a!B10 -> Russia & Central Asia | B9: =DataT13a!C10 -> -128.27684 | C9: =DataT13a!D10 -> 49.26714 | D9: =DataT13a!E10 -> -88.741473 | E9: =DataT13a!F10 -> -0.7352642 | F9: =DataT13a!G10 -> 68.418802 | G9: =DataT13a!H10 -> -100.06763 | H9: =DataT13a!I10 -> -0.018295672 | ... M9: =DataT13a!N10 -> -0.014272292
A10: =DataT13a!B11 -> South & South-East Asia | B10: =DataT13a!C11 -> -559.70779 | C10: =DataT13a!D11 -> 13.007702 | D10: =DataT13a!E11 -> -401.03062 | E10: =DataT13a!F11 -> 16.140673 | F10: =DataT13a!G11 -> 557.3974 | G10: =DataT13a!H11 -> -374.19269 | H10: =DataT13a!I11 -> -0.023574036 | ... M10: =DataT13a!N11 -> -0.015760424
A11: =DataT13a!B12 -> Sub-Saharan Africa | B11: =DataT13a!C12 -> -141.48179 | C11: =DataT13a!D12 -> 3.3159878 | D11: =DataT13a!E12 -> -161.08237 | E11: =DataT13a!F12 -> 2.574345 | F11: =DataT13a!G12 -> 194.13289 | G11: =DataT13a!H12 -> -102.54093 | H11: =DataT13a!I12 -> -0.026701018 | ... M11: =DataT13a!N12 -> -0.019351941
A12: =DataT13a!B13 -> World | B12: =DataT13a!C13 -> -935.03923 | C12: =DataT13a!D13 -> 51.249292 | D12: =DataT13a!E13 -> 125.46297 | E12: =DataT13a!F13 -> 17.563166 | F12: =DataT13a!G13 -> 663.90497 | G12: =DataT13a!H13 -> -76.858938 | H12: =DataT13a!I13 -> -0.0065434924 | ... M12: =DataT13a!N13 -> -0.00053786609
A13: Interpretation. In 2025, East Asia, Europe, and MENA present a positive current account, and South and South-East Asia approaches equilibrium in €. In contrast, North America displays a negative current account, led by an important trade balance deficit, while Latin America, Russia & Central Asia, and Sub-Saharan Africa report negative results, led by their deficit position in foreign capital income. While in $ MER terms the world's National Accounts sum to zero, in € PPP terms the disparities between local and international prices reveal an imbalance. When the MER results are compared with the PPP results, one can see that only the position of East Asia and North America & Oceania strengthens; for the rest, the position weakens. Relative to GDP, the current account is more significant in North America and Oceania, where the current account deficit amounts to 3.7% of GDP. By contrast, East Asia records a current account surplus of 3.5% of GDP, driven in both regions primarily by the contribution of the trade balance. In contrast, in North Africa and the Middle East, the current account remains below 1% of GDP. Sources and series: wid.world

Sheet T13b
A1: =DataT13b!B2 -> Table 13b. Current Account by World Region PPP $ (2025)
B2: =DataT13b!C3 -> PPP 2025 billions $ | H2: =DataT13d!C3 -> MER billions $
A3: =DataT13b!B4 -> Region | B3: =DataT13b!C4 -> Net foreign capital income | C3: =DataT13b!D4 -> Net foreign labor income | D3: =DataT13b!E4 -> Trade balance | E3: =DataT13b!F4 -> Foreign subsidies less taxes on production and imports | F3: =DataT13b!G4 -> Net foreign transfers | G3: =DataT13b!H4 -> Current Account | H3: =DataT13b!I4 -> Net foreign capital income as % of Gross Domestic Product | ... M3: =DataT13b!N4 -> Current Account as % of Gross Domestic Product
A4: =DataT13b!B5 -> East Asia | B4: =DataT13b!C5 -> 120.90696 | C4: =DataT13b!D5 -> -60.817082 | D4: =DataT13b!E5 -> 1991.3098 | E4: =DataT13b!F5 -> 4.0736191 | F4: =DataT13b!G5 -> -146.57385 | G4: =DataT13b!H5 -> 1908.8995 | H4: =DataT13b!I5 -> 0.0021978458 | ... M4: =DataT13b!N5 -> 0.034699962
A5: =DataT13b!B6 -> Europe | B5: =DataT13b!C6 -> 259.38409 | C5: =DataT13b!D6 -> 36.405792 | D5: =DataT13b!E6 -> 281.55759 | E5: =DataT13b!F6 -> 26.507303 | F5: =DataT13b!G6 -> -222.59501 | G5: =DataT13b!H6 -> 381.25976 | H5: =DataT13b!I6 -> 0.0072921854 | ... M5: =DataT13b!N6 -> 0.010718533
A6: =DataT13b!B7 -> Latin America | B6: =DataT13b!C7 -> -486.03818 | C6: =DataT13b!D7 -> 6.2296992 | D6: =DataT13b!E7 -> -147.69029 | E6: =DataT13b!F7 -> -7.3857667 | F6: =DataT13b!G7 -> 310.99269 | G6: =DataT13b!H7 -> -323.89184 | H6: =DataT13b!I7 -> -0.031925414 | ... M6: =DataT13b!N7 -> -0.021274831
A7: =DataT13b!B8 -> MENA | B7: =DataT13b!C8 -> -131.07474 | C7: =DataT13b!D8 -> 18.819653 | D7: =DataT13b!E8 -> 185.96388 | E7: =DataT13b!F8 -> 3.38187 | F7: =DataT13b!G8 -> 35.003484 | G7: =DataT13b!H8 -> 112.09414 | H7: =DataT13b!I8 -> -0.008328869 | ... M7: =DataT13b!N8 -> 0.0071227872
A8: =DataT13b!B9 -> North America & Oceania | B8: =DataT13b!C9 -> 81.110872 | C8: =DataT13b!D9 -> -21.790621 | D8: =DataT13b!E9 -> -1166.1383 | E8: =DataT13b!F9 -> -27.191456 | F8: =DataT13b!G9 -> -206.97922 | G8: =DataT13b!H9 -> -1340.9888 | H8: =DataT13b!I9 -> 0.0022504693 | ... M8: =DataT13b!N9 -> -0.037206527
A9: =DataT13b!B10 -> Russia & Central Asia | B9: =DataT13b!C10 -> -189.19752 | C9: =DataT13b!D10 -> 72.66488 | D9: =DataT13b!E10 -> -130.8862 | E9: =DataT13b!F10 -> -1.0844526 | F9: =DataT13b!G10 -> 100.91197 | G9: =DataT13b!H10 -> -147.59132 | H9: =DataT13b!I10 -> -0.018295674 | ... M9: =DataT13b!N10 -> -0.014272293
A10: =DataT13b!B11 -> South & South-East Asia | B10: =DataT13b!C11 -> -825.52183 | C10: =DataT13b!D11 -> 19.185266 | D10: =DataT13b!E11 -> -591.48638 | E10: =DataT13b!F11 -> 23.806131 | F10: =DataT13b!G11 -> 822.11418 | G10: =DataT13b!H11 -> -551.90266 | H10: =DataT13b!I11 -> -0.023574036 | ... M10: =DataT13b!N11 -> -0.015760424
A11: =DataT13b!B12 -> Sub-Saharan Africa | B11: =DataT13b!C12 -> -208.67371 | C11: =DataT13b!D12 -> 4.8908025 | D11: =DataT13b!E12 -> -237.58291 | E11: =DataT13b!F12 -> 3.7969418 | F11: =DataT13b!G12 -> 286.32965 | G11: =DataT13b!H12 -> -151.23923 | H11: =DataT13b!I12 -> -0.026701018 | ... M11: =DataT13b!N12 -> -0.019351941
A12: =DataT13b!B13 -> World | B12: =DataT13b!C13 -> -1379.1041 | C12: =DataT13b!D13 -> 75.588391 | D12: =DataT13b!E13 -> 185.04725 | E12: =DataT13b!F13 -> 25.90419 | F12: =DataT13b!G13 -> 979.20388 | G12: =DataT13b!H13 -> -113.36043 | H12: =DataT13b!I13 -> -0.0065434924 | ... M12: =DataT13b!N13 -> -0.00053786597
A13: Interpretation. In 2025, East Asia, Europe, and MENA present a positive current account, and South and South-East Asia approaches equilibrium in $. In contrast, North America displays a negative current account, led by an important trade balance deficit, while Latin America, Russia & Central Asia, and Sub-Saharan Africa report negative results, led by their deficit position in foreign capital income. While in $ MER terms the world's National Accounts sum to zero, in $ PPP terms the disparities between local and international prices reveal an imbalance. When the MER results are compared with the PPP results, one can see that only the position of East Asia strengthens; for the rest, the position weakens. Relative to GDP, the current account is more significant in North America and Oceania, where the current account deficit amounts to 3.7% of GDP. By contrast, East Asia records a current account surplus of 3.5% of GDP, driven in both regions primarily by the contribution of the trade balance. In contrast, in North Africa and the Middle East, the current account remains below 1% of GDP. Sources and series: wid.world

Sheet T13c
A1: =DataT13c!B2 -> Table 13c. Current Account by World Region MER € (2025)
B2: =DataT13c!C3 -> MER billions € | H2: =DataT13c!I3 -> % of Gross Domestic Product
A3: =DataT13c!B4 -> Region | B3: =DataT13c!C4 -> Net foreign capital income | C3: =DataT13c!D4 -> Net foreign labor income | D3: =DataT13c!E4 -> Trade balance | E3: =DataT13c!F4 -> Foreign subsidies less taxes on production and imports | F3: =DataT13c!G4 -> Net foreign transfers | G3: =DataT13c!H4 -> Current Account | H3: =DataT13c!I4 -> Net foreign capital income as % of Gross Domestic Product | ... M3: =DataT13c!N4 -> Current Account as % of Gross Domestic Product
A4: =DataT13c!B5 -> East Asia | B4: =DataT13c!C5 -> 154.03104 | C4: =DataT13c!D5 -> -25.137646 | D4: =DataT13c!E5 -> 777.20967 | E4: =DataT13c!F5 -> 2.1626942 | F4: =DataT13c!G5 -> -66.271846 | G4: =DataT13c!H5 -> 841.9939 | H4: =DataT13c!I5 -> 0.0066348063 | ... M4: =DataT13c!N5 -> 0.036268447
A5: =DataT13c!B6 -> Europe | B5: =DataT13c!C6 -> 296.89721 | C5: =DataT13c!D6 -> -2.0602719 | D5: =DataT13c!E6 -> 249.45904 | E5: =DataT13c!F6 -> 15.119702 | F5: =DataT13c!G6 -> -170.706 | G5: =DataT13c!H6 -> 388.70967 | H5: =DataT13c!I6 -> 0.012474344 | ... M5: =DataT13c!N6 -> 0.016331909
A6: =DataT13c!B7 -> Latin America | B6: =DataT13c!C7 -> -193.36139 | C6: =DataT13c!D7 -> 2.3476953 | D6: =DataT13c!E7 -> -56.445008 | E6: =DataT13c!F7 -> -2.4802233 | F6: =DataT13c!G7 -> 128.46446 | G6: =DataT13c!H7 -> -121.47446 | H6: =DataT13c!I7 -> -0.029764958 | ... M6: =DataT13c!N7 -> -0.018699091
A7: =DataT13c!B8 -> MENA | B7: =DataT13c!C8 -> -20.256614 | C7: =DataT13c!D8 -> 4.8811509 | D7: =DataT13c!E8 -> 154.88051 | E7: =DataT13c!F8 -> 2.0868644 | F7: =DataT13c!G8 -> -46.461643 | G7: =DataT13c!H8 -> 95.130267 | H7: =DataT13c!I8 -> -0.0036117679 | ... M7: =DataT13c!N8 -> 0.016961791
A8: =DataT13c!B9 -> North America & Oceania | B8: =DataT13c!C9 -> 61.735562 | C8: =DataT13c!D9 -> -17.59292 | D8: =DataT13c!E9 -> -981.97806 | E8: =DataT13c!F9 -> -22.773957 | F8: =DataT13c!G9 -> -176.08364 | G8: =DataT13c!H9 -> -1136.6931 | H8: =DataT13c!I9 -> 0.0020567114 | ... M8: =DataT13c!N9 -> -0.037868764
A9: =DataT13c!B10 -> Russia & Central Asia | B9: =DataT13c!C10 -> -53.359036 | C9: =DataT13c!D10 -> 20.179547 | D9: =DataT13c!E10 -> -27.455675 | E9: =DataT13c!F10 -> -0.38021404 | F9: =DataT13c!G10 -> 24.328045 | G9: =DataT13c!H10 -> -36.687328 | H9: =DataT13c!I10 -> -0.016941506 | ... M9: =DataT13c!N10 -> -0.011648235
A10: =DataT13c!B11 -> South & South-East Asia | B10: =DataT13c!C11 -> -152.41882 | C10: =DataT13c!D11 -> 2.9029623 | D10: =DataT13c!E11 -> -31.990197 | E10: =DataT13c!F11 -> 5.4792427 | F10: =DataT13c!G11 -> 177.43234 | G10: =DataT13c!H11 -> 1.4055155 | H10: =DataT13c!I11 -> -0.018916899 | ... M10: =DataT13c!N11 -> 0.00017444039
A11: =DataT13c!B12 -> Sub-Saharan Africa | B11: =DataT13c!C12 -> -93.267956 | C11: =DataT13c!D12 -> 14.479483 | D11: =DataT13c!E12 -> -83.679556 | E11: =DataT13c!F12 -> 0.78588958 | F11: =DataT13c!G12 -> 129.2983 | G11: =DataT13c!H12 -> -32.38384 | H11: =DataT13c!I12 -> -0.039581854 | ... M11: =DataT13c!N12 -> -0.013743332
A12: =DataT13c!B13 -> World | B12: =DataT13c!C13 -> 1.4051563e-07 | C12: =DataT13c!D13 -> 2.4930469e-07 | D12: =DataT13c!E13 -> 0.00072537337 | E12: =DataT13c!F13 -> -7.8742578e-07 | F12: =DataT13c!G13 -> 6.7894063e-06 | G12: =DataT13c!H13 -> 0.00063776175 | H12: =DataT13c!I13 -> 1.3682029e-12 | ... M12: =DataT13c!N13 -> 6.2098962e-09
A13: Interpretation. In 2025, East Asia, Europe, and MENA present a positive current account, and South and South-East Asia approaches equilibrium in $. In contrast, North America displays a negative current account, led by an important trade balance deficit, while Latin America, Russia & Central Asia, and Sub-Saharan Africa report negative results, led by their deficit position in foreign capital income. While in $ MER terms the world's National Accounts sum to zero, in € MER Eur terms the disparities between local and international prices reveal an imbalance. When the MER results are compared with the PPP results, one can see that only the position of East Asia strengthens; for the rest, the position weakens. Relative to GDP, the current account is more significant in North America and Oceania, where the current account deficit amounts to 3.8% of GDP. By contrast, East Asia records a current account surplus of 3.6% of GDP, driven in both regions primarily by the contribution of the trade balance. In contrast, in North Africa and the South and South East Asia, the current account remains below 1% of GDP. Sources and series: wid.world

Sheet T13d
A1: =DataT13d!B2 -> Table 13d. Current Account by World Region MER $ (2025)
B2: =DataT13d!C3 -> MER billions $ | H2: =DataT13d!I3 -> % of Gross Domestic Product
A3: =DataT13d!B4 -> Region | B3: =DataT13d!C4 -> Net foreign capital income | C3: =DataT13d!D4 -> Net foreign labor income | D3: =DataT13d!E4 -> Trade balance | E3: =DataT13d!F4 -> Foreign subsidies less taxes on production and imports | F3: =DataT13d!G4 -> Net foreign transfers | G3: =DataT13d!H4 -> Current Account | H3: =DataT13d!I4 -> Net foreign capital income as % of Gross Domestic Product | ... M3: =DataT13d!N4 -> Current Account as % of Gross Domestic Product
A4: =DataT13b!B5 -> East Asia | B4: =DataT13d!C5 -> 181.54661 | C4: =DataT13d!D5 -> -29.628147 | D4: =DataT13d!E5 -> 916.0476 | E4: =DataT13d!F5 -> 2.5490303 | F4: =DataT13d!G5 -> -78.110413 | G4: =DataT13d!H5 -> 992.40469 | H4: =DataT13d!I5 -> 0.0066348067 | I4: =DataT13d!J5 -> -0.001082791 | ... M4: =DataT13d!N5 -> 0.036268447
A5: =DataT13b!B6 -> Europe | B5: =DataT13d!C6 -> 349.93387 | C5: =DataT13d!D6 -> -2.4283122 | D5: =DataT13d!E6 -> 294.02151 | E5: =DataT13d!F6 -> 17.820633 | F5: =DataT13d!G6 -> -201.20032 | G5: =DataT13d!H6 -> 458.14741 | H5: =DataT13d!I6 -> 0.012474344 | I5: =DataT13d!J6 -> -8.6563792e-05 | ... M5: =DataT13d!N6 -> 0.016331909
A6: =DataT13b!B7 -> Latin America | B6: =DataT13d!C7 -> -227.90278 | C6: =DataT13d!D7 -> 2.7670791 | D6: =DataT13d!E7 -> -66.528144 | E6: =DataT13d!F7 -> -2.9232817 | F6: =DataT13d!G7 -> 151.41289 | G6: =DataT13d!H7 -> -143.17423 | H6: =DataT13d!I7 -> -0.029764958 | I6: =DataT13d!J7 -> 0.00036139091 | ... M6: =DataT13d!N7 -> -0.018699091
A7: =DataT13b!B8 -> MENA | B7: =DataT13d!C8 -> -23.875183 | C7: =DataT13d!D8 -> 5.7531032 | D7: =DataT13d!E8 -> 182.54782 | E7: =DataT13d!F8 -> 2.4596543 | F7: =DataT13d!G8 -> -54.76139 | G7: =DataT13d!H8 -> 112.124 | H7: =DataT13d!I8 -> -0.0036117677 | I7: =DataT13d!J8 -> 0.00087031262 | ... M7: =DataT13d!N8 -> 0.016961791
A8: =DataT13b!B9 -> North America & Oceania | B8: =DataT13d!C9 -> 72.763783 | C8: =DataT13d!D9 -> -20.735658 | D8: =DataT13d!E9 -> -1157.3951 | E8: =DataT13d!F9 -> -26.842216 | F8: =DataT13d!G9 -> -207.53859 | G8: =DataT13d!H9 -> -1339.7479 | H8: =DataT13d!I9 -> 0.0020567114 | I8: =DataT13d!J9 -> -0.00058610563 | ... M8: =DataT13d!N9 -> -0.037868768
A9: =DataT13b!B10 -> Russia & Central Asia | B9: =DataT13d!C10 -> -62.890905 | C9: =DataT13d!D10 -> 23.784349 | D9: =DataT13d!E10 -> -32.360258 | E9: =DataT13d!F10 -> -0.44813411 | F9: =DataT13d!G10 -> 28.673923 | G9: =DataT13d!H10 -> -43.241023 | H9: =DataT13d!I10 -> -0.016941506 | I9: =DataT13d!J10 -> 0.0064070104 | ... M9: =DataT13d!N10 -> -0.011648235
A10: =DataT13b!B11 -> South & South-East Asia | B10: =DataT13d!C11 -> -179.64638 | C10: =DataT13d!D11 -> 3.4215381 | D10: =DataT13d!E11 -> -37.704823 | E10: =DataT13d!F11 -> 6.4580356 | F10: =DataT13d!G11 -> 209.12823 | G10: =DataT13d!H11 -> 1.6565976 | H10: =DataT13d!I11 -> -0.018916899 | I10: =DataT13d!J11 -> 0.00036029058 | ... M10: =DataT13d!N11 -> 0.00017444098
A11: =DataT13b!B12 -> Sub-Saharan Africa | B11: =DataT13d!C12 -> -109.92902 | C11: =DataT13d!D12 -> 17.066047 | D11: =DataT13d!E12 -> -98.627775 | E11: =DataT13d!F12 -> 0.92627809 | F11: =DataT13d!G12 -> 152.39569 | G11: =DataT13d!H12 -> -38.168776 | H11: =DataT13d!I12 -> -0.039581854 | I11: =DataT13d!J12 -> 0.0061449269 | ... M11: =DataT13d!N12 -> -0.013743332
A12: =DataT13b!B13 -> World | B12: =DataT13d!C13 -> 5.9985625e-06 | C12: =DataT13d!D13 -> -4.0971094e-07 | D12: =DataT13d!E13 -> 0.000802843 | E12: =DataT13d!F13 -> -4.765625e-09 | F12: =DataT13d!G13 -> 1.7136875e-05 | G12: =DataT13d!H13 -> 0.000776168 | H12: =DataT13d!I13 -> 4.9555655e-11 | I12: =DataT13d!J13 -> -3.3847265e-12 | ... M12: =DataT13d!N13 -> 6.4121215e-09
A13: Interpretation. In 2025, East Asia, Europe, and MENA present a positive current account, and South and South-East Asia approaches equilibrium in $. In contrast, North America displays a negative current account, led by an important trade balance deficit, while Latin America, Russia & Central Asia, and Sub-Saharan Africa report negative results, led by their deficit position in foreign capital income. While in $ MER terms the world's National Accounts sum to zero, in $ PPP terms the disparities between local and international prices reveal an imbalance. When the MER results are compared with the PPP results, one can see that only the position of East Asia strengthens; for the rest, the position weakens. Relative to GDP, the current account is more significant in North America and Oceania, where the current account deficit amounts to 3.8% of GDP. By contrast, East Asia records a current account surplus of 3.6% of GDP, driven in both regions primarily by the contribution of the trade balance. In contrast, in South and South-east Asia, the current account remains below 1% of GDP. Sources and series: wid.world

Sheet T14a
A1: =DataT14a!B3 -> Table 14a. Net foreign Assets PPP € 2025 by World Regions (1980-2025)
A2: =DataT14a!B4 -> Region | B2: =DataT14a!C4 -> 1800 Net Foreign Assets | C2: =DataT14a!D4 -> 1980 Net Foreign Assets | D2: =DataT14a!E4 -> 2000 Net Foreign Assets | E2: =DataT14a!F4 -> 2020 Net Foreign Assets | F2: =DataT14a!G4 -> 2025 Net Foreign Assets | G2: =DataT14a!H4 -> 1800 Net Foreign Assets as % of NDP | H2: =DataT14a!I4 -> 1980 Net Foreign Assets as % of NDP | ... K2: =DataT14a!L4 -> 2025 Net Foreign Assets as % of NDP
A3: =DataT14a!B5 -> East Asia | B3: =DataT14a!C5 -> 0 | C3: =DataT14a!D5 -> 46.187317 | D3: =DataT14a!E5 -> 1593.2855 | E3: =DataT14a!F5 -> 11211.838 | F3: =DataT14a!G5 -> 15475.814 | G3: =DataT14a!H5 -> 0 | H3: =DataT14a!I5 -> 0.027053632 | ... K3: =DataT14a!L5 -> 0.51130581
A4: =DataT14a!B6 -> Europe | B4: =DataT14a!C6 -> 0.05792737 | C4: =DataT14a!D6 -> 210.04512 | D4: =DataT14a!E6 -> 332.96057 | E4: =DataT14a!F6 -> 2708.3359 | F4: =DataT14a!G6 -> 6075.5869 | G4: =DataT14a!H6 -> 0.042962994 | H4: =DataT14a!I6 -> 0.096269608 | ... K4: =DataT14a!L6 -> 0.30404478
A5: =DataT14a!B7 -> Latin America | B5: =DataT14a!C7 -> -0.012341409 | C5: =DataT14a!D7 -> -59.524601 | D5: =DataT14a!E7 -> -305.51279 | E5: =DataT14a!F7 -> -4376.75 | F5: =DataT14a!G7 -> -1507.7296 | G5: =DataT14a!H7 -> -0.14221147 | H5: =DataT14a!I7 -> -0.85415977 | ... K5: =DataT14a!L7 -> -0.16753545
A6: =DataT14a!B8 -> MENA | B6: =DataT14a!C8 -> 0 | C6: =DataT14a!D8 -> 241.00468 | D6: =DataT14a!E8 -> 441.19052 | E6: =DataT14a!F8 -> 4196.9517 | F6: =DataT14a!G8 -> 5232.6758 | G6: =DataT14a!H8 -> 0 | H6: =DataT14a!I8 -> 0.76987451 | ... K6: =DataT14a!L8 -> 0.5509752
A7: =DataT14a!B9 -> North America & Oceania | B7: =DataT14a!C9 -> -0.053805619 | C7: =DataT14a!D9 -> 26.646656 | D7: =DataT14a!E9 -> -1129.9969 | E7: =DataT14a!F9 -> -9175.0576 | F7: =DataT14a!G9 -> -16811.008 | G7: =DataT14a!H9 -> -0.19672768 | H7: =DataT14a!I9 -> 0.014173468 | ... K7: =DataT14a!L9 -> -0.82509017
A8: =DataT14a!B10 -> Russia & Central Asia | B8: =DataT14a!C10 -> 0 | C8: =DataT14a!D10 -> -0.000273905 | D8: =DataT14a!E10 -> 24.219545 | E8: =DataT14a!F10 -> 315.26096 | F8: =DataT14a!G10 -> 1172.9127 | G8: =DataT14a!H10 -> 0 | H8: =DataT14a!I10 -> -0.035078432 | ... K8: =DataT14a!L10 -> 0.19404331
A9: =DataT14a!B11 -> South & South-East Asia | B9: =DataT14a!C11 -> -0.0009080352 | C9: =DataT14a!D11 -> -5.0938611 | D9: =DataT14a!E11 -> -241.45279 | E9: =DataT14a!F11 -> -1369.9329 | F9: =DataT14a!G11 -> -4482.8691 | G9: =DataT14a!H11 -> -0.0013929685 | H9: =DataT14a!I11 -> -0.029723372 | ... K9: =DataT14a!L11 -> -0.21360268
A10: =DataT14a!B12 -> Sub-Saharan Africa | B10: =DataT14a!C12 -> 0 | C10: =DataT14a!D12 -> -15.662459 | D10: =DataT14a!E12 -> -152.00075 | E10: =DataT14a!F12 -> -726.36176 | F10: =DataT14a!G12 -> -1605.7135 | G10: =DataT14a!H12 -> 0 | H10: =DataT14a!I12 -> -0.27958003 | ... K10: =DataT14a!L12 -> -0.3358165
A11: =DataT14a!B13 -> World | B11: =DataT14a!C13 -> -0.0091276933 | C11: =DataT14a!D13 -> 443.60257 | D11: =DataT14a!E13 -> 562.69293 | E11: =DataT14a!F13 -> 2784.2842 | F11: =DataT14a!G13 -> 3549.6709 | G11: =DataT14a!H13 -> -0.0016245482 | H11: =DataT14a!I13 -> 0.069538169 | ... K11: =DataT14a!L13 -> 0.029352091
A12: Interpretation. Between 1800 and 2025, the net foreign assets in PPP € 2025 of Latin America, North America and Oceania, South and South-East Asia, and Sub-Saharan Africa have been consistently negative, in contrast with other regions such as Russia and Central Asia, which reported negative results only around 1980. During the last 5 years, the position of Latin America has strengthened in proportion to Net Domestic Product (NDP), while the deficit of North America and Oceania, South and South-East Asia, and Sub-Saharan Africa has increased as a share of NDP. Sources and series: wid.world

Sheet T14b
A1: =DataT14d!B3 -> Table 14d. Net foreign Assets MER$ by World Regions (1980-2025) | B1: =DataT14d!C3 -> 0 | C1: =DataT14d!D3 -> 0 | D1: =DataT14d!E3 -> 0 | E1: =DataT14d!F3 -> 0 | F1: =DataT14d!G3 -> 0 | G1: =DataT14d!H3 -> 0 | H1: =DataT14d!I3 -> 0 | ... K1: =DataT14d!L3 -> 0
A2: =DataT14d!B4 -> Region | B2: =DataT14d!C4 -> 1800 Net Foreign Assets | C2: =DataT14d!D4 -> 1980 Net Foreign Assets | D2: =DataT14d!E4 -> 2000 Net Foreign Assets | E2: =DataT14d!F4 -> 2020 Net Foreign Assets | F2: =DataT14d!G4 -> 2025 Net Foreign Assets | G2: =DataT14d!H4 -> 1800 Net Foreign Assets as % of NDP | H2: =DataT14d!I4 -> 1980 Net Foreign Assets as % of NDP | ... K2: =DataT14d!L4 -> 2025 Net Foreign Assets as % of NDP
A3: =DataT14b!B5 -> East Asia | B3: =DataT14b!C5 -> 0 | C3: =DataT14b!D5 -> 68.122398 | D3: =DataT14b!E5 -> 2349.9619 | E3: =DataT14b!F5 -> 16536.516 | F3: =DataT14b!G5 -> 22825.521 | G3: =DataT14b!H5 -> 0 | H3: =DataT14b!I5 -> 0.027053632 | ... K3: =DataT14b!L5 -> 0.51130581
A4: =DataT14b!B6 -> Europe | B4: =DataT14b!C6 -> 0.085437983 | C4: =DataT14b!D6 -> 309.79886 | D4: =DataT14b!E6 -> 491.08875 | E4: =DataT14b!F6 -> 3994.5671 | F4: =DataT14b!G6 -> 8960.9785 | G4: =DataT14b!H6 -> 0.042962994 | H4: =DataT14b!I6 -> 0.096269608 | ... K4: =DataT14b!L6 -> 0.30404478
A5: =DataT14b!B7 -> Latin America | B5: =DataT14b!C7 -> -0.018202538 | C5: =DataT14b!D7 -> -87.79377 | D5: =DataT14b!E7 -> -450.60559 | E5: =DataT14b!F7 -> -6455.3369 | F5: =DataT14b!G7 -> -2223.7742 | G5: =DataT14b!H7 -> -0.14221147 | H5: =DataT14b!I7 -> -0.85415977 | ... K5: =DataT14b!L7 -> -0.16753547
A6: =DataT14b!B8 -> MENA | B6: =DataT14b!C8 -> 0 | C6: =DataT14b!D8 -> 355.46158 | D6: =DataT14b!E8 -> 650.71875 | E6: =DataT14b!F8 -> 6190.1494 | F6: =DataT14b!G8 -> 7717.7554 | G6: =DataT14b!H8 -> 0 | H6: =DataT14b!I8 -> 0.76987451 | ... K6: =DataT14b!L8 -> 0.55097514
A7: =DataT14b!B9 -> North America & Oceania | B7: =DataT14b!C9 -> -0.079358742 | C7: =DataT14b!D9 -> 39.301567 | D7: =DataT14b!E9 -> -1666.6501 | E7: =DataT14b!F9 -> -13532.437 | F7: =DataT14b!G9 -> -24794.818 | G7: =DataT14b!H9 -> -0.19672768 | H7: =DataT14b!I9 -> 0.014173468 | ... K7: =DataT14b!L9 -> -0.82509023
A8: =DataT14b!B10 -> Russia & Central Asia | B8: =DataT14b!C10 -> 0 | C8: =DataT14b!D10 -> -0.00040398675 | D8: =DataT14b!E10 -> 35.721779 | E8: =DataT14b!F10 -> 464.98331 | F8: =DataT14b!G10 -> 1729.9474 | G8: =DataT14b!H10 -> 0 | H8: =DataT14b!I10 -> -0.035078432 | ... K8: =DataT14b!L10 -> 0.19404331
A9: =DataT14b!B11 -> South & South-East Asia | B9: =DataT14b!C11 -> -0.0013392755 | C9: =DataT14b!D11 -> -7.5130191 | D9: =DataT14b!E11 -> -356.12253 | E9: =DataT14b!F11 -> -2020.5356 | F9: =DataT14b!G11 -> -6611.8545 | G9: =DataT14b!H11 -> -0.0013929686 | H9: =DataT14b!I11 -> -0.029723385 | ... K9: =DataT14b!L11 -> -0.21360268
A10: =DataT14b!B12 -> Sub-Saharan Africa | B10: =DataT14b!C12 -> 0 | C10: =DataT14b!D12 -> -23.100807 | D10: =DataT14b!E12 -> -224.18829 | E10: =DataT14b!F12 -> -1071.3224 | F10: =DataT14b!G12 -> -2368.292 | G10: =DataT14b!H12 -> 0 | H10: =DataT14b!I12 -> -0.27958003 | ... K10: =DataT14b!L12 -> -0.33581647
A11: =DataT14b!B13 -> World | B11: =DataT14b!C13 -> -0.013462573 | C11: =DataT14b!D13 -> 654.27637 | D11: =DataT14b!E13 -> 829.92468 | E11: =DataT14b!F13 -> 4106.5845 | F11: =DataT14b!G13 -> 5235.4639 | G11: =DataT14b!H13 -> -0.0016245478 | H11: =DataT14b!I13 -> 0.069538169 | ... K11: =DataT14b!L13 -> 0.029352082
A12: Interpretation. Between 1800 and 2025, the net foreign assets in PPP $ 2025 of Latin America, North America and Oceania, South and South-East Asia, and Sub-Saharan Africa have been consistently negative, in contrast with other regions such as Russia and Central Asia, which reported negative results only around 1980. During the last 5 years, the position of Latin America has strengthened in proportion to Net Domestic Product (NDP), while the deficit of North America and Oceania, South and South-East Asia, and Sub-Saharan Africa has increased as a share of NDP. Sources and series: wid.world

Sheet T14c
A1: =DataT14c!B3 -> Table 14c. Net foreign Assets MER € by World Regions (1980-2025)
A2: =DataT14c!B4 -> Region | B2: =DataT14c!C4 -> 1800 Net Foreign Assets | C2: =DataT14c!D4 -> 1980 Net Foreign Assets | D2: =DataT14c!E4 -> 2000 Net Foreign Assets | E2: =DataT14c!F4 -> 2020 Net Foreign Assets | F2: =DataT14c!G4 -> 2025 Net Foreign Assets | G2: =DataT14c!H4 -> 1800 Net Foreign Assets as % of NDP | H2: =DataT14c!I4 -> 1980 Net Foreign Assets as % of NDP | ... K2: =DataT14c!L4 -> 2025 Net Foreign Assets as % of NDP
A3: =DataT14c!B5 -> East Asia | B3: =DataT14c!C5 -> 0 | C3: =DataT14c!D5 -> 21.657541 | D3: =DataT14c!E5 -> 1876.6206 | E3: =DataT14c!F5 -> 9184.9521 | F3: =DataT14c!G5 -> 10736.9 | G3: =DataT14c!H5 -> 0 | H3: =DataT14c!I5 -> 0.023236325 | ... K3: =DataT14c!L5 -> 0.57225132
A4: =DataT14c!B6 -> Europe | B4: =DataT14c!C6 -> 0.0071272468 | C4: =DataT14c!D6 -> 122.9166 | D4: =DataT14c!E6 -> 492.2644 | E4: =DataT14c!F6 -> 4218.4043 | F4: =DataT14c!G6 -> 7665.4629 | G4: =DataT14c!H6 -> 0.018664513 | H4: =DataT14c!I6 -> 0.049124006 | ... K4: =DataT14c!L6 -> 0.38964489
A5: =DataT14c!B7 -> Latin America | B5: =DataT14c!C7 -> -0.00064793153 | C5: =DataT14c!D7 -> -159.75687 | D5: =DataT14c!E7 -> -612.65118 | E5: =DataT14c!F7 -> -4013.3176 | F5: =DataT14c!G7 -> -545.88129 | G5: =DataT14c!H7 -> -0.036382481 | H5: =DataT14c!I7 -> -0.2671586 | ... K5: =DataT14c!L7 -> -0.096546933
A6: =DataT14c!B8 -> MENA | B6: =DataT14c!C8 -> 0 | C6: =DataT14c!D8 -> 108.43707 | D6: =DataT14c!E8 -> 341.88193 | E6: =DataT14c!F8 -> 2899.6011 | F6: =DataT14c!G8 -> 4178.8159 | G6: =DataT14c!H8 -> 0 | H6: =DataT14c!I8 -> 0.26117891 | ... K6: =DataT14c!L8 -> 0.84199613
A7: =DataT14c!B9 -> North America & Oceania | B7: =DataT14c!C9 -> -0.0051834523 | C7: =DataT14c!D9 -> 14.545067 | D7: =DataT14c!E9 -> -1746.0081 | E7: =DataT14c!F9 -> -11948.712 | F7: =DataT14c!G9 -> -21222.746 | G7: =DataT14c!H9 -> -0.19321911 | H7: =DataT14c!I9 -> 0.0073251049 | ... K7: =DataT14c!L9 -> -0.84829879
A8: =DataT14c!B10 -> Russia & Central Asia | B8: =DataT14c!C10 -> 0 | C8: =DataT14c!D10 -> -17.680599 | D8: =DataT14c!E10 -> 39.958115 | E8: =DataT14c!F10 -> 186.31934 | F8: =DataT14c!G10 -> 579.83051 | G8: =DataT14c!H10 -> 0 | H8: =DataT14c!I10 -> -0.034180421 | ... K8: =DataT14c!L10 -> 0.2132882
A9: =DataT14c!B11 -> South & South-East Asia | B9: =DataT14c!C11 -> -0.0012958631 | C9: =DataT14c!D11 -> -38.59737 | D9: =DataT14c!E11 -> -197.36664 | E9: =DataT14c!F11 -> -59.732872 | F9: =DataT14c!G11 -> -800.7644 | G9: =DataT14c!H11 -> -0.0063463836 | H9: =DataT14c!I11 -> -0.13292915 | ... K9: =DataT14c!L11 -> -0.11287446
A10: =DataT14c!B12 -> Sub-Saharan Africa | B10: =DataT14c!C12 -> 0 | C10: =DataT14c!D12 -> -51.521492 | D10: =DataT14c!E12 -> -194.6982 | E10: =DataT14c!F12 -> -467.5224 | F10: =DataT14c!G12 -> -591.61908 | G10: =DataT14c!H12 -> 0 | H10: =DataT14c!I12 -> -0.16620794 | ... K10: =DataT14c!L12 -> -0.27817076
A11: =DataT14c!B13 -> World | B11: =DataT14c!C13 -> -9.3750001e-11 | C11: =DataT14c!D13 -> -4.0808718e-05 | D11: =DataT14c!E13 -> 0.00096983102 | E11: =DataT14c!F13 -> -0.0075912606 | F11: =DataT14c!G13 -> -0.00069951202 | G11: =DataT14c!H13 -> -9.2435719e-11 | H11: =DataT14c!I13 -> -5.4046594e-09 | ... K11: =DataT14c!L13 -> -8.1328961e-09
A12: Interpretation. Between 1800 and 2025, the net foreign assets in € of Latin America, North America and Oceania, South and South-East Asia, and Sub-Saharan Africa have been consistently negative, in contrast with other regions such as Russia and Central Asia, which reported negative results only around 1980. During the last 5 years, the position of Latin America has strengthened in proportion to Net Domestic Product (NDP), while the deficit of North America and Oceania, South and South-East Asia, and Sub-Saharan Africa has increased as a share of NDP. Sources and series: wid.world

Sheet T14d
A1: =DataT14d!B3 -> Table 14d. Net foreign Assets MER$ by World Regions (1980-2025) | B1: =DataT14d!C3 -> 0 | C1: =DataT14d!D3 -> 0 | D1: =DataT14d!E3 -> 0 | E1: =DataT14d!F3 -> 0 | F1: =DataT14d!G3 -> 0 | G1: =DataT14d!H3 -> 0 | H1: =DataT14d!I3 -> 0 | ... K1: =DataT14d!L3 -> 0
A2: =DataT14d!B4 -> Region | B2: =DataT14d!C4 -> 1800 Net Foreign Assets | C2: =DataT14d!D4 -> 1980 Net Foreign Assets | D2: =DataT14d!E4 -> 2000 Net Foreign Assets | E2: =DataT14d!F4 -> 2020 Net Foreign Assets | F2: =DataT14d!G4 -> 2025 Net Foreign Assets | G2: =DataT14d!H4 -> 1800 Net Foreign Assets as % of NDP | H2: =DataT14d!I4 -> 1980 Net Foreign Assets as % of NDP | ... K2: =DataT14d!L4 -> 2025 Net Foreign Assets as % of NDP
A3: =DataT14d!B5 -> East Asia | B3: =DataT14d!C5 -> 0 | C3: =DataT14d!D5 -> 30.863928 | D3: =DataT14d!E5 -> 1733.2703 | E3: =DataT14d!F5 -> 10491.017 | F3: =DataT14d!G5 -> 12654.902 | G3: =DataT14d!H5 -> 0 | H3: =DataT14d!I5 -> 0.023236325 | ... K3: =DataT14d!L5 -> 0.57225132
A4: =DataT14d!B6 -> Europe | B4: =DataT14d!C6 -> 0.11 | C4: =DataT14d!D6 -> 175.16713 | D4: =DataT14d!E6 -> 454.66156 | E4: =DataT14d!F6 -> 4818.2515 | F4: =DataT14d!G6 -> 9034.7939 | G4: =DataT14d!H6 -> 0.018664513 | H4: =DataT14d!I6 -> 0.049124006 | ... K4: =DataT14d!L6 -> 0.38964486
A5: =DataT14d!B7 -> Latin America | B5: =DataT14d!C7 -> -0.0099999998 | C5: =DataT14d!D7 -> -227.66777 | D5: =DataT14d!E7 -> -565.85229 | E5: =DataT14d!F7 -> -4583.9956 | F5: =DataT14d!G7 -> -643.39557 | G5: =DataT14d!H7 -> -0.036382481 | H5: =DataT14d!I7 -> -0.2671586 | ... K5: =DataT14d!L7 -> -0.096546933
A6: =DataT14d!B8 -> MENA | B6: =DataT14d!C8 -> 0 | C6: =DataT14d!D8 -> 154.5325 | D6: =DataT14d!E8 -> 315.76642 | E6: =DataT14d!F8 -> 3311.9131 | F6: =DataT14d!G8 -> 4925.3052 | G6: =DataT14d!H8 -> 0 | H6: =DataT14d!I8 -> 0.26117891 | ... K6: =DataT14d!L8 -> 0.84199613
A7: =DataT14d!B9 -> North America & Oceania | B7: =DataT14d!C9 -> -0.079999998 | C7: =DataT14d!D9 -> 20.72802 | D7: =DataT14d!E9 -> -1612.6349 | E7: =DataT14d!F9 -> -13647.771 | F7: =DataT14d!G9 -> -25013.902 | G7: =DataT14d!H9 -> -0.19321913 | H7: =DataT14d!I9 -> 0.0073251063 | ... K7: =DataT14d!L9 -> -0.84829891
A8: =DataT14d!B10 -> Russia & Central Asia | B8: =DataT14d!C10 -> 0 | C8: =DataT14d!D10 -> -25.196432 | D8: =DataT14d!E10 -> 36.905811 | E8: =DataT14d!F10 -> 212.8132 | F8: =DataT14d!G10 -> 683.40942 | G8: =DataT14d!H10 -> 0 | H8: =DataT14d!I10 -> -0.034180421 | ... K8: =DataT14d!L10 -> 0.21328822
A9: =DataT14d!B11 -> South & South-East Asia | B9: =DataT14d!C11 -> -0.02 | C9: =DataT14d!D11 -> -55.004696 | D9: =DataT14d!E11 -> -182.29031 | E9: =DataT14d!F11 -> -68.2267 | F9: =DataT14d!G11 -> -943.81012 | G9: =DataT14d!H11 -> -0.0063463836 | H9: =DataT14d!I11 -> -0.13292915 | ... K9: =DataT14d!L11 -> -0.11287445
A10: =DataT14d!B12 -> Sub-Saharan Africa | B10: =DataT14d!C12 -> 0 | C10: =DataT14d!D12 -> -73.422722 | D10: =DataT14d!E12 -> -179.82568 | E10: =DataT14d!F12 -> -534.00226 | F10: =DataT14d!G12 -> -697.30383 | G10: =DataT14d!H12 -> 0 | H10: =DataT14d!I12 -> -0.16620795 | ... K10: =DataT14d!L12 -> -0.27817076
A11: =DataT14d!B13 -> World | B11: =DataT14d!C13 -> 0 | C11: =DataT14d!D13 -> -3.9979062e-05 | D11: =DataT14d!E13 -> 0.00091011601 | E11: =DataT14d!F13 -> -0.0017970989 | F11: =DataT14d!G13 -> -0.00161579 | G11: =DataT14d!H13 -> 0 | H11: =DataT14d!I13 -> -3.7154031e-09 | ... K11: =DataT14d!L13 -> -1.5938781e-08
A12: Interpretation. Between 1800 and 2025, the net foreign assets in $ of Latin America, North America and Oceania, South and South-East Asia, and Sub-Saharan Africa have been consistently negative, in contrast with other regions such as Russia and Central Asia, which reported negative results only around 1980. During the last 5 years, the position of Latin America has strengthened in proportion to Net Domestic Product (NDP), while the deficit of North America and Oceania, South and South-East Asia, and Sub-Saharan Africa has increased as a share of NDP. Sources and series: wid.world

Sheet T15a
A1: =DataT15a!B2 -> Table 15a. National Non-financial Assets by World Region PPP € (2025)
B2: =DataT15a!C3 -> PPP 2025 billions € | E2: =DataT15a!F3 -> % of Gross Domestic Product
A3: =DataT13d!B4 -> Region | B3: =DataT15a!C4 -> National housing assets | C3: =DataT15a!D4 -> National business and other non-financial assets | D3: =DataT15a!E4 -> National non-financial assets | E3: =DataT15a!F4 -> National housing assets as % of Gross Domestic Product | F3: =DataT15a!G4 -> National business and other non-financial assets as % of Gross Domestic Product | G3: =DataT15a!H4 -> National non-financial assets as % of Gross Domestic Product
A4: =DataT15a!B5 -> East Asia | B4: =DataT15a!C5 -> 96105.14 | C4: =DataT15a!D5 -> 148915.13 | D4: =DataT15a!E5 -> 245020.27 | E4: =DataT15a!F5 -> 2.5766756 | F4: =DataT15a!G5 -> 3.9925648 | G4: =DataT15a!H5 -> 6.5692404
A5: =DataT15a!B6 -> Europe | B5: =DataT15a!C6 -> 77970.539 | C5: =DataT15a!D6 -> 38980.765 | D5: =DataT15a!E6 -> 116951.3 | E5: =DataT15a!F6 -> 3.2330475 | F5: =DataT15a!G6 -> 1.616337 | G5: =DataT15a!H6 -> 4.8493845 | K5: =C4/D4 -> 0.60776658
A6: =DataT15a!B7 -> Latin America | B6: =DataT15a!C7 -> 21894.716 | C6: =DataT15a!D7 -> 18247.138 | D6: =DataT15a!E7 -> 40141.853 | E6: =DataT15a!F7 -> 2.121156 | F6: =DataT15a!G7 -> 1.7677793 | G6: =DataT15a!H7 -> 3.8889353 | K6: =C5/D5 -> 0.33330766
A7: =DataT15a!B8 -> MENA | B7: =DataT15a!C8 -> 19751.902 | C7: =DataT15a!D8 -> 29460.231 | D7: =DataT15a!E8 -> 49212.133 | E7: =DataT15a!F8 -> 1.8511566 | F7: =DataT15a!G8 -> 2.7610253 | G7: =DataT15a!H8 -> 4.6121819 | K7: =C6/D6 -> 0.4545664
A8: =DataT15a!B9 -> North America & Oceania | B8: =DataT15a!C9 -> 52577.841 | C8: =DataT15a!D9 -> 95108.991 | D8: =DataT15a!E9 -> 147686.83 | E8: =DataT15a!F9 -> 2.151612 | F8: =DataT15a!G9 -> 3.8920891 | G8: =DataT15a!H9 -> 6.0437011 | K8: =C7/D7 -> 0.59863755
A9: =DataT15a!B10 -> Russia & Central Asia | B9: =DataT15a!C10 -> 10858.049 | C9: =DataT15a!D10 -> 15421.551 | D9: =DataT15a!E10 -> 26279.6 | E9: =DataT15a!F10 -> 1.5486451 | F9: =DataT15a!G10 -> 2.1995213 | G9: =DataT15a!H10 -> 3.7481665 | K9: =C8/D8 -> 0.643991
A10: =DataT15a!B11 -> South & South-East Asia | B10: =DataT15a!C11 -> 65427.441 | C10: =DataT15a!D11 -> 45576.377 | D10: =DataT15a!E11 -> 111003.82 | E10: =DataT15a!F11 -> 2.7557036 | F10: =DataT15a!G11 -> 1.9196072 | G10: =DataT15a!H11 -> 4.6753108 | K10: =C9/D9 -> 0.58682595
A11: =DataT15a!B12 -> Sub-Saharan Africa | B11: =DataT15a!C12 -> 8096.046 | C11: =DataT15a!D12 -> 10525.042 | D11: =DataT15a!E12 -> 18621.088 | E11: =DataT15a!F12 -> 1.5279187 | F11: =DataT15a!G12 -> 1.9863288 | G11: =DataT15a!H12 -> 3.5142475 | K11: =C10/D10 -> 0.41058387
A12: =DataT15a!B13 -> World | B12: =DataT15a!C13 -> 352681.67 | C12: =DataT15a!D13 -> 402235.23 | D12: =DataT15a!E13 -> 754916.9 | E12: =DataT15a!F13 -> 2.4680995 | F12: =DataT15a!G13 -> 2.81488 | G12: =DataT15a!H13 -> 5.2829795 | K12: =C11/D11 -> 0.56522165
A13: Interpretation. In 2025, the world's national non-financial assets amounted to around €755 trillion (PPP 2025), equivalent to approximately 5,3 times global GDP. East Asia accounted for around 32% of total non-financial assets, with €245 trillion (PPP 2025), equivalent to approximately 5,6 times the region's GDP. It was followed, at a considerable distance, by North America and Oceania and Europe, with around €148 trillion and €117 trillion (PPP 2025), respectively. By contrast, Sub-Saharan Africa accounted for only €18 trillion (PPP 2025), or 2,5% of global non-financial assets, and also recorded the lowest level relative to GDP, at around 3,5 times regional GDP. These differences are largely explained by the level of national business and other non-financial assets, which account for less than half of total non-financial assets in South and South-East Asia and Latin America, although their shares remain above 40%. Europe stands out in this respect, with national business and other non-financial assets amounting to €39 trillion (PPP 2025), or only 33% of its total non-financial assets. Sources and series: wid.world

Sheet T15b
A1: =DataT15b!B2 -> Table 15b. National Non-financial Assets by World Region PPP $ (2025)
B2: =DataT15b!C3 -> PPP 2025 billions $ | E2: =DataT15b!F3 -> % of Gross Domestic Product
A3: =DataT13d!B4 -> Region | B3: =DataT15a!C4 -> National housing assets | C3: =DataT15a!D4 -> National business and other non-financial assets | D3: =DataT15a!E4 -> National non-financial assets | E3: =DataT15a!F4 -> National housing assets as % of Gross Domestic Product | F3: =DataT15a!G4 -> National business and other non-financial assets as % of Gross Domestic Product | G3: =DataT15a!H4 -> National non-financial assets as % of Gross Domestic Product
A4: =DataT15b!B5 -> East Asia | B4: =DataT15b!C5 -> 141746.98 | C4: =DataT15b!D5 -> 219637.26 | D4: =DataT15b!E5 -> 361384.25 | E4: =DataT15b!F5 -> 2.5766757 | F4: =DataT15b!G5 -> 3.9925645 | G4: =DataT15b!H5 -> 6.5692404
A5: =DataT15b!B6 -> Europe | B5: =DataT15b!C6 -> 114999.97 | C5: =DataT15b!D6 -> 57493.341 | D5: =DataT15b!E6 -> 172493.31 | E5: =DataT15b!F6 -> 3.2330475 | F5: =DataT15b!G6 -> 1.616337 | G5: =DataT15b!H6 -> 4.8493845
A6: =DataT15b!B7 -> Latin America | B6: =DataT15b!C7 -> 32292.858 | C6: =DataT15b!D7 -> 26912.989 | D6: =DataT15b!E7 -> 59205.846 | E6: =DataT15b!F7 -> 2.121156 | F6: =DataT15b!G7 -> 1.7677793 | G6: =DataT15b!H7 -> 3.8889353
A7: =DataT15b!B8 -> MENA | B7: =DataT15b!C8 -> 29132.389 | C7: =DataT15b!D8 -> 43451.356 | D7: =DataT15b!E8 -> 72583.747 | E7: =DataT15b!F8 -> 1.8511566 | F7: =DataT15b!G8 -> 2.7610253 | G7: =DataT15b!H8 -> 4.6121819
A8: =DataT15b!B9 -> North America & Oceania | B8: =DataT15b!C9 -> 77547.883 | C8: =DataT15b!D9 -> 140277.74 | D8: =DataT15b!E9 -> 217825.62 | E8: =DataT15b!F9 -> 2.151612 | F8: =DataT15b!G9 -> 3.892089 | G8: =DataT15b!H9 -> 6.043701
A9: =DataT15b!B10 -> Russia & Central Asia | B9: =DataT15b!C10 -> 16014.706 | C9: =DataT15b!D10 -> 22745.487 | D9: =DataT15b!E10 -> 38760.192 | E9: =DataT15b!F10 -> 1.5486451 | F9: =DataT15b!G10 -> 2.1995214 | G9: =DataT15b!H10 -> 3.7481663
A10: =DataT15b!B11 -> South & South-East Asia | B10: =DataT15b!C11 -> 96499.957 | C10: =DataT15b!D11 -> 67221.314 | D10: =DataT15b!E11 -> 163721.27 | E10: =DataT15b!F11 -> 2.7557035 | F10: =DataT15b!G11 -> 1.9196072 | G10: =DataT15b!H11 -> 4.6753107
A11: =DataT15b!B12 -> Sub-Saharan Africa | B11: =DataT15b!C12 -> 11940.985 | C11: =DataT15b!D12 -> 15523.55 | D11: =DataT15b!E12 -> 27464.535 | E11: =DataT15b!F12 -> 1.5279187 | F11: =DataT15b!G12 -> 1.9863288 | G11: =DataT15b!H12 -> 3.5142475
A12: =DataT15b!B13 -> World | B12: =DataT15b!C13 -> 520175.73 | C12: =DataT15b!D13 -> 593263.04 | D12: =DataT15b!E13 -> 1113438.8 | E12: =DataT15b!F13 -> 2.4680995 | F12: =DataT15b!G13 -> 2.8148799 | G12: =DataT15b!H13 -> 5.2829795
A13: Interpretation. In 2025, the world's national non-financial assets amounted to around $1 113 trillion (PPP 2025), equivalent to approximately 5,3 times global GDP. East Asia accounted for around 32% of total non-financial assets, with $361 trillion (PPP 2025), equivalent to approximately 5,6 times the region's GDP. It was followed, at a considerable distance, by North America and Oceania and Europe, with around $217 trillion and $172 trillion (PPP 2025), respectively. By contrast, Sub-Saharan Africa accounted for only $27 trillion (PPP 2025), or 2,5% of global non-financial assets, and also recorded the lowest level relative to GDP, at around 3,5 times regional GDP. These differences are largely explained by the level of national business and other non-financial assets, which account for less than half of total non-financial assets in South and South-East Asia and Latin America, although their shares remain above 40%. Europe stands out in this respect, with national business and other non-financial assets amounting to $57 trillion (PPP 2025), or only 33% of its total non-financial assets. Sources and series: wid.world

Sheet T15c
A1: =DataT15c!B2 -> Table 15c. National Non-financial Assets by World Region MER € (2025)
B2: =DataT15c!C3 -> Billions € | E2: =DataT15c!F3 -> % of Gross Domestic Product
A3: =DataT13d!B4 -> Region | B3: =DataT15a!C4 -> National housing assets | C3: =DataT15a!D4 -> National business and other non-financial assets | D3: =DataT15a!E4 -> National non-financial assets | E3: =DataT15a!F4 -> National housing assets as % of Gross Domestic Product | F3: =DataT15a!G4 -> National business and other non-financial assets as % of Gross Domestic Product | G3: =DataT15a!H4 -> National non-financial assets as % of Gross Domestic Product
A4: =DataT15c!B5 -> East Asia | B4: =DataT15c!C5 -> 59575.59 | C4: =DataT15c!D5 -> 91546.253 | D4: =DataT15c!E5 -> 151121.85 | E4: =DataT15c!F5 -> 2.5661873 | F4: =DataT15c!G5 -> 3.9433068 | G4: =DataT15c!H5 -> 6.5094944
A5: =DataT15c!B6 -> Europe | B5: =DataT15c!C6 -> 77389.936 | C5: =DataT15c!D6 -> 37689.071 | D5: =DataT15c!E6 -> 115079.01 | E5: =DataT15c!F6 -> 3.2515925 | F5: =DataT15c!G6 -> 1.5835328 | G5: =DataT15c!H6 -> 4.8351252
A6: =DataT15c!B7 -> Latin America | B6: =DataT15c!C7 -> 13780.236 | C6: =DataT15c!D7 -> 11172.814 | D6: =DataT15c!E7 -> 24953.049 | E6: =DataT15c!F7 -> 2.1212515 | F6: =DataT15c!G7 -> 1.7198797 | G6: =DataT15c!H7 -> 3.8411311
A7: =DataT15c!B8 -> MENA | B7: =DataT15c!C8 -> 10586.133 | C7: =DataT15c!D8 -> 16036.847 | D7: =DataT15c!E8 -> 26622.979 | E7: =DataT15c!F8 -> 1.8875146 | F7: =DataT15c!G8 -> 2.8593807 | G7: =DataT15c!H8 -> 4.7468952
A8: =DataT15c!B9 -> North America & Oceania | B8: =DataT15c!C9 -> 64059.977 | C8: =DataT15c!D9 -> 117527.39 | D8: =DataT15c!E9 -> 181587.36 | E8: =DataT15c!F9 -> 2.1341489 | F8: =DataT15c!G9 -> 3.9154079 | G8: =DataT15c!H9 -> 6.0495566
A9: =DataT15c!B10 -> Russia & Central Asia | B9: =DataT15c!C10 -> 4868.6403 | C9: =DataT15c!D10 -> 6939.6745 | D9: =DataT15c!E10 -> 11808.315 | E9: =DataT15c!F10 -> 1.5457944 | F9: =DataT15c!G10 -> 2.2033482 | G9: =DataT15c!H10 -> 3.7491426
A10: =DataT15c!B11 -> South & South-East Asia | B10: =DataT15c!C11 -> 21843.173 | C10: =DataT15c!D11 -> 14600.049 | D10: =DataT15c!E11 -> 36443.222 | E10: =DataT15c!F11 -> 2.7109849 | F10: =DataT15c!G11 -> 1.8120313 | G10: =DataT15c!H11 -> 4.5230162
A11: =DataT15c!B12 -> Sub-Saharan Africa | B11: =DataT15c!C12 -> 3469.0411 | C11: =DataT15c!D12 -> 4404.8449 | D11: =DataT15c!E12 -> 7873.8861 | E11: =DataT15c!F12 -> 1.4722214 | F11: =DataT15c!G12 -> 1.8693658 | G11: =DataT15c!H12 -> 3.3415873
A12: =DataT15c!B13 -> World | B12: =DataT15c!C13 -> 255572.73 | C12: =DataT15c!D13 -> 299916.94 | D12: =DataT15c!E13 -> 555489.67 | E12: =DataT15c!F13 -> 2.4885157 | F12: =DataT15c!G13 -> 2.920296 | G12: =DataT15c!H13 -> 5.4088118
A13: Interpretation. In 2025, the world's national non-financial assets amounted to around €555 trillion, equivalent to approximately 5,4 times global GDP. North America and Oceania accounted for around 33% of total non-financial assets, with €181 trillion, equivalent to approximately 6 times the region's GDP. It was followed, at a considerable distance, by East Asia and Europe, with around €151 trillion and €115 trillion, respectively. By contrast, Sub-Saharan Africa accounted for only €8 trillion, or 1,4% of global non-financial assets, and also recorded the lowest level relative to GDP, at around 3,3 times regional GDP. These differences are largely explained by the level of national business and other non-financial assets, which account for less than half of total non-financial assets in South and South-East Asia and Latin America, although their shares remain above 40%. Europe stands out in this respect, with national business and other non-financial assets amounting to €38 trillion, or only 33% of its total non-financial assets. Sources and series: wid.world

Sheet T15d
A1: =DataT15d!B2 -> Table 15d. National Non-financial Assets by World Region MER $ (2025)
B2: =DataT15d!C3 -> Billions $ | E2: =DataT15d!F3 -> % of Gross Domestic Product
A3: =DataT13d!B4 -> Region | B3: =DataT15a!C4 -> National housing assets | C3: =DataT15a!D4 -> National business and other non-financial assets | D3: =DataT15a!E4 -> National non-financial assets | E3: =DataT15a!F4 -> National housing assets as % of Gross Domestic Product | F3: =DataT15a!G4 -> National business and other non-financial assets as % of Gross Domestic Product | G3: =DataT15a!H4 -> National non-financial assets as % of Gross Domestic Product
A4: =DataT15d!B5 -> East Asia | B4: =DataT15d!C5 -> 70217.963 | C4: =DataT15d!D5 -> 107899.75 | D4: =DataT15d!E5 -> 178117.71 | E4: =DataT15d!F5 -> 2.5661873 | F4: =DataT15d!G5 -> 3.9433068 | G4: =DataT15d!H5 -> 6.5094943
A5: =DataT15d!B6 -> Europe | B5: =DataT15d!C6 -> 91214.601 | C5: =DataT15d!D6 -> 44421.715 | D5: =DataT15d!E6 -> 135636.32 | E5: =DataT15d!F6 -> 3.2515924 | F5: =DataT15d!G6 -> 1.5835328 | G5: =DataT15d!H6 -> 4.8351253
A6: =DataT15d!B7 -> Latin America | B6: =DataT15d!C7 -> 16241.888 | C6: =DataT15d!D7 -> 13168.686 | D6: =DataT15d!E7 -> 29410.573 | E6: =DataT15d!F7 -> 2.1212515 | F6: =DataT15d!G7 -> 1.7198798 | G6: =DataT15d!H7 -> 3.8411312
A7: =DataT15d!B8 -> MENA | B7: =DataT15d!C8 -> 12477.202 | C7: =DataT15d!D8 -> 18901.613 | D7: =DataT15d!E8 -> 31378.815 | E7: =DataT15d!F8 -> 1.8875145 | F7: =DataT15d!G8 -> 2.8593806 | G7: =DataT15d!H8 -> 4.7468951
A8: =DataT15d!B9 -> North America & Oceania | B8: =DataT15d!C9 -> 75503.423 | C8: =DataT15d!D9 -> 138522.06 | D8: =DataT15d!E9 -> 214025.48 | E8: =DataT15d!F9 -> 2.1341489 | F8: =DataT15d!G9 -> 3.9154079 | G8: =DataT15d!H9 -> 6.0495568
A9: =DataT15d!B10 -> Russia & Central Asia | B9: =DataT15d!C10 -> 5738.357 | C9: =DataT15d!D10 -> 8179.3535 | D9: =DataT15d!E10 -> 13917.711 | E9: =DataT15d!F10 -> 1.5457944 | F9: =DataT15d!G10 -> 2.2033482 | G9: =DataT15d!H10 -> 3.7491428
A10: =DataT15d!B11 -> South & South-East Asia | B10: =DataT15d!C11 -> 25745.16 | C10: =DataT15d!D11 -> 17208.15 | D10: =DataT15d!E11 -> 42953.31 | E10: =DataT15d!F11 -> 2.7109849 | F10: =DataT15d!G11 -> 1.8120313 | G10: =DataT15d!H11 -> 4.5230162
A11: =DataT15d!B12 -> Sub-Saharan Africa | B11: =DataT15d!C12 -> 4088.7383 | C11: =DataT15d!D12 -> 5191.7109 | D11: =DataT15d!E12 -> 9280.4492 | E11: =DataT15d!F12 -> 1.4722214 | F11: =DataT15d!G12 -> 1.8693658 | G11: =DataT15d!H12 -> 3.3415872
A12: =DataT15d!B13 -> World | B12: =DataT15d!C13 -> 301227.33 | C12: =DataT15d!D13 -> 353493.03 | D12: =DataT15d!E13 -> 654720.37 | E12: =DataT15d!F13 -> 2.4885157 | F12: =DataT15d!G13 -> 2.920296 | G12: =DataT15d!H13 -> 5.4088118
A13: Interpretation. In 2025, the world's national non-financial assets amounted to around $655 trillion, equivalent to approximately 5,4 times global GDP. North America and Oceania accounted for around 33% of total non-financial assets, with $214 trillion, equivalent to approximately 6 times the region's GDP. It was followed, at a considerable distance, by East Asia and Europe, with around $178 trillion and $135 trillion, respectively. By contrast, Sub-Saharan Africa accounted for only $9 trillion, or 1,4% of global non-financial assets, and also recorded the lowest level relative to GDP, at around 3,3 times regional GDP. These differences are largely explained by the level of national business and other non-financial assets, which account for less than half of total non-financial assets in South and South-East Asia and Latin America, although their shares remain above 40%. Europe stands out in this respect, with national business and other non-financial assets amounting to $44 trillion, or only 33% of its total non-financial assets. Sources and series: wid.world

Sheet T16a
A1: =DataT16a!B2 -> Table 16a. National Capital shares by World Region PPP € (2025) | B1: =DataT16a!C2 -> 0 | C1: =DataT16a!D2 -> 0 | D1: =DataT16a!E2 -> 0 | E1: =DataT16a!F2 -> 0 | F1: =DataT16a!G2 -> 0 | G1: =DataT16a!H2 -> 0 | H1: =DataT16a!I2 -> 0 | ... L1: =DataT16a!M2 -> 0
B2: =DataT16a!C3 -> PPP 2025 billions € | C2: =DataT16a!D3 -> % of GDP | D2: =DataT16a!E3 -> PPP 2025 billions € | E2: =DataT16a!F3 -> 0 | F2: =DataT16a!G3 -> 0 | G2: =DataT16a!H3 -> 0 | H2: =DataT16a!I3 -> % of sector Gross Value Added | I2: =DataT16a!J3 -> 0 | ... L2: =DataT16a!M3 -> 0
B3: =DataT16a!C4 -> Gross domestic product at factor-price | C3: =DataT16a!D4 -> Gross domestic product at factor-price as % of GDP | D3: =DataT16a!E4 -> Gross operating surplus of the government | E3: =DataT16a!F4 -> Gross value added of the corporate sector | F3: =DataT16a!G4 -> Gross mixed income of household sector | G3: =DataT16a!H4 -> Gross operating surplus of household sector | H3: =DataT16a!I4 -> Capital share in the total Economy | I3: =DataT16a!J4 -> Capital share in the government | ... L3: =DataT16a!M4 -> Capital share in the operating surplus of household sector
A4: =DataT16a!B5 -> East Asia | B4: =DataT16a!C5 -> 34422.474 | C4: =DataT16a!D5 -> 0.9229012 | D4: =DataT16a!E5 -> 695.79177 | E4: =DataT16a!F5 -> 11739.232 | F4: =DataT16a!G5 -> 4756.5883 | G4: =DataT16a!H5 -> 2702.6604 | H4: =DataT16a!I5 -> 0.49503472 | ... L4: =DataT16a!M5 -> 0.33290578
A5: =DataT16a!B6 -> Europe | B5: =DataT16a!C6 -> 21505.111 | C5: =DataT16a!D6 -> 0.89170919 | D5: =DataT16a!E6 -> 633.57898 | E5: =DataT16a!F6 -> 5993.4136 | F5: =DataT16a!G6 -> 2030.5754 | G5: =DataT16a!H6 -> 1545.9744 | H5: =DataT16a!I6 -> 0.41781682 | ... L5: =DataT16a!M6 -> 0.35379214
A6: =DataT16a!B7 -> Latin America | B6: =DataT16a!C7 -> 9032.3285 | C6: =DataT16a!D7 -> 0.87505032 | D6: =DataT16a!E7 -> 158.84138 | E6: =DataT16a!F7 -> 3088.3059 | F6: =DataT16a!G7 -> 1468.3627 | G6: =DataT16a!H7 -> 661.96931 | H6: =DataT16a!I7 -> 0.49781867 | ... L6: =DataT16a!M7 -> 0.2599799
A7: =DataT16a!B8 -> MENA | B7: =DataT16a!C8 -> 9819.8234 | C7: =DataT16a!D8 -> 0.920318 | D7: =DataT16a!E8 -> 177.41741 | E7: =DataT16a!F8 -> 4434.0787 | F7: =DataT16a!G8 -> 1657.9901 | G7: =DataT16a!H8 -> 611.20192 | H7: =DataT16a!I8 -> 0.599389 | ... L7: =DataT16a!M8 -> 0.23942812
A8: =DataT16a!B9 -> North America & Oceania | B8: =DataT16a!C9 -> 23089.543 | C8: =DataT16a!D9 -> 0.94487973 | D8: =DataT16a!E9 -> 893.6719 | E8: =DataT16a!F9 -> 5618.7544 | F8: =DataT16a!G9 -> 3298.8293 | G8: =DataT16a!H9 -> 1674.74 | H8: =DataT16a!I9 -> 0.41173176 | ... L8: =DataT16a!M9 -> 0.2394373
A9: =DataT16a!B10 -> Russia & Central Asia | B9: =DataT16a!C10 -> 6241.1367 | C9: =DataT16a!D10 -> 0.89015127 | D9: =DataT16a!E10 -> 224.14987 | E9: =DataT16a!F10 -> 2216.8356 | F9: =DataT16a!G10 -> 537.50705 | G9: =DataT16a!H10 -> 338.19205 | H9: =DataT16a!I10 -> 0.4797492 | ... L9: =DataT16a!M10 -> 0.34765938
A10: =DataT16a!B11 -> South & South-East Asia | B10: =DataT16a!C11 -> 21807.427 | C10: =DataT16a!D11 -> 0.91849545 | D10: =DataT16a!E11 -> 520.63367 | E10: =DataT16a!F11 -> 6189.7953 | F10: =DataT16a!G11 -> 5064.2308 | G10: =DataT16a!H11 -> 1834.8088 | H10: =DataT16a!I11 -> 0.4847399 | ... L10: =DataT16a!M11 -> 0.21887385
A11: =DataT16a!B12 -> Sub-Saharan Africa | B11: =DataT16a!C12 -> 4917.3082 | C11: =DataT16a!D12 -> 0.9280144 | D11: =DataT16a!E12 -> 104.48952 | E11: =DataT16a!F12 -> 1391.1884 | F11: =DataT16a!G12 -> 1583.522 | G11: =DataT16a!H12 -> 342.35024 | H11: =DataT16a!I12 -> 0.50259957 | ... L11: =DataT16a!M12 -> 0.16266194
A12: =DataT16a!B13 -> World | B12: =DataT16a!C13 -> 130835.15 | C12: =DataT16a!D13 -> 0.9155967 | D12: =DataT16a!E13 -> 3408.5745 | E12: =DataT16a!F13 -> 40671.604 | F12: =DataT16a!G13 -> 20397.606 | G12: =DataT16a!H13 -> 9711.8971 | H12: =DataT16a!I13 -> 0.47350515 | ... L12: =DataT16a!M13 -> 0.26946066
A13: Interpretation. In 2025 the World Gross Domestic Product at factor-price amounted to around €131 trillion (PPP 2025), representing 92% of world GDP at market prices. In this context, the capital share of the economy - defined as the sum of the gross operating surplus of the government, corporate, and household sectors, plus 40% of gross mixed income, divided by GDP at factor-price - amounted to around 47% of GDP at factor-price. At a regional level, Middle East and North Africa (MENA) leads the ranking with a capital share of 60%, driven by a 73% share in the corporate sector (this is the gross operative surplus of the corported sector divied by Gross value added of the coportate sector), contrasting with the total 41% total capital share of North America & Oceania, dragged down by a capital share in the corporate sector of only 42%. Sources and series: wid.world

Sheet T16b
A1: =DataT16b!B2 -> Table 16b. National Capital shares by World Region PPP $ (2025) | B1: =DataT16b!C2 -> 0 | C1: =DataT16b!D2 -> 0 | D1: =DataT16b!E2 -> 0 | E1: =DataT16b!F2 -> 0 | F1: =DataT16b!G2 -> 0 | G1: =DataT16b!H2 -> 0 | H1: =DataT16b!I2 -> 0 | ... L1: =DataT16b!M2 -> 0
B2: =DataT16b!C3 -> PPP 2025 billions $ | C2: =DataT16b!D3 -> % of GDP | D2: =DataT16b!E3 -> PPP 2025 billions $ | E2: =DataT16b!F3 -> 0 | F2: =DataT16b!G3 -> 0 | G2: =DataT16b!H3 -> 0 | H2: =DataT16b!I3 -> % of sector Gross Value Added | I2: =DataT16b!J3 -> 0 | ... L2: =DataT16b!M3 -> 0
B3: =DataT16b!C4 -> Gross domestic product at factor-price | C3: =DataT16b!D4 -> Gross domestic product at factor-price as % of GDP | D3: =DataT16b!E4 -> Gross operating surplus of the government | E3: =DataT16b!F4 -> Gross value added of the corporate sector | F3: =DataT16b!G4 -> Gross mixed income of household sector | G3: =DataT16b!H4 -> Gross operating surplus of household sector | H3: =DataT16b!I4 -> Capital share in the total Economy | I3: =DataT16b!J4 -> Capital share in the government | ... L3: =DataT16b!M4 -> Capital share in the operating surplus of household sector
A4: =DataT16b!B5 -> East Asia | B4: =DataT16b!C5 -> 50770.246 | C4: =DataT16b!D5 -> 0.92290117 | D4: =DataT16b!E5 -> 1026.2342 | E4: =DataT16b!F5 -> 17314.378 | F4: =DataT16b!G5 -> 7015.5671 | G4: =DataT16b!H5 -> 3986.1963 | H4: =DataT16b!I5 -> 0.49503473 | ... L4: =DataT16b!M5 -> 0.33290579
A5: =DataT16b!B6 -> Europe | B5: =DataT16b!C6 -> 31718.225 | C5: =DataT16b!D6 -> 0.8917092 | D5: =DataT16b!E6 -> 934.47555 | E5: =DataT16b!F6 -> 8839.7794 | F5: =DataT16b!G6 -> 2994.9274 | G5: =DataT16b!H6 -> 2280.1818 | H5: =DataT16b!I6 -> 0.41781681 | ... L5: =DataT16b!M6 -> 0.35379214
A6: =DataT16b!B7 -> Latin America | B6: =DataT16b!C7 -> 13321.923 | C6: =DataT16b!D7 -> 0.87505034 | D6: =DataT16b!E7 -> 234.27765 | E6: =DataT16b!F7 -> 4554.9908 | F6: =DataT16b!G7 -> 2165.7111 | G6: =DataT16b!H7 -> 976.34892 | H6: =DataT16b!I7 -> 0.49781867 | ... L6: =DataT16b!M7 -> 0.2599799
A7: =DataT16b!B8 -> MENA | B7: =DataT16b!C8 -> 14483.412 | C7: =DataT16b!D8 -> 0.92031801 | D7: =DataT16b!E8 -> 261.67573 | E7: =DataT16b!F8 -> 6539.8923 | F7: =DataT16b!G8 -> 2445.3957 | G7: =DataT16b!H8 -> 901.47128 | H7: =DataT16b!I8 -> 0.599389 | ... L7: =DataT16b!M8 -> 0.23942812
A8: =DataT16b!B9 -> North America & Oceania | B8: =DataT16b!C9 -> 34055.126 | C8: =DataT16b!D9 -> 0.94487965 | D8: =DataT16b!E9 -> 1318.0906 | E8: =DataT16b!F9 -> 8287.1887 | F8: =DataT16b!G9 -> 4865.4949 | G8: =DataT16b!H9 -> 2470.1003 | H8: =DataT16b!I9 -> 0.41173178 | ... L8: =DataT16b!M9 -> 0.23943732
A9: =DataT16b!B10 -> Russia & Central Asia | B9: =DataT16b!C10 -> 9205.1503 | C9: =DataT16b!D10 -> 0.89015128 | D9: =DataT16b!E10 -> 330.60214 | E9: =DataT16b!F10 -> 3269.6456 | F9: =DataT16b!G10 -> 792.77759 | G9: =DataT16b!H10 -> 498.80475 | H9: =DataT16b!I10 -> 0.47974921 | ... L9: =DataT16b!M10 -> 0.34765939
A10: =DataT16b!B11 -> South & South-East Asia | B10: =DataT16b!C11 -> 32164.118 | C10: =DataT16b!D11 -> 0.91849547 | D10: =DataT16b!E11 -> 767.89079 | E10: =DataT16b!F11 -> 9129.4263 | F10: =DataT16b!G11 -> 7469.3135 | G10: =DataT16b!H11 -> 2706.1883 | H10: =DataT16b!I11 -> 0.48473989 | ... L10: =DataT16b!M11 -> 0.21887385
A11: =DataT16b!B12 -> Sub-Saharan Africa | B11: =DataT16b!C12 -> 7252.6153 | C11: =DataT16b!D12 -> 0.92801443 | D11: =DataT16b!E12 -> 154.11323 | E11: =DataT16b!F12 -> 2051.8857 | F11: =DataT16b!G12 -> 2335.5615 | G11: =DataT16b!H12 -> 504.93773 | H11: =DataT16b!I12 -> 0.50259956 | ... L11: =DataT16b!M12 -> 0.16266193
A12: =DataT16b!B13 -> World | B12: =DataT16b!C13 -> 192970.81 | C12: =DataT16b!D13 -> 0.91559668 | D12: =DataT16b!E13 -> 5027.3599 | E12: =DataT16b!F13 -> 59987.187 | F12: =DataT16b!G13 -> 30084.749 | G12: =DataT16b!H13 -> 14324.229 | H12: =DataT16b!I13 -> 0.47350516 | ... L12: =DataT16b!M13 -> 0.26946067
A13: Interpretation. In 2025 the World Gross Domestic Product at factor-price amounted to around $193 trillion (PPP 2025), representing 92% of world GDP at market prices. In this context, the capital share of the economy - defined as the sum of the gross operating surplus of the government, corporate, and household sectors, plus 40% of gross mixed income, divided by GDP at factor-price - amounted to around 47% of GDP at factor-price. At a regional level, Middle East and North Africa (MENA) leads the ranking with a capital share of 60%, driven by a 73% share in the corporate sector (this is the gross operative surplus of the corported sector divied by Gross value added of the coportate sector), contrasting with the total 41% total capital share of North America & Oceania, dragged down by a capital share in the corporate sector of only 42%. Sources and series: wid.world

Sheet T16c
A1: =DataT16c!B2 -> Table 16c. National Capital shares by World Region MER € (2025) | B1: =DataT16c!C2 -> 0 | C1: =DataT16c!D2 -> 0 | D1: =DataT16c!E2 -> 0 | E1: =DataT16c!F2 -> 0 | F1: =DataT16c!G2 -> 0 | G1: =DataT16c!H2 -> 0 | H1: =DataT16c!I2 -> 0 | ... L1: =DataT16c!M2 -> 0
B2: =DataT16c!C3 -> Billions € | C2: =DataT16c!D3 -> % of GDP | D2: =DataT16c!E3 -> Billions € | E2: =DataT16c!F3 -> 0 | F2: =DataT16c!G3 -> 0 | G2: =DataT16c!H3 -> 0 | H2: =DataT16c!I3 -> % of sector Gross Value Added | I2: =DataT16c!J3 -> 0 | ... L2: =DataT16c!M3 -> 0
B3: =DataT16c!C4 -> Gross domestic product at factor-price | C3: =DataT16c!D4 -> Gross domestic product at factor-price as % of GDP | D3: =DataT16c!E4 -> Gross operating surplus of the government | E3: =DataT16c!F4 -> Gross value added of the corporate sector | F3: =DataT16c!G4 -> Gross mixed income of household sector | G3: =DataT16c!H4 -> Gross operating surplus of household sector | H3: =DataT16c!I4 -> Capital share in the total Economy | I3: =DataT16c!J4 -> Capital share in the government | ... L3: =DataT16c!M4 -> Capital share in the operating surplus of household sector
A4: =DataT16c!B5 -> East Asia | B4: =DataT16c!C5 -> 21452.418 | C4: =DataT16c!D5 -> 0.92405166 | D4: =DataT16c!E5 -> 449.77817 | E4: =DataT16c!F5 -> 7324.2233 | F4: =DataT16c!G5 -> 2820.1321 | G4: =DataT16c!H5 -> 1665.5366 | H4: =DataT16c!I5 -> 0.49260604 | ... L4: =DataT16c!M5 -> 0.33991949
A5: =DataT16c!B6 -> Europe | B5: =DataT16c!C6 -> 21265.326 | C5: =DataT16c!D6 -> 0.89347758 | D5: =DataT16c!E6 -> 624.38073 | E5: =DataT16c!F6 -> 5914.9805 | F5: =DataT16c!G6 -> 1904.6053 | G5: =DataT16c!H6 -> 1534.9534 | H5: =DataT16c!I6 -> 0.41551946 | ... L5: =DataT16c!M6 -> 0.36315259
A6: =DataT16c!B7 -> Latin America | B6: =DataT16c!C7 -> 5694.3637 | C6: =DataT16c!D7 -> 0.87655812 | D6: =DataT16c!E7 -> 101.67389 | E6: =DataT16c!F7 -> 1967.619 | F6: =DataT16c!G7 -> 922.5159 | G6: =DataT16c!H7 -> 421.24541 | H6: =DataT16c!I7 -> 0.50217105 | ... L6: =DataT16c!M7 -> 0.26253934
A7: =DataT16c!B8 -> MENA | B7: =DataT16c!C8 -> 5141.6624 | C7: =DataT16c!D8 -> 0.91676189 | D7: =DataT16c!E8 -> 101.08265 | E7: =DataT16c!F8 -> 2333.3023 | F7: =DataT16c!G8 -> 793.78272 | G7: =DataT16c!H8 -> 326.1967 | H7: =DataT16c!I8 -> 0.59865748 | ... L7: =DataT16c!M8 -> 0.26688004
A8: =DataT16c!B9 -> North America & Oceania | B8: =DataT16c!C9 -> 28399.088 | C8: =DataT16c!D9 -> 0.94611151 | D8: =DataT16c!E9 -> 1104.9421 | E8: =DataT16c!F9 -> 6903.6829 | F8: =DataT16c!G9 -> 4062.618 | G8: =DataT16c!H9 -> 2082.3292 | H8: =DataT16c!I9 -> 0.41254851 | ... L8: =DataT16c!M9 -> 0.24025486
A9: =DataT16c!B10 -> Russia & Central Asia | B9: =DataT16c!C10 -> 2800.2796 | C9: =DataT16c!D10 -> 0.88908941 | D9: =DataT16c!E10 -> 103.27392 | E9: =DataT16c!F10 -> 985.50639 | F9: =DataT16c!G10 -> 231.02755 | G9: =DataT16c!H10 -> 151.89518 | H9: =DataT16c!I10 -> 0.47605478 | ... L9: =DataT16c!M10 -> 0.35584387
A10: =DataT16c!B11 -> South & South-East Asia | B10: =DataT16c!C11 -> 7425.3271 | C10: =DataT16c!D11 -> 0.92156711 | D10: =DataT16c!E11 -> 172.52857 | E10: =DataT16c!F11 -> 2182.0047 | F10: =DataT16c!G11 -> 1631.5208 | G10: =DataT16c!H11 -> 613.68416 | H10: =DataT16c!I11 -> 0.48763181 | ... L10: =DataT16c!M11 -> 0.22516202
A11: =DataT16c!B12 -> Sub-Saharan Africa | B11: =DataT16c!C12 -> 2156.1156 | C11: =DataT16c!D12 -> 0.91503082 | D11: =DataT16c!E12 -> 46.809682 | E11: =DataT16c!F12 -> 563.42904 | F11: =DataT16c!G12 -> 702.22477 | G11: =DataT16c!H12 -> 132.36876 | H11: =DataT16c!I12 -> 0.47469505 | ... L11: =DataT16c!M12 -> 0.14246219
A12: =DataT16c!B13 -> World | B12: =DataT16c!C13 -> 94334.581 | C12: =DataT16c!D13 -> 0.91853732 | D12: =DataT16c!E13 -> 2704.4697 | E12: =DataT16c!F13 -> 28174.748 | F12: =DataT16c!G13 -> 13068.427 | G12: =DataT16c!H13 -> 6928.2093 | H12: =DataT16c!I13 -> 0.45619324 | ... L12: =DataT16c!M13 -> 0.28047154
A13: Interpretation. In 2025 the World Gross Domestic Product at factor-price amounted to around €94 trillion, representing 92% of world GDP at market prices. In this context, the capital share of the economy - defined as the sum of the gross operating surplus of the government, corporate, and household sectors, plus 40% of gross mixed income, divided by GDP at factor-price - amounted to around 46% of GDP at factor-price. At a regional level, Middle East and North Africa (MENA) leads the ranking with a capital share of 60%, driven by a 71% share in the corporate sector (the gross operating surplus of the corporate sector divided by the gross value added of the corporate sector), contrasting with the total capital share of North America & Oceania at 41%, dragged down by a capital share in the corporate sector of 43%, the second-lowest globally, only surpassed by Europe's 42%. Sources and series: wid.world

Sheet T16d
A1: =DataT16d!B2 -> Table 16d. National Capital shares by World Region MER $ (2025) | B1: =DataT16d!C2 -> 0 | C1: =DataT16d!D2 -> 0 | D1: =DataT16d!E2 -> 0 | E1: =DataT16d!F2 -> 0 | F1: =DataT16d!G2 -> 0 | G1: =DataT16d!H2 -> 0 | H1: =DataT16d!I2 -> 0 | ... L1: =DataT16d!M2 -> 0
B2: =DataT16d!C3 -> Billions $ | C2: =DataT16d!D3 -> % of GDP | D2: =DataT16d!E3 -> Billions $ | E2: =DataT16d!F3 -> 0 | F2: =DataT16d!G3 -> 0 | G2: =DataT16d!H3 -> 0 | H2: =DataT16d!I3 -> % of sector Gross Value Added | I2: =DataT16d!J3 -> 0 | ... L2: =DataT16d!M3 -> 0
B3: =DataT16d!C4 -> Gross domestic product at factor-price | C3: =DataT16d!D4 -> Gross domestic product at factor-price as % of GDP | D3: =DataT16d!E4 -> Gross operating surplus of the government | E3: =DataT16d!F4 -> Gross value added of the corporate sector | F3: =DataT16d!G4 -> Gross mixed income of household sector | G3: =DataT16d!H4 -> Gross operating surplus of household sector | H3: =DataT16d!I4 -> Capital share in the total Economy | I3: =DataT16d!J4 -> Capital share in the government | ... L3: =DataT16d!M4 -> Capital share in the operating surplus of household sector
A4: =DataT16d!B5 -> East Asia | B4: =DataT16d!C5 -> 25284.602 | C4: =DataT16d!D5 -> 0.92405166 | D4: =DataT16d!E5 -> 530.12494 | E4: =DataT16d!F5 -> 8632.5965 | F4: =DataT16d!G5 -> 3323.9106 | G4: =DataT16d!H5 -> 1963.0622 | H4: =DataT16d!I5 -> 0.49260605 | ... L4: =DataT16d!M5 -> 0.3399195
A5: =DataT16d!B6 -> Europe | B5: =DataT16d!C6 -> 25064.089 | C5: =DataT16d!D6 -> 0.89347759 | D5: =DataT16d!E6 -> 735.9179 | E5: =DataT16d!F6 -> 6971.6118 | F5: =DataT16d!G6 -> 2244.8372 | G5: =DataT16d!H6 -> 1809.1521 | H5: =DataT16d!I6 -> 0.41551946 | ... L5: =DataT16d!M6 -> 0.36315259
A6: =DataT16d!B7 -> Latin America | B6: =DataT16d!C7 -> 6711.5848 | C6: =DataT16d!D7 -> 0.87655816 | D6: =DataT16d!E7 -> 119.83655 | E6: =DataT16d!F7 -> 2319.1075 | F6: =DataT16d!G7 -> 1087.3109 | G6: =DataT16d!H7 -> 496.49521 | H6: =DataT16d!I7 -> 0.50217105 | ... L6: =DataT16d!M7 -> 0.26253935
A7: =DataT16d!B8 -> MENA | B7: =DataT16d!C8 -> 6060.1511 | C7: =DataT16d!D8 -> 0.91676189 | D7: =DataT16d!E8 -> 119.1397 | E7: =DataT16d!F8 -> 2750.1151 | F7: =DataT16d!G8 -> 935.58128 | G7: =DataT16d!H8 -> 384.46734 | H7: =DataT16d!I8 -> 0.59865746 | ... L7: =DataT16d!M8 -> 0.26688005
A8: =DataT16d!B9 -> North America & Oceania | B8: =DataT16d!C9 -> 33472.199 | C8: =DataT16d!D9 -> 0.9461115 | D8: =DataT16d!E9 -> 1302.325 | E8: =DataT16d!F9 -> 8136.9319 | F8: =DataT16d!G9 -> 4788.3495 | G8: =DataT16d!H9 -> 2454.3091 | H8: =DataT16d!I9 -> 0.41254852 | ... L8: =DataT16d!M9 -> 0.24025488
A9: =DataT16d!B10 -> Russia & Central Asia | B9: =DataT16d!C10 -> 3300.5117 | C9: =DataT16d!D10 -> 0.88908941 | D9: =DataT16d!E10 -> 121.72239 | E9: =DataT16d!F10 -> 1161.5538 | F9: =DataT16d!G10 -> 272.2975 | G9: =DataT16d!H10 -> 179.0292 | H9: =DataT16d!I10 -> 0.47605478 | ... L9: =DataT16d!M10 -> 0.35584387
A10: =DataT16d!B11 -> South & South-East Asia | B10: =DataT16d!C11 -> 8751.7615 | C10: =DataT16d!D11 -> 0.92156714 | D10: =DataT16d!E11 -> 203.34846 | E10: =DataT16d!F11 -> 2571.7902 | F10: =DataT16d!G11 -> 1922.9699 | G10: =DataT16d!H11 -> 723.31051 | H10: =DataT16d!I11 -> 0.4876318 | ... L10: =DataT16d!M11 -> 0.22516201
A11: =DataT16d!B12 -> Sub-Saharan Africa | B11: =DataT16d!C12 -> 2541.2764 | C11: =DataT16d!D12 -> 0.9150308 | D11: =DataT16d!E12 -> 55.171599 | E11: =DataT16d!F12 -> 664.078 | F11: =DataT16d!G12 -> 827.66772 | G11: =DataT16d!H12 -> 156.01465 | H11: =DataT16d!I12 -> 0.47469505 | ... L11: =DataT16d!M12 -> 0.14246219
A12: =DataT16d!B13 -> World | B12: =DataT16d!C13 -> 111186.17 | C12: =DataT16d!D13 -> 0.91853732 | D12: =DataT16d!E13 -> 3187.5865 | E12: =DataT16d!F13 -> 33207.785 | F12: =DataT16d!G13 -> 15402.925 | G12: =DataT16d!H13 -> 8165.8403 | H12: =DataT16d!I13 -> 0.45619324 | ... L12: =DataT16d!M13 -> 0.28047155
A13: Interpretation. In 2025 the World Gross Domestic Product at factor-price amounted to around $111 trillion, representing 92% of world GDP at market prices. In this context, the capital share of the economy - defined as the sum of the gross operating surplus of the government, corporate, and household sectors, plus 40% of gross mixed income, divided by GDP at factor-price - amounted to around 46% of GDP at factor-price. At a regional level, Middle East and North Africa (MENA) leads the ranking with a capital share of 60%, driven by a 71% share in the corporate sector (the gross operating surplus of the corporate sector divided by the gross value added of the corporate sector), contrasting with the total capital share of North America & Oceania at 41%, dragged down by a capital share in the corporate sector of 43%, the second-lowest globally, only surpassed by Europe's 42%. Sources and series: wid.world

Sheet Appendix1
A3: Name of Country | B3: Per capita national income (PPP 2025 €) | C3: Income decile | D3: Region | E3: Total national income (PPP 2025 €) | F3: Population 2025 (millions) | G3: Country code | H3: Net Foreign Income (PPP 2025 €) | I3: Net Foreign Capital Income (PPP 2025 €) | J3: Net Foreign Labor Income (PPP 2025 €) | K3: Net Foreign Wealth (PPP 2025 €) | L3: Net Domestic Product (PPP 2025 €) | M3: GDP (PPP 2025 €) | N3: GDP (PPP 2025 $) | O3: GDP (€) | P3: GDP ($) | Q3: Ratio MER/PPP Per Capita National Income (2025 €) | R3: Ratio MER/PPP Per Capita National Income (2025 $) | S3: Ratio MER/PPP Per Capita National Income (2021 €) | T3: Ratio MER/PPP Per Capita National Income (2021 $) | U3: Net Foreign Income as % of National Disposable Income | V3: Net Foreign Transfers as % of the National Disposable Income
A4: Monaco | B4: 169163.17 | C4: 90%-100% | D4: Europe | E4: 6485884928 | F4: 38341 | G4: MC | H4: -2635004928 | I4: -2688736768 | J4: -11238426 | K4: 99965444096 | L4: 9120889856 | M4: 11422899200 | N4: 16847813632 | O4: 11420002304 | P4: 13460031488 | Q4: 0.99974638 | R4: 0.7989186 | S4: 1.0346941 | T4: 0.83258408 | U4: -0.4106777 | V4: -0.010855217
A5: Liechtenstein | B5: 147878.45 | C5: 90%-100% | D5: Europe | E5: 5934066688 | F5: 40128 | G5: LI | H5: 1116934528 | I5: 1305211392 | J5: -12201865 | K5: 69156864000 | L5: 4817132032 | M5: 5764568576 | N5: 8502253056 | O5: 8152464896 | P5: 9608792064 | Q5: 1.4142368 | R5: 1.1301466 | S5: 1.4370357 | T5: 1.1563351 | U5: 0.18934566 | V5: -0.0059584999
A6: Luxembourg | B6: 127784.85 | C6: 90%-100% | D6: Europe | E6: 86951583744 | F6: 680453 | G6: LU | H6: 27893823488 | I6: 39816540160 | J6: -11925958656 | K6: 404244365312 | L6: 59057758208 | M6: 69475926016 | N6: 102471131136 | O6: 89522200576 | P6: 105514131456 | Q6: 1.2885356 | R6: 1.0296962 | S6: 1.2263348 | T6: 0.98679107 | U6: 0.31631157 | V6: 0.013982761
A7: Bermuda | B7: 126080.46 | C7: 90%-100% | D7: North America & Oceania | E7: 8139124224 | F7: 64555 | G7: BM | H7: 3009701888 | I7: 1982366208 | J7: 936577408 | K7: 260002430976 | L7: 5129422336 | M7: 5399391744 | N7: 7963647488 | O7: 7728161792 | P7: 9108692992 | Q7: 1.4313023 | R7: 1.143784 | S7: 1.5179735 | T7: 1.2214632 | U7: 0.37599546 | V7: -0.016802937
A8: Guernsey | B8: 125533.95 | C8: 90%-100% | D8: Europe | E8: 8094052864 | F8: 64477 | G8: GG | H8: 3894073344 | I8: 3873055232 | J8: -6143264.5 | K8: 136834605056 | L8: 4199979520 | M8: 5005654528 | N8: 7382918656 | O8: 5936060928 | P8: 6996457984 | Q8: 1.185871 | R8: 0.94765478 | S8: 1.1433886 | T8: 0.92004704 | U8: 0.48277125 | V8: -0.0034674967
A9: Jersey | B9: 121734.24 | C9: 90%-100% | D9: Europe | E9: 12659021824 | F9: 103989 | G9: JE | H9: 5971734016 | I9: 5938406400 | J9: -9654247 | K9: 145862279168 | L9: 6687287808 | M9: 7961007104 | N9: 11741813760 | O9: 9440727040 | P9: 11127186432 | Q9: 1.185871 | R9: 0.94765478 | S9: 1.1433886 | T9: 0.92004704 | U9: 0.47340086 | V9: -0.0035262618
A10: Singapore | B10: 107491.48 | C10: 90%-100% | D10: South & South-East Asia | E10: 631055646720 | F10: 5870750 | G10: SG | H10: 66965573632 | I10: 71294427136 | J10: -4106567424 | K10: 1253698961408 | L10: 564090044416 | M10: 667098021888 | N10: 983913267200 | O10: 503649501184 | P10: 593619714048 | Q10: 0.75498581 | R10: 0.60332519 | S10: 0.75020152 | T10: 0.60366237 | U10: 0.105956 | V10: 0.0015147639
A11: Cayman Islands | B11: 101096.93 | C11: 90%-100% | D11: Latin America | E11: 7667595776 | F11: 75844 | G11: KY | H11: 3143677184 | I11: 3162051328 | J11: -44994576 | K11: -308550172672 | L11: 4523918336 | M11: 4905377792 | N11: 7235018240 | O11: 6868285440 | P11: 8095212032 | Q11: 1.4001544 | R11: 1.1188931 | S11: 1.4486872 | T11: 1.1657107 | U11: 0.39541999 | V11: 0.035549682
A12: Gibraltar | B12: 86012.516 | C12: 90%-100% | D12: Europe | E12: 3451338240 | F12: 40126 | G12: GI | H12: 935415424 | I12: 922787520 | J12: -3551318 | K12: 20421632000 | L12: 2515922688 | M12: 2996204800 | N12: 4419149312 | O12: 3553112576 | P12: 4187827968 | Q12: 1.185871 | R12: 0.94765478 | S12: 1.1433886 | T12: 0.92004704 | U12: 0.26327324 | V12: 0.028618788
A13: Macao | B13: 78176.766 | C13: 90%-100% | D13: East Asia | E13: 56444170240 | F13: 722007 | G13: MO | H13: 2939763968 | I13: 5833635328 | J13: -3078751232 | K13: 219241398272 | L13: 53504405504 | M13: 63747739648 | N13: 94022541312 | O13: 43861221376 | P13: 51696435200 | Q13: 0.68804359 | R13: 0.54983026 | S13: 0.76021987 | T13: 0.61172384 | U13: 0.056573655 | V13: -0.086227722
A14: Anguilla | B14: 73980.734 | C14: 90%-100% | D14: Latin America | E14: 1089588224 | F14: 14728 | G14: AI | H14: -37522444 | I14: -41481080 | J14: 215971.06 | K14: -1905376128 | L14: 1127110784 | M14: 1328113792 | N14: 1958855808 | O14: 411254400 | P14: 484719456 | Q14: 0.30965298 | R14: 0.24745029 | S14: 0.30789548 | T14: 0.24775332 | U14: -0.036218405 | V14: -0.051721144
A15: Norway | B15: 70146.875 | C15: 90%-100% | D15: Europe | E15: 394440867840 | F15: 5623071 | G15: NO | H15: 54407671808 | I15: 58597707776 | J15: -5090473472 | K15: 1391784755200 | L15: 340033175552 | M15: 407300505600 | N15: 600733908992 | O15: 448300744704 | P15: 528383606784 | Q15: 1.1006633 | R15: 0.87956345 | S15: 1.2998536 | T15: 1.0459492 | U15: 0.13942356 | V15: -0.010783047
... A219: Burundi | B219: 622.83752 | C219: 0%-10% | D219: Sub-Saharan Africa | E219: 8962633728 | F219: 14390003 | G219: BI | H219: -88164864 | I219: -126779984 | J219: 27826902 | K219: -7880659968 | L219: 9050798080 | M219: 10833367040 | N219: 15978302464 | O219: 5342335488 | P219: 6296671744 | Q219: 0.49313712 | R219: 0.39407638 | S219: 0.38339996 | T219: 0.30850926 | U219: -0.0090293428 | V219: 0.082098126

Sheet DataF0a
A1: Data series used for the figures on exchange rates and PPP euro/dollar and euro/yuan
C4: Exchange rate euro/dollar | D4: Purchasing power parity euro/dollar | E4: Exchange rate euro/yuan | F4: Purchasing power parity euro/yuan
B5: 1990 | C5: 1.3198069 | D5: 1.372208 | E5: 6.3129115 | F5: 1.6601443
B6: 1991 | C6: 1.2800217 | D6: 1.363212 | E6: 6.8140564 | F6: 1.7430335
B7: 1992 | C7: 1.3417661 | D7: 1.3375367 | E7: 7.3992925 | F7: 1.8872715
B8: 1993 | C8: 1.1998588 | D8: 1.3276162 | E8: 6.9135361 | F8: 2.1704929
B9: 1994 | C9: 1.2030994 | D9: 1.3274263 | E9: 10.369205 | F9: 2.6680019
B10: 1995 | C10: 1.30858 | D10: 1.3234214 | E10: 10.928497 | F10: 2.8944542
B11: 1996 | C11: 1.2878896 | D11: 1.3258107 | E11: 10.707739 | F11: 3.2167997
B12: 1997 | C12: 1.1299685 | D12: 1.3335083 | E12: 9.3672323 | F12: 3.2970531
B13: 1998 | C13: 1.1125753 | D13: 1.3308794 | E13: 9.2109642 | F13: 3.4617131
B14: 1999 | C14: 1.0657765 | D14: 1.3378733 | E14: 8.8227634 | F14: 3.4397454
B15: 2000 | C15: 0.92361248 | D15: 1.3533812 | E15: 7.6461301 | F15: 3.5399935
B16: 2001 | C16: 0.89562958 | D16: 1.3523477 | E16: 7.413187 | F16: 3.5765097
... B40: 2025 | C40: 1.1786364 | D40: 1.4749156 | E40: 8.4438696 | F40: 5.0082645

Sheet DataF1
A1: Data series used for the figure on average income across world regions (national income per capita, PPP € 2025)
C4: World | D4: Europe | E4: North America/ Oceania | F4: Latin America | G4: Middle East/North Africa | H4: Subsaharan Africa | I4: Russia/ Central Asia | J4: East Asia | K4: South & South-East Asia | L4: DE | M4: DK | N4: ES | O4: FR | P4: GB | Q4: IT | R4: NL | S4: NO | T4: SE | U4: OC | V4: QM | W4: US | X4: CA | Y4: AU | Z4: NZ | AA4: OH | AB4: AR | AC4: BR | AD4: CL | AE4: CO | AF4: MX | AG4: OD | AH4: AE | AI4: DZ | AJ4: EG | AK4: IR | AL4: MA | AM4: SA | AN4: TR | AO4: OE | AP4: CD | AQ4: CI | AR4: ET | AS4: KE | AT4: ML | AU4: NE | AV4: NG | AW4: RW | AX4: SD | AY4: ZA | AZ4: OJ | BA4: RU | BB4: OA | BC4: CN | BD4: JP | BE4: KR | BF4: TW | BG4: OB | BH4: BD | BI4: IN | BJ4: ID | BK4: MM | BL4: PK | BM4: PH | BN4: TH | BO4: VN | BP4: OI
B5: 1800 | C5: 730.17249 | D5: 1370.3827 | E5: 1283.8405 | F5: 843.06177 | G5: 640.56012 | H5: 623.88971 | I5: 630.09674 | J5: 751.17542 | K5: 785.30469 | L5: 1810.4558 | M5: 1648.1161 | N5: 1585.5116 | O5: 1256.853 | P5: 2975.6355 | Q5: 2109.2439 | R5: 2572.5249 | S5: 1622.7782 | T5: 1089.9889 | U5: 1593.2117 | V5: 646.91724 | W5: 1777.0096 | X5: 1000.8845 | Y5: 847.40851 | Z5: 761.20264 | AA5: 311.58298 | AB5: 976.75232 | AC5: 722.03461 | AD5: 600.43573 | AE5: 832.60352 | AF5: 1052.4484 | AG5: 544.88599 | AH5: 448.92169 | AI5: 642.2785 | AJ5: 804.67749 | AK5: 502.86456 | AL5: 505.73511 | AM5: 1031.3004 | AN5: 602.97614 | AO5: 1014.0021 | AP5: 905.35327 | AQ5: 627.01978 | AR5: 510.57071 | AS5: 729.5686 | AT5: 671.06805 | AU5: 659.45825 | AV5: 686.46362 | AW5: 391.74356 | AX5: 329.47675 | AY5: 2048.5669 | AZ5: 272.44897 | BA5: 807.11578 | BB5: 655.97595 | BC5: 745.72699 | BD5: 807.88416 | BE5: 564.92633 | BF5: 762.37421 | BG5: 1452.4775 | BH5: 1152.0449 | BI5: 810.90027 | BJ5: 562.22858 | BK5: 320.77966 | BL5: 908.58966 | BM5: 884.09906 | BN5: 791.96613 | BO5: 636.47589 | BP5: 1532.6392
B6: 1801 | C6: 731.59656 | D6: 1378.3745 | E6: 1306.819 | F6: 836.7926 | G6: 643.39349 | H6: 623.86426 | I6: 630.32019 | J6: 749.06488 | K6: 784.45795 | L6: 1804.6395 | M6: 1651.1864 | N6: 1626.6403 | O6: 1230.1875 | P6: 3085.0505 | Q6: 2109.7273 | R6: 2532.3577 | S6: 1626.0266 | T6: 1079.86 | U6: 1601.667 | V6: 650.00055 | W6: 1801.3029 | X6: 1003.0456 | Y6: 847.14874 | Z6: 760.9693 | AA6: 314.48196 | AB6: 979.82855 | AC6: 721.42517 | AD6: 586.33307 | AE6: 829.57135 | AF6: 1046.4512 | AG6: 535.26807 | AH6: 451.15591 | AI6: 644.5412 | AJ6: 807.52264 | AK6: 504.64264 | AL6: 506.86499 | AM6: 1043.5991 | AN6: 605.77789 | AO6: 1018.366 | AP6: 905.74176 | AQ6: 627.28882 | AR6: 510.79001 | AS6: 729.96051 | AT6: 671.3559 | AU6: 659.74115 | AV6: 686.75812 | AW6: 391.91183 | AX6: 329.61813 | AY6: 2042.8281 | AZ6: 272.45035 | BA6: 807.39795 | BB6: 656.20538 | BC6: 743.44006 | BD6: 807.34192 | BE6: 564.75317 | BF6: 762.14038 | BG6: 1448.3745 | BH6: 1148.2666 | BI6: 810.35992 | BJ6: 562.0412 | BK6: 320.61929 | BL6: 905.60968 | BM6: 884.56366 | BN6: 791.5705 | BO6: 636.26385 | BP6: 1530.1538
B7: 1802 | C7: 736.70184 | D7: 1404.8837 | E7: 1323.4177 | F7: 823.62665 | G7: 646.03821 | H7: 623.85211 | I7: 630.37366 | J7: 747.01953 | K7: 780.72278 | L7: 1820.7906 | M7: 1654.0316 | N7: 1609.743 | O7: 1256.6569 | P7: 3225.417 | Q7: 2106.3601 | R7: 2668.2783 | S7: 1628.7371 | T7: 1130.8357 | U7: 1628.7759 | V7: 660.77081 | W7: 1815.4171 | X7: 1005.2605 | Y7: 846.93005 | Z7: 760.77283 | AA7: 317.27051 | AB7: 982.73743 | AC7: 720.49414 | AD7: 582.41028 | AE7: 841.22894 | AF7: 1026.5723 | AG7: 518.95972 | AH7: 453.42322 | AI7: 646.69653 | AJ7: 810.01727 | AK7: 506.20154 | AL7: 507.90717 | AM7: 1056.095 | AN7: 608.43115 | AO7: 1022.4355 | AP7: 906.17371 | AQ7: 627.58856 | AR7: 511.03381 | AS7: 730.14227 | AT7: 671.6767 | AU7: 660.05646 | AV7: 687.0863 | AW7: 392.09891 | AX7: 329.77594 | AY7: 2036.7423 | AZ7: 272.46497 | BA7: 807.46283 | BB7: 656.25806 | BC7: 741.19598 | BD7: 807.13385 | BE7: 564.60736 | BF7: 761.94397 | BG7: 1444.093 | BH7: 1144.1946 | BI7: 805.52472 | BJ7: 561.75488 | BK7: 320.37366 | BL7: 902.39825 | BM7: 884.52881 | BN7: 790.96362 | BO7: 635.93909 | BP7: 1522.7681
B8: 1803 | C8: 737.75116 | D8: 1412.5326 | E8: 1348.8091 | F8: 816.69806 | G8: 648.82776 | H8: 623.87598 | I8: 630.52899 | J8: 745.02069 | K8: 777.16394 | L8: 1827.601 | M8: 1656.9806 | N8: 1523.3563 | O8: 1289.6423 | P8: 3262.2383 | Q8: 2112.0493 | R8: 2612.1968 | S8: 1631.6842 | T8: 1119.7118 | U8: 1636.0386 | V8: 663.46954 | W8: 1842.968 | X8: 1007.5344 | Y8: 846.75745 | Z8: 760.61786 | AA8: 320.04236 | AB8: 985.76294 | AC8: 719.75635 | AD8: 574.10071 | AE8: 846.0379 | AF8: 1018.0983 | AG8: 507.96634 | AH8: 455.72614 | AI8: 648.92853 | AJ8: 812.73566 | AK8: 507.90033 | AL8: 509.00565 | AM8: 1068.7981 | AN8: 611.19257 | AO8: 1026.7131 | AP8: 906.65594 | AQ8: 627.92194 | AR8: 511.30527 | AS8: 730.39276 | AT8: 672.03357 | AU8: 660.40704 | AV8: 687.45129 | AW8: 392.30719 | AX8: 329.95078 | AY8: 2030.8918 | AZ8: 272.49405 | BA8: 807.65796 | BB8: 656.41663 | BC8: 738.9989 | BD8: 806.96948 | BE8: 564.49237 | BF8: 761.78851 | BG8: 1439.9763 | BH8: 1140.3198 | BI8: 800.88922 | BJ8: 561.52747 | BK8: 320.17932 | BL8: 899.34229 | BM8: 884.72705 | BN8: 790.48389 | BO8: 635.68219 | BP8: 1515.6669
B9: 1804 | C9: 742.5943 | D9: 1438.7714 | E9: 1361.2887 | F9: 808.17889 | G9: 652.09125 | H9: 620.66205 | I9: 631.78571 | J9: 743.18805 | K9: 774.20874 | L9: 1833.384 | M9: 1659.9126 | N9: 1567.8715 | O9: 1334.0698 | P9: 3326.5471 | Q9: 2117.7083 | R9: 2734.8975 | S9: 1634.585 | T9: 1047.1 | U9: 1666.182 | V9: 675.59485 | W9: 1850.3248 | X9: 1010.027 | Y9: 846.76361 | Z9: 760.62335 | AA9: 322.87701 | AB9: 989.21497 | AC9: 719.7818 | AD9: 570.91895 | AE9: 856.79816 | AF9: 998.78156 | AG9: 502.88745 | AH9: 458.13651 | AI9: 651.44073 | AJ9: 816.31976 | AK9: 510.14011 | AL9: 510.32016 | AM9: 1081.8799 | AN9: 614.35297 | AO9: 1031.7728 | AP9: 907.32703 | AQ9: 628.38672 | AR9: 511.68372 | AS9: 731.03448 | AT9: 672.53094 | AU9: 660.89587 | AV9: 687.96021 | AW9: 392.5976 | AX9: 330.19504 | AY9: 1956.3853 | AZ9: 271.17255 | BA9: 809.26404 | BB9: 657.72192 | BC9: 736.96381 | BD9: 806.9754 | BE9: 564.4964 | BF9: 761.79401 | BG9: 1436.476 | BH9: 1137.1726 | BI9: 796.94873 | BJ9: 561.53558 | BK9: 320.18625 | BL9: 896.86005 | BM9: 884.87598 | BN9: 790.50104 | BO9: 635.69141 | BP9: 1509.5575
B10: 1805 | C10: 746.4071 | D10: 1463.4163 | E10: 1382.4811 | F10: 797.65417 | G10: 654.68927 | H10: 615.84155 | I10: 631.94928 | J10: 741.15424 | K10: 770.43103 | L10: 1748.9912 | M10: 1662.7537 | N10: 1721.4377 | O10: 1417.2319 | P10: 3350.3518 | Q10: 2118.6511 | R10: 2573.3716 | S10: 1637.2629 | T10: 1113.2094 | U10: 1695.4722 | V10: 687.24677 | W10: 1870.9607 | X10: 1012.2148 | Y10: 846.50983 | Z10: 760.39532 | AA10: 325.54117 | AB10: 992.06738 | AC10: 718.69855 | AD10: 567.71124 | AE10: 869.65625 | AF10: 984.49744 | AG10: 487.15643 | AH10: 460.41977 | AI10: 653.56482 | AJ10: 818.66748 | AK10: 511.60733 | AL10: 511.32669 | AM10: 1094.7889 | AN10: 616.96576 | AO10: 1035.752 | AP10: 907.7215 | AQ10: 628.66052 | AR10: 511.90695 | AS10: 731.26105 | AT10: 672.82397 | AU10: 661.18378 | AV10: 688.25983 | AW10: 392.76883 | AX10: 330.33923 | AY10: 1852.2462 | AZ10: 269.18585 | BA10: 809.4696 | BB10: 657.88916 | BC10: 734.70874 | BD10: 807.02716 | BE10: 564.32721 | BF10: 761.56567 | BG10: 1432.1488 | BH10: 1132.9977 | BI10: 792.06024 | BJ10: 561.20221 | BK10: 319.90045 | BL10: 893.56744 | BM10: 884.75598 | BN10: 789.79578 | BO10: 635.31342 | BP10: 1502.1073
B11: 1806 | C11: 750.90308 | D11: 1486.6042 | E11: 1394.625 | F11: 790.07611 | G11: 657.97455 | H11: 616.2348 | I11: 632.49176 | J11: 739.3468 | K11: 767.61029 | L11: 1762.4623 | M11: 1665.6854 | N11: 1811.8375 | O11: 1490.4401 | P11: 3309.5728 | Q11: 2118.03 | R11: 2592.0605 | S11: 1640.1488 | T11: 1125.9763 | U11: 1723.584 | V11: 698.55231 | W11: 1877.6559 | X11: 1014.7109 | Y11: 846.50916 | Z11: 760.39484 | AA11: 328.20404 | AB11: 995.52777 | AC11: 718.6969 | AD11: 561.59265 | AE11: 875.86346 | AF11: 967.59119 | AG11: 482.32474 | AH11: 462.85135 | AI11: 656.08472 | AJ11: 822.24634 | AK11: 513.84381 | AL11: 512.6391 | AM11: 1108.1802 | AN11: 620.14154 | AO11: 1040.8348 | AP11: 908.388 | AQ11: 629.12152 | AR11: 512.28186 | AS11: 731.86578 | AT11: 673.31738 | AU11: 661.6687 | AV11: 688.76459 | AW11: 393.05646 | AX11: 330.58112 | AY11: 1852.2438 | AZ11: 269.36508 | BA11: 810.16162 | BB11: 658.45111 | BC11: 732.67963 | BD11: 807.02643 | BE11: 564.32678 | BF11: 761.56506 | BG11: 1428.667 | BH11: 1129.844 | BI11: 788.13843 | BJ11: 561.20154 | BK11: 319.90018 | BL11: 891.08026 | BM11: 892.41455 | BN11: 789.79437 | BO11: 635.31323 | BP11: 1496.0432
B12: 1807 | C12: 752.69775 | D12: 1495.4689 | E12: 1411.4203 | F12: 778.20184 | G12: 661.25073 | H12: 624.28046 | I12: 633.0246 | J12: 737.53644 | K12: 764.67938 | L12: 1764.6334 | M12: 1668.6133 | N12: 1835.0903 | O12: 1573.0037 | P12: 3227.8169 | Q12: 2119.1555 | R12: 2376.8828 | S12: 1643.0182 | T12: 1078.8796 | U12: 1736.061 | V12: 703.52368 | W12: 1891.3129 | X12: 1017.2049 | Y12: 846.50165 | Z12: 760.38806 | AA12: 330.67609 | AB12: 998.98029 | AC12: 718.66589 | AD12: 550.88074 | AE12: 874.64532 | AF12: 943.42511 | AG12: 474.62381 | AH12: 465.29208 | AI12: 658.60364 | AJ12: 825.80573 | AK12: 516.06818 | AL12: 513.94666 | AM12: 1121.726 | AN12: 623.3186 | AO12: 1045.9186 | AP12: 909.04456 | AQ12: 629.57678 | AR12: 512.65283 | AS12: 732.48895 | AT12: 673.80469 | AU12: 662.14758 | AV12: 689.26306 | AW12: 393.34113 | AX12: 330.82068 | AY12: 2008.6798 | AZ12: 272.7283 | BA12: 810.83978 | BB12: 659.00269 | BC12: 730.65015 | BD12: 807.0199 | BE12: 564.32178 | BF12: 761.55853 | BG12: 1425.1573 | BH12: 1126.6716 | BI12: 784.21045 | BJ12: 561.19196 | BK12: 319.89163 | BL12: 888.57825 | BM12: 892.31573 | BN12: 789.77356 | BO12: 635.30176 | BP12: 1489.9764
B13: 1808 | C13: 753.07855 | D13: 1501.9034 | E13: 1429.0985 | F13: 766.48096 | G13: 664.57257 | H13: 612.42651 | I13: 633.56451 | J13: 735.73981 | K13: 761.7807 | L13: 1821.8213 | M13: 1671.5521 | N13: 1860.2451 | O13: 1579.0598 | P13: 3216.1636 | Q13: 2114.9575 | R13: 2228.1665 | S13: 1645.9065 | T13: 1021.4189 | U13: 1744.0194 | V13: 706.66162 | W13: 1906.6973 | X13: 1019.7103 | Y13: 846.49866 | Z13: 760.38531 | AA13: 333.36154 | AB13: 1002.4559 | AC13: 718.65112 | AD13: 536.42706 | AE13: 866.89417 | AF13: 920.07483 | AG13: 466.97525 | AH13: 467.74808 | AI13: 661.13898 | AJ13: 829.40228 | AK13: 518.3158 | AL13: 515.26276 | AM13: 1135.4432 | AN13: 626.52081 | AO13: 1051.0475 | AP13: 909.71021 | AQ13: 630.03613 | AR13: 513.02679 | AS13: 733.11432 | AT13: 674.29614 | AU13: 662.63055 | AV13: 689.76587 | AW13: 393.62802 | AX13: 331.06171 | AY13: 1758.5852 | AZ13: 267.81146 | BA13: 811.5274 | BB13: 659.56152 | BC13: 728.63019 | BD13: 807.01691 | BE13: 564.31976 | BF13: 764.73071 | BG13: 1421.7239 | BH13: 1123.5255 | BI13: 780.31805 | BJ13: 561.18738 | BK13: 319.88818 | BL13: 886.09698 | BM13: 892.27515 | BN13: 789.76526 | BO13: 635.29724 | BP13: 1483.9655
B14: 1809 | C14: 750.48035 | D14: 1491.6211 | E14: 1442.8024 | F14: 753.69727 | G14: 667.95264 | H14: 610.85687 | I14: 634.13196 | J14: 733.92975 | K14: 759.11084 | L14: 1863.1384 | M14: 1674.52 | N14: 1685.9724 | O14: 1544.6804 | P14: 3219.0193 | Q14: 2110.856 | R14: 2453.3862 | S14: 1648.8566 | T14: 974.36438 | U14: 1729.7075 | V14: 700.76001 | W14: 1916.1858 | X14: 1022.2437 | Y14: 846.51367 | Z14: 760.39911 | AA14: 336.16403 | AB14: 1005.9896 | AC14: 718.716 | AD14: 515.43732 | AE14: 853.63867 | AF14: 894.3476 | AG14: 459.48114 | AH14: 470.22696 | AI14: 663.71271 | AJ14: 833.10394 | AK14: 520.62872 | AL14: 516.60413 | AM14: 1149.3533 | AN14: 629.78021 | AO14: 1056.2872 | AP14: 910.3913 | AQ14: 630.50897 | AR14: 513.41211 | AS14: 733.75775 | AT14: 674.80225 | AU14: 663.12793 | AV14: 690.28357 | AW14: 393.92371 | AX14: 331.31021 | AY14: 1718.5267 | AZ14: 267.17279 | BA14: 812.25037 | BB14: 660.14917 | BC14: 726.63159 | BD14: 807.03143 | BE14: 564.33002 | BF14: 761.56934 | BG14: 1418.3607 | BH14: 1120.4601 | BI14: 776.5116 | BJ14: 561.20721 | BK14: 319.90515 | BL14: 883.6795 | BM14: 902.30518 | BN14: 789.80719 | BO14: 635.31964 | BP14: 1478.085
B15: 1810 | C15: 745.41565 | D15: 1465.7872 | E15: 1459.7648 | F15: 735.74408 | G15: 671.17035 | H15: 620.08386 | I15: 634.59717 | J15: 732.07812 | K15: 756.0777 | L15: 1944.3271 | M15: 1677.4043 | N15: 1594.3341 | O15: 1461.8051 | P15: 3122.3992 | Q15: 2103.4675 | R15: 2426.644 | S15: 1651.6001 | T15: 1053.2671 | U15: 1695.1818 | V15: 687.98639 | W15: 1930.609 | X15: 1024.7009 | Y15: 846.46112 | Z15: 760.35132 | AA15: 339.07037 | AB15: 1009.3681 | AC15: 718.48975 | AD15: 486.27182 | AE15: 820.1402 | AF15: 863.64996 | AG15: 446.19666 | AH15: 472.68146 | AI15: 666.18976 | AJ15: 836.48688 | AK15: 522.74335 | AL15: 517.86664 | AM15: 1163.3403 | AN15: 632.90564 | AO15: 1061.2592 | AP15: 911.00287 | AQ15: 630.9325 | AR15: 513.75653 | AS15: 734.32758 | AT15: 675.25555 | AU15: 663.57336 | AV15: 690.74725 | AW15: 394.1879 | AX15: 331.53275 | AY15: 1898.8364 | AZ15: 271.02698 | BA15: 812.84375 | BB15: 660.63104 | BC15: 724.57983 | BD15: 806.98047 | BE15: 564.29456 | BF15: 761.52179 | BG15: 1414.7725 | BH15: 1117.1351 | BI15: 772.47638 | BJ15: 561.138 | BK15: 319.84583 | BL15: 881.05713 | BM15: 900.93134 | BN15: 789.66034 | BO15: 635.24133 | BP15: 1471.8878
